[Pylon, Nexus, Gateway, Assimilator, CyberneticsCore] (50) {4154.588} -> 0.549
[Pylon, Gateway, Gateway, Pylon, Pylon, Pylon] (64) {2438.325} -> 0.481
[Pylon, Gateway, Assimilator, CyberneticsCore, Gateway, Pylon, SingularityCharge, Pylon] (53) {3194.574} -> 0.574
[Pylon, Gateway, Assimilator, CyberneticsCore, Pylon, SingularityCharge, Gateway] (56) {3925.81} -> 0.414
[Pylon, Gateway, Assimilator, CyberneticsCore, Pylon, SingularityCharge, Pylon] (136) {3782.225} -> 0.493
[Pylon, Gateway, Assimilator, Pylon, CyberneticsCore] (93) {3471.872} -> 0.489
[Pylon, Gateway, Pylon] (132) {3175.346} -> 0.541
[Pylon, Forge, Nexus, Gateway] (64) {4225.123} -> 0.492
[Pylon, Forge, Nexus, PhotonCannon] (56) {3945.632} -> 0.439
[Pylon, Forge, PhotonCannon, Nexus, Gateway] (71) {3517.778} -> 0.611
[Pylon, Forge, PhotonCannon, PhotonCannon] (67) {3669.794} -> 0.5
