[Pylon, Gateway, Gateway, Pylon, Assimilator, CyberneticsCore] (20) {1888.731} -> 0.5
[Pylon, Gateway, Gateway, Pylon, Assimilator, Pylon] (19) {1876.12} -> 0.48
[Pylon, Gateway, Gateway, Pylon, Pylon, Assimilator] (31) {2710.053} -> 0.342
[Pylon, Gateway, Gateway, Pylon, Pylon, Pylon, Pylon] (20) {2395.393} -> 0.643
[Pylon, Gateway, Assimilator, CyberneticsCore, Pylon, SingularityCharge, Gateway] (19) {4266.158} -> 0.421
[Pylon, Gateway, Assimilator, CyberneticsCore, Pylon, SingularityCharge, Pylon] (30) {3925.733} -> 0.567
[Pylon, Gateway, Assimilator, CyberneticsCore, Pylon, Gateway] (26) {1965.692} -> 0.462
[Pylon, Gateway, Assimilator, CyberneticsCore, Pylon, Pylon] (19) {3467.684} -> 0.579
[Pylon, Gateway, Assimilator, Pylon, Gateway] (21) {3326.857} -> 0.476
[Pylon, Gateway, Assimilator, Pylon, CyberneticsCore, Gateway, Pylon] (26) {2996.115} -> 0.538
[Pylon, Gateway, Assimilator, Pylon, CyberneticsCore, Pylon, SingularityCharge] (38) {4022.526} -> 0.316
[Pylon, Gateway, Assimilator, Pylon, Pylon] (24) {3641.708} -> 0.625
[Pylon, Gateway, Pylon, Assimilator, CyberneticsCore, Pylon] (19) {4039.737} -> 0.579
