[Pylon, Nexus, Gateway, Assimilator, CyberneticsCore, Gateway, Pylon] (25) {4204.885} -> 0.654
[Pylon, Nexus, Gateway, Assimilator, Pylon, CyberneticsCore, Gateway, SingularityCharge] (22) {3673.478} -> 0.652
[Pylon, Gateway, Assimilator, CyberneticsCore, Gateway, SingularityCharge, Pylon, Pylon] (33) {2684.353} -> 0.559
[Pylon, Gateway, Assimilator, CyberneticsCore, Gateway, Pylon, SingularityCharge, Pylon, Pylon] (32) {3144.485} -> 0.576
[Pylon, Gateway, Assimilator, CyberneticsCore, Pylon, SingularityCharge, Gateway, Pylon, Pylon] (27) {3872.321} -> 0.5
[Pylon, Gateway, Assimilator, CyberneticsCore, Pylon, SingularityCharge, Pylon, RoboticsFacility, Pylon] (27) {4262.821} -> 0.429
[Pylon, Gateway, Assimilator, CyberneticsCore, Pylon, SingularityCharge, Pylon, Nexus, Pylon] (21) {4198.091} -> 0.682
[Pylon, Gateway, Assimilator, CyberneticsCore, Pylon, SingularityCharge, Pylon, Gateway] (20) {3001.762} -> 0.571
[Pylon, Gateway, Assimilator, CyberneticsCore, Pylon, Gateway] (29) {2691.333} -> 0.6
[Pylon, Gateway, Assimilator, CyberneticsCore, Pylon, Pylon] (29) {3867.8} -> 0.5
[Pylon, Gateway, Assimilator, Pylon, CyberneticsCore] (31) {4113.71} -> 0.613
[Pylon, Gateway, Pylon] (27) {2855.556} -> 0.63
