[Pylon, Nexus, Forge] (25) {3610.846} -> 0.5
[Pylon, Gateway, Gateway, Pylon, Pylon, Pylon] (28) {2403.838} -> 0.486
[Pylon, Gateway, Forge] (28) {3081.586} -> 0.414
[Pylon, Gateway, Pylon, Nexus] (27) {3942.138} -> 0.621
[Pylon, Forge, Nexus, Gateway, PhotonCannon] (29) {3860.6} -> 0.533
[Pylon, Forge, Nexus, PhotonCannon, Gateway] (27) {3914.31} -> 0.517
[Pylon, Forge, Nexus, PhotonCannon, PhotonCannon] (25) {3650.852} -> 0.333
[Pylon, Forge, PhotonCannon, Nexus, Gateway, Assimilator, Pylon, CyberneticsCore] (22) {3848.739} -> 0.565
[Pylon, Forge, PhotonCannon, Nexus, Gateway, Pylon, Assimilator] (22) {3339.609} -> 0.652
[Pylon, Forge, PhotonCannon, PhotonCannon, Nexus, Gateway] (23) {3528.08} -> 0.68
[Pylon, Forge, PhotonCannon, Pylon] (32) {3628.879} -> 0.394
[Pylon, Forge, Pylon] (31) {3713.5} -> 0.406
