[Extractor, Hatchery] (22) {2368.318} -> 0.591
[SpawningPool, Extractor, MetabolicBoost, Hatchery, Hatchery] (43) {3563.333} -> 0.479
[SpawningPool, Extractor, Hatchery, Hatchery, Extractor] (22) {4339.44} -> 0.56
[SpawningPool, Hatchery, Extractor, Hatchery] (37) {3625.474} -> 0.632
[SpawningPool, Hatchery, CreepColony] (26) {3255.407} -> 0.556
[SpawningPool, Hatchery, Hatchery, Extractor, MetabolicBoost] (34) {4864.257} -> 0.486
[Hatchery, SpawningPool, Extractor, Hatchery, MetabolicBoost] (27) {3320.821} -> 0.607
[Hatchery, SpawningPool, CreepColony] (28) {3808.821} -> 0.536
[Hatchery, SpawningPool, Hatchery, Extractor, CreepColony] (22) {3550.217} -> 0.478
[Hatchery, SpawningPool, Hatchery, Extractor, MetabolicBoost] (40) {4450.341} -> 0.463
[Hatchery, SpawningPool, Hatchery, Extractor, Hatchery] (32) {4025.182} -> 0.424
[Hatchery, SpawningPool, Hatchery, Hatchery, Extractor] (25) {4912.8} -> 0.56
