[Pylon, Nexus, Gateway, Assimilator, CyberneticsCore] (65) {4427.508} -> 0.431
[Pylon, Nexus, Gateway, Assimilator, Pylon, CyberneticsCore, Gateway] (59) {3978.288} -> 0.559
[Pylon, Gateway, Gateway, Pylon, Pylon] (102) {2619.68} -> 0.505
[Pylon, Gateway, Assimilator, CyberneticsCore, Pylon, SingularityCharge, Pylon, RoboticsFacility] (78) {4736.288} -> 0.55
[Pylon, Gateway, Assimilator, CyberneticsCore, Pylon, SingularityCharge, Pylon, Nexus, Pylon] (58) {4840.9} -> 0.417
[Pylon, Gateway, Assimilator, CyberneticsCore, Pylon, Pylon] (78) {3824.65} -> 0.462
[Pylon, Gateway, Assimilator, Pylon, CyberneticsCore, Pylon] (97) {4028.092} -> 0.469
[Pylon, Gateway, Pylon, Assimilator, CyberneticsCore, Pylon] (60) {4468.767} -> 0.683
[Pylon, Forge, Nexus] (116) {4901.812} -> 0.444
[Pylon, Forge, PhotonCannon, Nexus] (86) {4589.08} -> 0.517
[Pylon, Forge, PhotonCannon, PhotonCannon] (67) {4235.279} -> 0.382
