[Pylon, Gateway, Gateway, Pylon, Pylon, Pylon] (17) {2068.105} -> 0.474
[Pylon, Gateway, Assimilator, CyberneticsCore, Pylon, SingularityCharge, Pylon] (27) {4512.167} -> 0.5
[Pylon, Gateway, Assimilator, CyberneticsCore, Pylon, Gateway] (17) {4010.368} -> 0.421
[Pylon, Gateway, Assimilator, CyberneticsCore, Pylon, Pylon] (28) {3764.433} -> 0.367
[Pylon, Gateway, Assimilator, Pylon, CyberneticsCore, Pylon, Nexus] (19) {4104.955} -> 0.364
[Pylon, Gateway, Assimilator, Pylon, CyberneticsCore, Pylon, SingularityCharge] (40) {3513.233} -> 0.512
[Pylon, Gateway, Assimilator, Pylon, Pylon] (15) {3273.059} -> 0.706
[Pylon, Gateway, Pylon, Assimilator, CyberneticsCore, Pylon, Nexus] (25) {5441.654} -> 0.769
[Pylon, Gateway, Pylon, Assimilator, CyberneticsCore, Pylon, SingularityCharge, Nexus] (17) {4674.167} -> 0.611
[Pylon, Gateway, Pylon, Assimilator, Pylon] (16) {3347.706} -> 0.588
