[Pylon, Nexus, Forge] (46) {4829.652} -> 0.5
[Pylon, Gateway, Gateway, Pylon, Pylon, Pylon] (32) {2446.73} -> 0.622
[Pylon, Gateway, Assimilator, Pylon, CyberneticsCore, Pylon, Stargate] (22) {4298.727} -> 0.409
[Pylon, Gateway, Pylon] (46) {3585.152} -> 0.543
[Pylon, Forge, Nexus, Gateway] (40) {5305.073} -> 0.439
[Pylon, Forge, Nexus, PhotonCannon] (39) {4291.75} -> 0.4
[Pylon, Forge, Nexus, Pylon] (22) {5218.522} -> 0.478
[Pylon, Forge, PhotonCannon, Nexus, Gateway, Pylon] (21) {4164.955} -> 0.591
[Pylon, Forge, PhotonCannon, Nexus, Pylon, Gateway] (20) {5345.762} -> 0.524
[Pylon, Forge, PhotonCannon, PhotonCannon, Nexus, Gateway] (31) {4850.545} -> 0.515
[Pylon, Forge, PhotonCannon, Pylon] (22) {4245.13} -> 0.739
[Pylon, Forge, Pylon, PhotonCannon] (20) {3857.143} -> 0.571
