[Pylon, Gateway, Gateway] (1) {1142} -> 1
[Pylon, Gateway, Assimilator, Gateway, Pylon, Pylon, Assimilator, Pylon, Pylon, CyberneticsCore, Gateway, RoboticsFacility, Pylon, Observatory, Pylon, Gateway, ShieldBattery, Forge, CitadelofAdun] (2) {987} -> 0.5
[Pylon, Gateway, Assimilator, CyberneticsCore, Pylon, SingularityCharge] (2) {2579} -> 0
[Pylon, Gateway, Assimilator, CyberneticsCore, Pylon, Gateway] (1) {3718} -> 1
[Pylon, Gateway, Assimilator, Assimilator] (1) {1404} -> 1
[Pylon, Gateway, Assimilator, Pylon] (1) {1790} -> 0
[Pylon, Forge, Nexus] (3) {3614.333} -> 0
[Pylon, Forge, PhotonCannon, Nexus] (1) {2441} -> 0
[Pylon, Forge, PhotonCannon, Pylon] (1) {1366} -> 1
