[Pylon, Gateway, Gateway, Pylon, Pylon, Assimilator, CyberneticsCore, Pylon, Gateway, CitadelofAdun, Pylon, Forge, TemplarArchives, PhotonCannon, Pylon, PhotonCannon, Pylon, ProtossGroundWeapons, Gateway, PhotonCannon, PhotonCannon, PhotonCannon, PhotonCannon, PhotonCannon] (2) {1458} -> 0.5
[Pylon, Gateway, Assimilator, Gateway, Pylon, Pylon, Assimilator, Pylon, Pylon, CyberneticsCore, Gateway, RoboticsFacility, Pylon, Observatory, Pylon, Gateway, ShieldBattery, Forge, CitadelofAdun] (2) {987} -> 0.5
[Pylon, Gateway, Assimilator, Pylon, CyberneticsCore, RoboticsFacility] (1) {1100} -> 1
[Pylon, Gateway, Assimilator, Pylon, CyberneticsCore, Pylon] (1) {1790} -> 0
