[SupplyDepot, Barracks, Refinery, Factory, SupplyDepot, Factory, CommandCenter] (1) {3466} -> 1
[SupplyDepot, Barracks, Refinery, Factory, SupplyDepot, Factory, MachineShop] (1) {1941} -> 0
[SupplyDepot, Barracks, Refinery, SupplyDepot] (1) {5261} -> 0
[SupplyDepot, Refinery] (2) {5646.5} -> 0
