[Extractor, SpawningPool, Hatchery, Hatchery, HydraliskDen] (1) {1827} -> 0
[Extractor, SpawningPool, Hatchery, Hatchery, EvolutionChamber] (1) {3050} -> 1
[SpawningPool] (1) {3502} -> 0
[Hatchery, SpawningPool, Extractor, CreepColony] (1) {1532} -> 1
[Hatchery, SpawningPool, Extractor, MetabolicBoost] (1) {2245} -> 0
[Hatchery, SpawningPool, CreepColony] (1) {5505} -> 0
[Hatchery, SpawningPool, Hatchery] (3) {3336.667} -> 0
