[Extractor, SpawningPool, Hatchery, Hatchery, HydraliskDen] (1) {1827} -> 0
[Extractor, SpawningPool, Hatchery, Hatchery, EvolutionChamber] (1) {3050} -> 1
[SpawningPool] (1) {3502} -> 0
[Hatchery, SpawningPool, Extractor] (1) {1532} -> 1
[Hatchery, SpawningPool, CreepColony] (1) {5505} -> 0
