[Pylon, Gateway, Gateway, Pylon, Assimilator] (15) {2311.333} -> 0.4
[Pylon, Gateway, Gateway, Pylon, Pylon, Assimilator] (16) {3292.938} -> 0.438
[Pylon, Gateway, Assimilator, CyberneticsCore, Pylon, SingularityCharge, Pylon] (20) {3509.75} -> 0.75
[Pylon, Gateway, Assimilator, CyberneticsCore, Pylon, Gateway] (22) {3227.318} -> 0.318
[Pylon, Gateway, Assimilator, CyberneticsCore, Pylon, Pylon] (26) {2844.5} -> 0.423
[Pylon, Gateway, Assimilator, Pylon, CyberneticsCore, Gateway, Pylon] (21) {2544.714} -> 0.429
[Pylon, Gateway, Assimilator, Pylon, CyberneticsCore, Pylon, RoboticsFacility] (15) {3699.333} -> 0.6
[Pylon, Gateway, Assimilator, Pylon, CyberneticsCore, Pylon, SingularityCharge, RoboticsFacility, Pylon] (17) {3421} -> 0.529
[Pylon, Gateway, Assimilator, Pylon, CyberneticsCore, Pylon, SingularityCharge, Gateway] (17) {2598.882} -> 0.353
[Pylon, Gateway, Assimilator, Pylon, Pylon, CyberneticsCore] (18) {2726.611} -> 0.5
[Pylon, Gateway, Pylon, Assimilator, CyberneticsCore, Pylon, SingularityCharge] (28) {3689.036} -> 0.607
