[Pylon, Nexus, Gateway, Assimilator] (29) {3430.586} -> 0.483
[Pylon, Gateway, Gateway, Pylon] (24) {2589.333} -> 0.5
[Pylon, Gateway, Assimilator, CyberneticsCore, Pylon, RoboticsFacility, Pylon] (34) {4105.189} -> 0.514
[Pylon, Gateway, Assimilator, CyberneticsCore, Pylon, SingularityCharge, Gateway, Pylon] (42) {3086.489} -> 0.34
[Pylon, Gateway, Assimilator, CyberneticsCore, Pylon, SingularityCharge, Pylon, RoboticsFacility, Gateway, Pylon, Observatory] (22) {4085.815} -> 0.519
[Pylon, Gateway, Assimilator, CyberneticsCore, Pylon, SingularityCharge, Pylon, RoboticsFacility, Pylon] (76) {4290.407} -> 0.519
[Pylon, Gateway, Assimilator, CyberneticsCore, Pylon, SingularityCharge, Pylon, Nexus, Pylon] (37) {3960.293} -> 0.61
[Pylon, Gateway, Assimilator, CyberneticsCore, Pylon, SingularityCharge, Pylon, Gateway] (38) {3562.548} -> 0.429
[Pylon, Gateway, Assimilator, CyberneticsCore, Pylon, SingularityCharge, Pylon, Pylon] (25) {4023.31} -> 0.69
[Pylon, Gateway, Assimilator, CyberneticsCore, Pylon, Gateway] (28) {3060.194} -> 0.387
[Pylon, Gateway, Assimilator, CyberneticsCore, Pylon, CitadelofAdun] (34) {3580.676} -> 0.486
[Pylon, Gateway, Assimilator, CyberneticsCore, Pylon, Pylon] (40) {3112.326} -> 0.465
[Pylon, Gateway, Assimilator, Assimilator] (23) {3177.846} -> 0.654
[Pylon, Gateway, Assimilator, Pylon, CyberneticsCore, Pylon] (37) {3278.925} -> 0.425
