[Pylon, Nexus, Forge] (44) {3231.844} -> 0.533
[Pylon, Gateway, Gateway, Pylon, Pylon, Pylon] (35) {1922.512} -> 0.488
[Pylon, Gateway, Assimilator, Pylon, CyberneticsCore, Pylon, Stargate] (32) {3361.583} -> 0.583
[Pylon, Gateway, Assimilator, Pylon, CyberneticsCore, Pylon, CitadelofAdun] (27) {3216.29} -> 0.516
[Pylon, Gateway, Pylon] (35) {2617.189} -> 0.405
[Pylon, Forge, Nexus, Gateway, Pylon] (29) {3575.226} -> 0.419
[Pylon, Forge, Nexus, PhotonCannon, PhotonCannon] (28) {3971.8} -> 0.467
[Pylon, Forge, PhotonCannon, Nexus, Gateway, Pylon, Assimilator] (24) {3425.538} -> 0.615
[Pylon, Forge, PhotonCannon, PhotonCannon, Nexus] (38) {3434.805} -> 0.39
[Pylon, Forge, PhotonCannon, PhotonCannon, Pylon] (23) {2651.423} -> 0.577
[Pylon, Forge, PhotonCannon, Pylon] (28) {3254.3} -> 0.533
[Pylon, Forge, Pylon] (29) {3489.774} -> 0.452
