[Extractor, Hatchery, SpawningPool] (54) {3167.255} -> 0.4
[SpawningPool, Extractor, MetabolicBoost, Hatchery, Hatchery] (81) {3184.721} -> 0.514
[SpawningPool, Extractor, Hatchery, MetabolicBoost] (83) {2714.551} -> 0.48
[SpawningPool, Hatchery, Extractor] (97) {2829.972} -> 0.533
[SpawningPool, Hatchery, Hatchery, Extractor] (122) {3435.556} -> 0.489
[Hatchery, SpawningPool, Extractor, CreepColony] (68) {2738.893} -> 0.48
[Hatchery, SpawningPool, Extractor, MetabolicBoost] (94) {2580.554} -> 0.396
[Hatchery, SpawningPool, Extractor, Hatchery] (99) {3125.349} -> 0.491
[Hatchery, SpawningPool, Hatchery, Extractor, Extractor] (92) {4280.47} -> 0.4
[Hatchery, SpawningPool, Hatchery, Extractor, CreepColony, Extractor] (56) {3442.227} -> 0.394
[Hatchery, SpawningPool, Hatchery, Extractor, MetabolicBoost] (65) {3124.959} -> 0.479
[Hatchery, SpawningPool, Hatchery, Hatchery] (56) {4082.339} -> 0.629
