[Extractor, Hatchery] (23) {3134.417} -> 0.375
[SpawningPool, Extractor, MetabolicBoost, Hatchery, Hatchery] (70) {3783.679} -> 0.506
[SpawningPool, Extractor, Hatchery, MetabolicBoost, Hatchery] (23) {2560.267} -> 0.467
[SpawningPool, Hatchery, Extractor, Hatchery] (35) {3319.95} -> 0.575
[SpawningPool, Hatchery, Hatchery, Extractor, MetabolicBoost] (28) {3469.588} -> 0.529
[SpawningPool, Hatchery, Hatchery, Hatchery, Extractor] (28) {4173.559} -> 0.324
[Hatchery, SpawningPool, Extractor, Hatchery] (49) {3019.745} -> 0.529
[Hatchery, SpawningPool, Hatchery, Extractor, HydraliskDen] (28) {3292.161} -> 0.548
[Hatchery, SpawningPool, Hatchery, Extractor, Hatchery] (25) {4111.536} -> 0.607
[Hatchery, SpawningPool, Hatchery, Hatchery, Extractor] (39) {4187.333} -> 0.69
