[Extractor, SpawningPool, Hatchery, Spire] (14) {2678.071} -> 0.5
[Extractor, SpawningPool, Hatchery, MetabolicBoost, Spire] (13) {2657.786} -> 0.571
[SpawningPool, Extractor, Spire] (13) {2133.385} -> 0.385
[SpawningPool, Extractor, CreepColony] (19) {2950.105} -> 0.421
[SpawningPool, Extractor, MetabolicBoost, Spire, CreepColony] (27) {2061.93} -> 0.628
[SpawningPool, Extractor, MetabolicBoost, Spire, Hatchery] (28) {2194.727} -> 0.545
[SpawningPool, Extractor, MetabolicBoost, CreepColony, Spire] (14) {1518.35} -> 0.55
[SpawningPool, Extractor, MetabolicBoost, Hatchery] (13) {1684.647} -> 0.471
[SpawningPool, Extractor, Hatchery, Spire] (21) {2556.571} -> 0.571
[SpawningPool, Extractor, Hatchery, MetabolicBoost, Spire] (42) {2479.592} -> 0.571
[SpawningPool, Hatchery, Extractor] (16) {2210.5} -> 0.688
[Hatchery, SpawningPool, Extractor, CreepColony] (25) {2243.074} -> 0.296
[Hatchery, SpawningPool, Extractor, MetabolicBoost, Spire] (21) {2371.31} -> 0.517
