[Pylon, Nexus, Gateway] (570) {3556.017} -> 0.503
[Pylon, Gateway, Gateway, Pylon, Pylon] (809) {2598.418} -> 0.504
[Pylon, Gateway, Assimilator, CyberneticsCore, Pylon, SingularityCharge, Pylon, RoboticsFacility] (576) {3841.989} -> 0.472
[Pylon, Gateway, Assimilator, CyberneticsCore, Pylon, SingularityCharge, Pylon, Nexus] (580) {3913.584} -> 0.479
[Pylon, Gateway, Assimilator, Pylon, CyberneticsCore, Pylon, SingularityCharge] (434) {3097.334} -> 0.531
[Pylon, Gateway, Pylon] (864) {3066.295} -> 0.529
[Pylon, Forge, Nexus, Gateway] (494) {3539.376} -> 0.485
[Pylon, Forge, Nexus, PhotonCannon] (625) {3265.598} -> 0.486
[Pylon, Forge, PhotonCannon, Nexus, Gateway] (674) {3548.082} -> 0.463
[Pylon, Forge, PhotonCannon, PhotonCannon] (594) {2998.894} -> 0.441
[Pylon, Forge, Pylon] (445) {3046.868} -> 0.51
