[Pylon, Nexus, Gateway, Gateway] (128) {2387.046} -> 0.577
[Pylon, Gateway, Gateway, Pylon, Pylon, Pylon] (196) {2355.108} -> 0.554
[Pylon, Gateway, Assimilator, CyberneticsCore, Pylon, SingularityCharge, Pylon, RoboticsFacility] (136) {3043.255} -> 0.49
[Pylon, Gateway, Assimilator, CyberneticsCore, Pylon, Gateway] (148) {2510.15} -> 0.444
[Pylon, Gateway, Assimilator, CyberneticsCore, Pylon, CitadelofAdun] (141) {2693.379} -> 0.503
[Pylon, Gateway, Assimilator, CyberneticsCore, Pylon, Pylon] (150) {2580.519} -> 0.389
[Pylon, Gateway, Assimilator, Pylon, CyberneticsCore, Gateway, Pylon] (145) {2833.368} -> 0.503
[Pylon, Gateway, Assimilator, Pylon, CyberneticsCore, Pylon, RoboticsFacility] (147) {2774.036} -> 0.536
[Pylon, Gateway, Assimilator, Pylon, CyberneticsCore, Pylon, SingularityCharge, RoboticsFacility, Pylon, Gateway] (135) {3083.182} -> 0.513
[Pylon, Gateway, Assimilator, Pylon, CyberneticsCore, Pylon, SingularityCharge, Pylon] (162) {3180.818} -> 0.591
[Pylon, Gateway, Assimilator, Pylon, Pylon, CyberneticsCore] (147) {2845.055} -> 0.503
[Pylon, Gateway, Pylon, Assimilator, CyberneticsCore] (163) {2973.375} -> 0.524
