[Pylon, Nexus, Gateway, Assimilator, CyberneticsCore] (175) {3806.367} -> 0.565
[Pylon, Gateway, Assimilator, CyberneticsCore, Gateway] (159) {2812.978} -> 0.425
[Pylon, Gateway, Assimilator, CyberneticsCore, Pylon, Gateway] (177) {2710.654} -> 0.463
[Pylon, Gateway, Assimilator, CyberneticsCore, Pylon, CitadelofAdun] (196) {2800.408} -> 0.562
[Pylon, Gateway, Assimilator, CyberneticsCore, Pylon, Pylon] (268) {2965.538} -> 0.459
[Pylon, Gateway, Assimilator, CyberneticsCore, Pylon, RoboticsFacility] (156) {3227.617} -> 0.544
[Pylon, Gateway, Assimilator, CyberneticsCore, Pylon, SingularityCharge, Nexus, Gateway] (152) {3337.33} -> 0.5
[Pylon, Gateway, Assimilator, CyberneticsCore, Pylon, SingularityCharge, Gateway, Pylon, Pylon] (156) {3077.139} -> 0.47
[Pylon, Gateway, Assimilator, CyberneticsCore, Pylon, SingularityCharge, Pylon, RoboticsFacility, Pylon] (318) {3929.448} -> 0.5
[Pylon, Gateway, Assimilator, CyberneticsCore, Pylon, SingularityCharge, Pylon, Nexus, Pylon] (261) {3800.678} -> 0.498
[Pylon, Gateway, Assimilator, CyberneticsCore, Pylon, SingularityCharge, Pylon, Gateway] (273) {3264.487} -> 0.497
[Pylon, Gateway, Assimilator, CyberneticsCore, Pylon, SingularityCharge, Pylon, Pylon] (161) {3302.189} -> 0.529
[Pylon, Gateway, Assimilator, Pylon, CyberneticsCore, Pylon] (177) {3141.278} -> 0.571
[Pylon, Gateway, Pylon] (200) {2960.845} -> 0.534
