[Pylon, Nexus, Forge] (260) {3310.407} -> 0.521
[Pylon, Gateway, Gateway, Pylon, Pylon, Pylon] (262) {2623.733} -> 0.564
[Pylon, Gateway, Assimilator, CyberneticsCore, Pylon] (202) {3107.79} -> 0.463
[Pylon, Gateway, Assimilator, Pylon, CyberneticsCore, Pylon] (353) {3239.572} -> 0.5
[Pylon, Gateway, Pylon] (452) {3164.694} -> 0.531
[Pylon, Forge, Nexus, Gateway] (493) {3545.822} -> 0.485
[Pylon, Forge, Nexus, PhotonCannon, Gateway] (300) {3725.578} -> 0.494
[Pylon, Forge, Nexus, PhotonCannon, PhotonCannon] (230) {2791.216} -> 0.472
[Pylon, Forge, PhotonCannon, Nexus, Gateway, Assimilator, Pylon] (222) {3294.823} -> 0.449
[Pylon, Forge, PhotonCannon, Nexus, Gateway, Pylon, Assimilator, CyberneticsCore] (201) {3508.305} -> 0.525
[Pylon, Forge, PhotonCannon, PhotonCannon, Nexus, Gateway] (312) {3225.042} -> 0.464
[Pylon, Forge, PhotonCannon, Pylon] (218) {3072.923} -> 0.502
[Pylon, Forge, Pylon, PhotonCannon] (265) {3120.256} -> 0.488
