[Barracks, SupplyDepot, SupplyDepot, Bunker] (160) {2910.707} -> 0.479
[SupplyDepot, Barracks, Barracks, SupplyDepot, Refinery] (135) {3043.852} -> 0.544
[SupplyDepot, Barracks, CommandCenter, SupplyDepot, Barracks] (226) {4009.213} -> 0.545
[SupplyDepot, Barracks, CommandCenter, SupplyDepot, Refinery] (152) {3893.211} -> 0.46
[SupplyDepot, Barracks, SupplyDepot, CommandCenter, Barracks, SupplyDepot, Refinery, Academy] (161) {4081.277} -> 0.553
[SupplyDepot, Barracks, SupplyDepot, CommandCenter, Barracks, Refinery, Academy] (188) {4060.617} -> 0.603
[SupplyDepot, Barracks, SupplyDepot, CommandCenter, SupplyDepot, Barracks, Refinery, Academy] (161) {3975.031} -> 0.55
[SupplyDepot, Barracks, SupplyDepot, CommandCenter, SupplyDepot, Refinery] (226) {3919.171} -> 0.544
[SupplyDepot, Barracks, SupplyDepot, CommandCenter, Refinery, SupplyDepot] (146) {3739.847} -> 0.506
[SupplyDepot, Barracks, SupplyDepot, CommandCenter, Bunker] (151) {3243.789} -> 0.514
[SupplyDepot, Barracks, SupplyDepot, Bunker] (171) {2882.574} -> 0.537
[SupplyDepot, Barracks, Refinery, Factory, SupplyDepot] (146) {3360.052} -> 0.455
[SupplyDepot, Barracks, Refinery, SupplyDepot, Factory, SupplyDepot] (142) {3215.058} -> 0.474
