[Extractor, Hatchery, SpawningPool] (163) {3377.025} -> 0.528
[SpawningPool, Extractor, MetabolicBoost, Hatchery] (189) {2134.571} -> 0.5
[SpawningPool, Extractor, Hatchery, Hatchery, Extractor] (154) {2653.241} -> 0.538
[SpawningPool, Hatchery, Extractor] (234) {2778.138} -> 0.504
[SpawningPool, Hatchery, Hatchery, Extractor] (232) {3366.382} -> 0.532
[Hatchery, SpawningPool, Extractor, CreepColony] (224) {3490.524} -> 0.444
[Hatchery, SpawningPool, Extractor, MetabolicBoost, Spire] (149) {3276.916} -> 0.484
[Hatchery, SpawningPool, Extractor, Hatchery] (251) {3219.412} -> 0.437
[Hatchery, SpawningPool, Hatchery, Extractor, Extractor, CreepColony] (135) {3525.432} -> 0.528
[Hatchery, SpawningPool, Hatchery, Extractor, Extractor, MetabolicBoost, Spire] (149) {3531.586} -> 0.466
[Hatchery, SpawningPool, Hatchery, Extractor, CreepColony, Extractor] (236) {3544.876} -> 0.481
[Hatchery, SpawningPool, Hatchery, Extractor, CreepColony, MetabolicBoost] (133) {3208.528} -> 0.417
[Hatchery, SpawningPool, Hatchery, Extractor, MetabolicBoost, Extractor] (197) {3738.846} -> 0.473
