[Extractor, SpawningPool, Hatchery, MetabolicBoost] (128) {2570} -> 0.492
[SpawningPool, Extractor, Spire] (120) {2469.846} -> 0.515
[SpawningPool, Extractor, MetabolicBoost, Spire] (679) {2255.232} -> 0.591
[SpawningPool, Extractor, MetabolicBoost, Spire, CreepColony, CreepColony] (131) {1862.965} -> 0.617
[SpawningPool, Extractor, MetabolicBoost, Spire, Hatchery] (209) {1963.755} -> 0.654
[SpawningPool, Extractor, MetabolicBoost, CreepColony] (143) {1690.035} -> 0.602
[SpawningPool, Extractor, Hatchery, MetabolicBoost, Spire] (379) {2191.719} -> 0.486
[SpawningPool, Extractor, Hatchery, MetabolicBoost, CreepColony] (142) {2136.127} -> 0.381
[Hatchery, SpawningPool, Extractor, CreepColony] (257) {2284.35} -> 0.361
[Hatchery, SpawningPool, Extractor, MetabolicBoost, Spire] (321) {2238.989} -> 0.524
