[Pylon, Gateway, Gateway, Assimilator] (1) {1254} -> 0
[Pylon, Gateway, Gateway, Pylon, Assimilator, CyberneticsCore] (1) {2168} -> 0
[Pylon, Gateway, Gateway, Pylon, Assimilator, Pylon] (2) {2165} -> 1
[Pylon, Gateway, Assimilator, Gateway] (1) {2487} -> 1
[Pylon, Gateway, Assimilator, CyberneticsCore, Pylon, SingularityCharge] (1) {2843} -> 1
[Pylon, Gateway, Assimilator, CyberneticsCore, Pylon, Gateway] (1) {4652} -> 0
[Pylon, Gateway, Assimilator, Pylon] (1) {1588} -> 0
