[Pylon, Nexus] (101) {2936.515} -> 0.455
[Pylon, Gateway, Gateway, Pylon, Assimilator, Pylon, CyberneticsCore] (97) {3038.77} -> 0.44
[Pylon, Gateway, Gateway, Pylon, Pylon, Assimilator] (185) {2890.767} -> 0.435
[Pylon, Gateway, Gateway, Pylon, Pylon, Pylon] (146) {2762.669} -> 0.461
[Pylon, Gateway, Assimilator, CyberneticsCore, Pylon, RoboticsFacility, Pylon] (143) {3144.589} -> 0.438
[Pylon, Gateway, Assimilator, CyberneticsCore, Pylon, SingularityCharge, Gateway] (93) {3793.333} -> 0.469
[Pylon, Gateway, Assimilator, CyberneticsCore, Pylon, SingularityCharge, Pylon, RoboticsFacility] (129) {3845} -> 0.545
[Pylon, Gateway, Assimilator, CyberneticsCore, Pylon, SingularityCharge, Pylon, Gateway] (102) {3875.714} -> 0.552
[Pylon, Gateway, Assimilator, CyberneticsCore, Pylon, Gateway] (95) {3253.898} -> 0.49
[Pylon, Gateway, Assimilator, CyberneticsCore, Pylon, Pylon] (134) {3198.65} -> 0.54
[Pylon, Gateway, Assimilator, Pylon, CyberneticsCore, Pylon] (301) {2963.752} -> 0.419
[Pylon, Gateway, Pylon, Assimilator] (136) {2945.073} -> 0.555
