[Pylon, Gateway, Gateway, Pylon, Assimilator, Pylon, CyberneticsCore, Pylon] (28) {2608.1} -> 0.467
[Pylon, Gateway, Gateway, Pylon, Pylon, Assimilator, CyberneticsCore] (26) {2638.207} -> 0.379
[Pylon, Gateway, Gateway, Pylon, Pylon, Assimilator, Pylon] (33) {2757.528} -> 0.472
[Pylon, Gateway, Gateway, Pylon, Pylon, Pylon] (26) {2260.862} -> 0.552
[Pylon, Gateway, Assimilator, CyberneticsCore, Pylon, Gateway] (31) {2219.667} -> 0.333
[Pylon, Gateway, Assimilator, Pylon, Gateway] (37) {2486.282} -> 0.564
[Pylon, Gateway, Assimilator, Pylon, CyberneticsCore, Gateway, Pylon] (50) {2668.846} -> 0.462
[Pylon, Gateway, Assimilator, Pylon, CyberneticsCore, Pylon, RoboticsFacility] (42) {2594.227} -> 0.568
[Pylon, Gateway, Assimilator, Pylon, CyberneticsCore, Pylon, SingularityCharge] (42) {2784.432} -> 0.477
[Pylon, Gateway, Assimilator, Pylon, CyberneticsCore, Pylon, Gateway, SingularityCharge] (28) {2738.967} -> 0.6
[Pylon, Gateway, Assimilator, Pylon, Pylon, CyberneticsCore] (40) {3035.714} -> 0.667
[Pylon, Gateway, Pylon, Assimilator, CyberneticsCore] (27) {2927.786} -> 0.607
