[Pylon, Gateway, Assimilator, CyberneticsCore, Pylon, RoboticsFacility, Pylon, SingularityCharge] (62) {3187.016} -> 0.492
[Pylon, Gateway, Assimilator, CyberneticsCore, Pylon, SingularityCharge, Gateway, Pylon, Pylon] (48) {3650.449} -> 0.551
[Pylon, Gateway, Assimilator, CyberneticsCore, Pylon, SingularityCharge, Pylon, RoboticsFacility, Gateway, Pylon] (47) {4136.917} -> 0.5
[Pylon, Gateway, Assimilator, CyberneticsCore, Pylon, SingularityCharge, Pylon, RoboticsFacility, Pylon] (66) {3820.299} -> 0.582
[Pylon, Gateway, Assimilator, CyberneticsCore, Pylon, SingularityCharge, Pylon, Gateway, Pylon] (61) {3802.145} -> 0.565
[Pylon, Gateway, Assimilator, CyberneticsCore, Pylon, SingularityCharge, Pylon, Pylon] (39) {3324} -> 0.575
[Pylon, Gateway, Assimilator, CyberneticsCore, Pylon, Gateway, Pylon] (38) {3671.718} -> 0.615
[Pylon, Gateway, Assimilator, CyberneticsCore, Pylon, Pylon, SingularityCharge] (39) {3465.925} -> 0.6
[Pylon, Gateway, Assimilator, Assimilator, CyberneticsCore] (34) {3100.118} -> 0.5
[Pylon, Gateway, Assimilator, Pylon, CyberneticsCore, Pylon] (35) {3050.571} -> 0.514
