[Pylon, Nexus, Forge] (61) {2757.098} -> 0.492
[Pylon, Gateway, Gateway, Pylon, Assimilator, CyberneticsCore, Pylon] (40) {3186.619} -> 0.31
[Pylon, Gateway, Gateway, Pylon, Assimilator, Pylon, CyberneticsCore, Pylon] (41) {2837.814} -> 0.395
[Pylon, Gateway, Gateway, Pylon, Pylon, Assimilator, CyberneticsCore, Pylon] (46) {2810.673} -> 0.442
[Pylon, Gateway, Gateway, Pylon, Pylon, Assimilator, Pylon, CyberneticsCore] (48) {2997.291} -> 0.455
[Pylon, Gateway, Gateway, Pylon, Pylon, Pylon, Assimilator] (68) {2853.588} -> 0.459
[Pylon, Gateway, Assimilator, CyberneticsCore, Pylon, Stargate] (45) {3438.348} -> 0.348
[Pylon, Gateway, Assimilator, Pylon, CyberneticsCore, Pylon, Stargate] (77) {3012.936} -> 0.5
[Pylon, Gateway, Assimilator, Pylon, CyberneticsCore, Pylon, CitadelofAdun] (43) {2879.023} -> 0.273
[Pylon, Gateway, Assimilator, Pylon, Forge] (45) {3174.467} -> 0.444
[Pylon, Gateway, Pylon, Assimilator, CyberneticsCore] (42) {2720.093} -> 0.442
[Pylon, Forge] (62) {2759.935} -> 0.403
