[SupplyDepot, Barracks, Refinery, Factory, SupplyDepot, Factory, Armory] (16) {4055.75} -> 0.562
[SupplyDepot, Barracks, Refinery, Factory, SupplyDepot, Factory, SupplyDepot, MachineShop] (20) {4059.7} -> 0.7
[SupplyDepot, Barracks, Refinery, Factory, SupplyDepot, Factory, MachineShop, Armory, SupplyDepot] (14) {4790.786} -> 0.429
[SupplyDepot, Barracks, Refinery, Factory, SupplyDepot, Factory, MachineShop, SupplyDepot, SpiderMines, SupplyDepot] (34) {3698.029} -> 0.412
[SupplyDepot, Barracks, Refinery, Factory, SupplyDepot, Factory, MachineShop, SupplyDepot, IonThrusters, SupplyDepot] (15) {2788.933} -> 0.667
[SupplyDepot, Barracks, Refinery, SupplyDepot, Factory, Factory, Armory] (15) {4231.8} -> 0.6
[SupplyDepot, Barracks, Refinery, SupplyDepot, Factory, Factory, SupplyDepot, MachineShop] (54) {3686.722} -> 0.519
[SupplyDepot, Barracks, Refinery, SupplyDepot, Factory, Factory, MachineShop, SupplyDepot, IonThrusters] (19) {3452.105} -> 0.368
[SupplyDepot, Refinery, Barracks, Factory, SupplyDepot] (17) {4896.176} -> 0.588
