[Extractor, SpawningPool, Hatchery, MetabolicBoost, Spire] (113) {2580.239} -> 0.487
[Extractor, Hatchery, SpawningPool, Extractor, CreepColony] (108) {3083.216} -> 0.486
[SpawningPool, Extractor, MetabolicBoost] (133) {2435.515} -> 0.47
[SpawningPool, Extractor, Hatchery] (144) {2836.703} -> 0.579
[SpawningPool, Hatchery, Hatchery] (137) {3585.978} -> 0.623
[Hatchery, SpawningPool, Extractor, Extractor] (124) {3872.763} -> 0.534
[Hatchery, SpawningPool, Extractor, CreepColony, HydraliskDen] (141) {4164.783} -> 0.5
[Hatchery, SpawningPool, Extractor, CreepColony, CreepColony] (174) {3596.573} -> 0.416
[Hatchery, SpawningPool, Extractor, MetabolicBoost] (136) {3062.231} -> 0.538
[Hatchery, SpawningPool, Extractor, Hatchery] (242) {3562.434} -> 0.526
[Hatchery, SpawningPool, CreepColony] (163) {3467.612} -> 0.509
[Hatchery, SpawningPool, Hatchery, Extractor, CreepColony] (149) {4205.89} -> 0.545
[Hatchery, SpawningPool, Hatchery, CreepColony] (105) {3151.578} -> 0.596
