[Extractor, Hatchery, SpawningPool, Extractor, CreepColony] (59) {3218.831} -> 0.407
[SpawningPool, Extractor] (71) {3119.208} -> 0.361
[SpawningPool, Hatchery] (50) {3288.137} -> 0.471
[Hatchery, SpawningPool, Extractor, Extractor, CreepColony] (50) {3621.296} -> 0.593
[Hatchery, SpawningPool, Extractor, CreepColony, HydraliskDen, CreepColony, LurkerAspect] (38) {4109.378} -> 0.444
[Hatchery, SpawningPool, Extractor, CreepColony, CreepColony, HydraliskDen] (55) {3871.081} -> 0.468
[Hatchery, SpawningPool, Extractor, CreepColony, CreepColony, CreepColony] (40) {3367.809} -> 0.277
[Hatchery, SpawningPool, Extractor, CreepColony, MetabolicBoost, HydraliskDen] (35) {3459.326} -> 0.326
[Hatchery, SpawningPool, Extractor, MetabolicBoost] (38) {3799.405} -> 0.524
[Hatchery, SpawningPool, Extractor, Hatchery, CreepColony] (50) {3897.278} -> 0.444
[Hatchery, SpawningPool, CreepColony] (53) {3662.056} -> 0.426
[Hatchery, SpawningPool, Hatchery, Extractor, CreepColony, CreepColony] (47) {4796.271} -> 0.479
[Hatchery, SpawningPool, Hatchery, CreepColony] (38) {3390.282} -> 0.564
