[Pylon, Nexus, Gateway, Assimilator, Pylon, CyberneticsCore] (11) {2748.273} -> 0.455
[Pylon, Nexus, Forge] (12) {3349.083} -> 0.5
[Pylon, Gateway, Gateway, Pylon, Pylon] (15) {2777.467} -> 0.733
[Pylon, Gateway, Assimilator, CyberneticsCore, Pylon, RoboticsFacility, Pylon] (11) {3130.545} -> 0.636
[Pylon, Gateway, Assimilator, CyberneticsCore, Pylon, SingularityCharge, Pylon, RoboticsFacility, Pylon] (12) {3622.917} -> 0.417
[Pylon, Gateway, Assimilator, CyberneticsCore, Pylon, SingularityCharge, Pylon, Nexus, Pylon] (13) {4283.308} -> 0.538
[Pylon, Gateway, Assimilator, Pylon, CyberneticsCore, Pylon, RoboticsFacility] (11) {3122.364} -> 0.727
[Pylon, Gateway, Assimilator, Pylon, CyberneticsCore, Pylon, SingularityCharge] (15) {3485.133} -> 0.4
[Pylon, Forge, Nexus, Gateway] (11) {3444.727} -> 0.909
[Pylon, Forge, Nexus, PhotonCannon, Gateway, Pylon] (11) {3605.545} -> 0.818
[Pylon, Forge, PhotonCannon, Nexus, Gateway] (10) {2240.4} -> 0.5
[Pylon, Forge, PhotonCannon, PhotonCannon, Nexus] (15) {3587.467} -> 0.733
