[Pylon, Gateway, Gateway, Pylon, Assimilator] (6) {3242} -> 0.167
[Pylon, Gateway, Gateway, Pylon, Pylon, Assimilator, CyberneticsCore, Pylon] (5) {2739.6} -> 0.6
[Pylon, Gateway, Gateway, Pylon, Pylon, Pylon, Pylon] (5) {2825.6} -> 0.6
[Pylon, Gateway, Assimilator, CyberneticsCore, Pylon, SingularityCharge, Pylon, RoboticsFacility, Pylon] (5) {3544.4} -> 0.4
[Pylon, Gateway, Assimilator, Pylon, CyberneticsCore, Gateway, Pylon] (6) {3434.667} -> 0.333
[Pylon, Gateway, Assimilator, Pylon, CyberneticsCore, Pylon, RoboticsFacility, SingularityCharge] (5) {2658.6} -> 0.6
[Pylon, Gateway, Assimilator, Pylon, CyberneticsCore, Pylon, RoboticsFacility, Pylon] (6) {3362.333} -> 1
[Pylon, Gateway, Assimilator, Pylon, CyberneticsCore, Pylon, SingularityCharge, RoboticsFacility, Pylon] (5) {4193} -> 0.4
[Pylon, Gateway, Assimilator, Pylon, CyberneticsCore, Pylon, SingularityCharge, Gateway, Pylon, RoboticsFacility, Pylon, Observatory, Pylon] (6) {2496.333} -> 0.333
[Pylon, Gateway, Assimilator, Pylon, CyberneticsCore, Pylon, Gateway, SingularityCharge, Pylon, RoboticsFacility, Pylon] (6) {2803.333} -> 0.667
[Pylon, Gateway, Pylon, Assimilator, CyberneticsCore, Pylon] (9) {3369.778} -> 0.556
