[Pylon, Nexus, Gateway, Assimilator, Pylon, CyberneticsCore, Gateway, SingularityCharge] (8) {2436.25} -> 0.5
[Pylon, Nexus, Gateway, Assimilator, Pylon, CyberneticsCore, Gateway, SingularityCharge, Pylon] (4) {2436.25} -> 0.5
[Pylon, Gateway, Assimilator, CyberneticsCore, Gateway] (4) {2558} -> 0.5
[Pylon, Gateway, Assimilator, CyberneticsCore, Pylon, RoboticsFacility, Pylon, SingularityCharge, Pylon, Observatory, Pylon, RoboticsSupportBay, Nexus] (4) {2721.25} -> 0.5
[Pylon, Gateway, Assimilator, CyberneticsCore, Pylon, RoboticsFacility, Pylon, SingularityCharge, Pylon, Observatory, Pylon, RoboticsSupportBay, Pylon] (4) {2741.75} -> 1
[Pylon, Gateway, Assimilator, CyberneticsCore, Pylon, SingularityCharge, Gateway, Pylon, Pylon] (4) {3165.25} -> 1
[Pylon, Gateway, Assimilator, CyberneticsCore, Pylon, SingularityCharge, Pylon, RoboticsFacility, Pylon, RoboticsSupportBay] (4) {4495.25} -> 0.25
[Pylon, Gateway, Assimilator, CyberneticsCore, Pylon, SingularityCharge, Pylon, Nexus, Gateway, Pylon] (4) {4014.75} -> 1
[Pylon, Gateway, Assimilator, CyberneticsCore, Pylon, SingularityCharge, Pylon, Nexus, Pylon, RoboticsFacility, Gateway] (7) {4799.571} -> 0.714
[Pylon, Gateway, Assimilator, CyberneticsCore, Pylon, SingularityCharge, Pylon, Nexus, Pylon, Gateway, Gateway, RoboticsFacility, Pylon] (4) {4524.75} -> 0.5
[Pylon, Gateway, Assimilator, CyberneticsCore, Pylon, SingularityCharge, Pylon, Gateway, RoboticsFacility] (4) {4420.5} -> 0.5
[Pylon, Gateway, Assimilator, CyberneticsCore, Pylon, Gateway, SingularityCharge, Pylon] (4) {3038.5} -> 0.25
[Pylon, Gateway, Assimilator, Pylon, CyberneticsCore, Pylon] (4) {3963.25} -> 0.5
