[Pylon, Nexus, Forge, PhotonCannon, Gateway] (5) {2218.8} -> 0.4
[Pylon, Gateway, Gateway, Pylon, Pylon] (7) {2934.143} -> 0.571
[Pylon, Gateway, Assimilator, Pylon, CyberneticsCore, Pylon] (6) {3278.167} -> 0.667
[Pylon, Assimilator, Forge, ProtossGroundWeapons, Gateway] (6) {2166.333} -> 0.333
[Pylon, Forge, Nexus, Gateway, PhotonCannon] (6) {3955.167} -> 0.833
[Pylon, Forge, Nexus, PhotonCannon, Gateway, Pylon, Assimilator, CyberneticsCore] (5) {3918.2} -> 0.8
[Pylon, Forge, Nexus, PhotonCannon, PhotonCannon, Pylon, Gateway, Assimilator, CyberneticsCore] (6) {3093} -> 0.5
[Pylon, Forge, Nexus, PhotonCannon, Pylon, Gateway] (5) {3571.8} -> 0.6
[Pylon, Forge, Nexus, Pylon, Gateway] (5) {4675.8} -> 0.4
[Pylon, Forge, PhotonCannon, Nexus, Gateway, Pylon, Assimilator] (7) {2260.429} -> 0.286
[Pylon, Forge, PhotonCannon, Nexus, Pylon] (6) {4663.667} -> 0.667
[Pylon, Forge, PhotonCannon, PhotonCannon, Nexus, Gateway, Pylon] (5) {4571.6} -> 1
[Pylon, Forge, PhotonCannon, PhotonCannon, Nexus, Pylon, Gateway, Assimilator] (5) {3136.4} -> 0.6
[Pylon, Forge, PhotonCannon, Pylon, Nexus] (6) {3591.833} -> 0.5
[Pylon, Forge, Pylon, PhotonCannon] (5) {3743.4} -> 0.4
