[Barracks] (1) {2722} -> 0
[SupplyDepot, Barracks, Refinery, Factory] (1) {1305} -> 0
[SupplyDepot, Barracks, Refinery, SupplyDepot, Factory, Factory] (1) {6216} -> 0
[SupplyDepot, Barracks, Refinery, SupplyDepot, Factory, SupplyDepot] (1) {2492} -> 1
[SupplyDepot, CommandCenter] (1) {4444} -> 1
[SupplyDepot, Refinery] (1) {2673} -> 1
