[SpawningPool, Extractor, MetabolicBoost, Hatchery, HydraliskDen, MuscularAugments, GroovedSpines] (6) {1535.875} -> 0.75
[SpawningPool, Extractor, MetabolicBoost, Hatchery, Hatchery] (9) {3450.9} -> 0.5
[SpawningPool, Extractor, Hatchery, MetabolicBoost] (5) {3477.167} -> 0.333
[SpawningPool, Hatchery, Extractor] (7) {2518.5} -> 0.25
[SpawningPool, Hatchery, Hatchery, Extractor] (14) {3929.867} -> 0.6
[SpawningPool, Hatchery, Hatchery, Hatchery, Extractor] (8) {3637.556} -> 0.556
[Hatchery, SpawningPool, Extractor, Hatchery, MetabolicBoost] (5) {4024.333} -> 0.333
[Hatchery, SpawningPool, Hatchery, Extractor, Extractor] (7) {4173.625} -> 0.25
[Hatchery, SpawningPool, Hatchery, Extractor, HydraliskDen] (6) {4277.714} -> 0.143
[Hatchery, SpawningPool, Hatchery, Extractor, CreepColony] (7) {3196.375} -> 0.375
[Hatchery, SpawningPool, Hatchery, Extractor, EvolutionChamber] (5) {3135.667} -> 0.333
[Hatchery, SpawningPool, Hatchery, Extractor, MetabolicBoost] (6) {2940.286} -> 0.143
[Hatchery, SpawningPool, Hatchery, Extractor, Hatchery] (8) {3783.333} -> 0.333
[Hatchery, SpawningPool, Hatchery, Hatchery, Extractor, EvolutionChamber] (6) {4139.857} -> 0
