[Pylon, Nexus] (398) {3773.639} -> 0.495
[Pylon, Gateway, Gateway, Pylon, Pylon] (425) {2225.175} -> 0.49
[Pylon, Gateway, Assimilator, CyberneticsCore, Pylon, Pylon] (243) {3521.502} -> 0.463
[Pylon, Gateway, Assimilator, CyberneticsCore, Pylon, SingularityCharge, Pylon, RoboticsFacility, Pylon] (249) {4542.795} -> 0.537
[Pylon, Gateway, Assimilator, CyberneticsCore, Pylon, SingularityCharge, Pylon, Nexus] (293) {4270.901} -> 0.503
[Pylon, Gateway, Assimilator, Assimilator] (269) {3723.768} -> 0.497
[Pylon, Gateway, Assimilator, Pylon, CyberneticsCore, Pylon] (435) {3594.343} -> 0.486
[Pylon, Gateway, Pylon, Assimilator] (298) {3421.531} -> 0.512
[Pylon, Assimilator] (275) {3795.326} -> 0.513
[Pylon, Forge, Nexus, PhotonCannon, PhotonCannon] (256) {4279.053} -> 0.498
[Pylon, Forge, PhotonCannon, Nexus, Gateway] (278) {3961.233} -> 0.476
[Pylon, Forge, PhotonCannon, PhotonCannon] (359) {3531.245} -> 0.459
[Pylon, Forge, Pylon] (301) {3589.903} -> 0.45
