[Pylon, Gateway, Gateway, Pylon, Pylon, Assimilator] (71) {1906.961} -> 0.473
[Pylon, Gateway, Gateway, Pylon, Pylon, Pylon] (102) {1795.281} -> 0.575
[Pylon, Gateway, Assimilator, CyberneticsCore, Pylon, SingularityCharge, Pylon] (119) {3529.221} -> 0.457
[Pylon, Gateway, Assimilator, CyberneticsCore, Pylon, Pylon] (69) {3100.533} -> 0.456
[Pylon, Gateway, Assimilator, Pylon, CyberneticsCore, Gateway] (95) {2414.783} -> 0.513
[Pylon, Gateway, Assimilator, Pylon, CyberneticsCore, Pylon, SingularityCharge, Pylon] (84) {4025.173} -> 0.529
[Pylon, Gateway, Assimilator, Pylon, Pylon, CyberneticsCore] (80) {3527.66} -> 0.49
[Pylon, Gateway, Pylon, Gateway] (79) {2454.154} -> 0.481
[Pylon, Gateway, Pylon, Assimilator, CyberneticsCore, Pylon, SingularityCharge] (72) {3407.153} -> 0.541
[Pylon, Gateway, Pylon, Pylon] (119) {3365.306} -> 0.562
