[Pylon, Nexus, Gateway, Assimilator] (107) {3774.991} -> 0.509
[Pylon, Gateway, Gateway, Pylon] (131) {1863.589} -> 0.534
[Pylon, Gateway, Assimilator, CyberneticsCore, Pylon, SingularityCharge, Gateway, Pylon] (104) {2864.39} -> 0.471
[Pylon, Gateway, Assimilator, CyberneticsCore, Pylon, SingularityCharge, Pylon, RoboticsFacility, Pylon] (240) {4844.32} -> 0.54
[Pylon, Gateway, Assimilator, CyberneticsCore, Pylon, SingularityCharge, Pylon, Nexus, Pylon] (134) {3943.012} -> 0.56
[Pylon, Gateway, Assimilator, CyberneticsCore, Pylon, SingularityCharge, Pylon, Gateway] (130) {3603.198} -> 0.512
[Pylon, Gateway, Assimilator, CyberneticsCore, Pylon, SingularityCharge, Pylon, Pylon] (125) {4082.051} -> 0.58
[Pylon, Gateway, Assimilator, CyberneticsCore, Pylon, Gateway] (130) {2711.987} -> 0.478
[Pylon, Gateway, Assimilator, CyberneticsCore, Pylon, Pylon, SingularityCharge] (117) {3625.778} -> 0.486
[Pylon, Gateway, Assimilator, Assimilator, CyberneticsCore, Pylon] (137) {3852.032} -> 0.468
[Pylon, Gateway, Assimilator, Pylon, CyberneticsCore, Pylon] (124) {3581.412} -> 0.541
[Pylon, Gateway, Pylon, Assimilator] (118) {3503.724} -> 0.52
[Pylon, Assimilator, Gateway, Assimilator] (136) {4190.101} -> 0.568
