[Pylon, Nexus, Forge] (170) {3770.006} -> 0.485
[Pylon, Gateway, Gateway, Pylon, Pylon] (232) {2478.624} -> 0.444
[Pylon, Gateway, Assimilator, CyberneticsCore, Pylon] (111) {3340.435} -> 0.487
[Pylon, Gateway, Assimilator, Pylon, CyberneticsCore, Pylon] (140) {3312.097} -> 0.483
[Pylon, Gateway, Pylon] (144) {2669.925} -> 0.452
[Pylon, Forge, Nexus, PhotonCannon, Gateway] (154) {4238.535} -> 0.497
[Pylon, Forge, Nexus, PhotonCannon, PhotonCannon, Gateway, Assimilator] (115) {4443.146} -> 0.472
[Pylon, Forge, PhotonCannon, Nexus, Gateway, Assimilator] (101) {3847.269} -> 0.426
[Pylon, Forge, PhotonCannon, Nexus, Gateway, Pylon, Assimilator] (101) {4141.574} -> 0.519
[Pylon, Forge, PhotonCannon, Nexus, PhotonCannon] (103) {3619.101} -> 0.495
[Pylon, Forge, PhotonCannon, Nexus, Pylon] (102) {4116.435} -> 0.454
[Pylon, Forge, PhotonCannon, PhotonCannon, Nexus, Gateway] (137) {3822.669} -> 0.493
[Pylon, Forge, PhotonCannon, Pylon] (182) {3760.053} -> 0.449
[Pylon, Forge, Pylon, PhotonCannon] (226) {3823.33} -> 0.465
[Pylon, Pylon] (110) {3570.342} -> 0.441
