[Extractor, SpawningPool] (114) {2694.614} -> 0.447
[SpawningPool, Extractor, MetabolicBoost, Hatchery, Hatchery, Spire] (128) {3792.39} -> 0.54
[SpawningPool, Extractor, Hatchery, Extractor, Hatchery] (108) {3302.29} -> 0.621
[SpawningPool, Extractor, Hatchery, Hatchery, Extractor] (142) {3113.341} -> 0.632
[SpawningPool, Hatchery, Extractor, Hatchery, MetabolicBoost, Spire, Hatchery] (139) {3856.721} -> 0.59
[SpawningPool, Hatchery, Hatchery, Extractor, MetabolicBoost, Spire, Hatchery] (133) {3862.763} -> 0.61
[SpawningPool, Hatchery, Hatchery, Extractor, Hatchery] (115) {3524.058} -> 0.538
[SpawningPool, Hatchery, Hatchery, Hatchery] (103) {3456.08} -> 0.62
[Hatchery, SpawningPool, Extractor, Hatchery] (164) {3762.095} -> 0.571
[Hatchery, SpawningPool, Hatchery, Extractor] (204) {4058.65} -> 0.519
