[SupplyDepot, Barracks, Barracks, SupplyDepot, Refinery, Academy] (1) {6931} -> 1
[SupplyDepot, Barracks, Barracks, SupplyDepot, Refinery, SupplyDepot] (2) {1603.5} -> 0
[SupplyDepot, Barracks, Barracks, Refinery] (1) {3179} -> 0
[SupplyDepot, Barracks, Refinery, Factory] (2) {3344.5} -> 0
[SupplyDepot, Barracks, Refinery, SupplyDepot, Factory, Barracks] (1) {3586} -> 1
[SupplyDepot, Barracks, Refinery, SupplyDepot, Factory, Factory] (1) {6962} -> 1
[SupplyDepot, Barracks, Refinery, SupplyDepot, Factory, SupplyDepot] (1) {2710} -> 0
[SupplyDepot, Barracks, Refinery, SupplyDepot, SupplyDepot] (1) {3418} -> 0
[SupplyDepot, Refinery] (1) {6484} -> 1
