[SupplyDepot, Barracks, Refinery, SupplyDepot, Factory] (2) {5280.5} -> 1
[SupplyDepot, Barracks, Refinery, SupplyDepot, SupplyDepot] (1) {3418} -> 0
[SupplyDepot, Refinery] (1) {7184} -> 0
