[SupplyDepot, Barracks, Barracks, SupplyDepot, Refinery, Academy] (1) {6931} -> 1
[SupplyDepot, Barracks, Barracks, SupplyDepot, Refinery, SupplyDepot] (2) {1603.5} -> 0
[SupplyDepot, Barracks, Barracks, Refinery] (1) {3179} -> 0
[SupplyDepot, Barracks, Refinery, Factory] (1) {1450} -> 0
[SupplyDepot, Barracks, Refinery, SupplyDepot] (1) {3586} -> 1
