[Pylon, Gateway, Gateway, Pylon, CyberneticsCore] (1) {2403} -> 0
[Pylon, Gateway, Gateway, Pylon, Pylon, Assimilator, CyberneticsCore, Assimilator] (1) {2280} -> 0
[Pylon, Gateway, Gateway, Pylon, Pylon, Assimilator, CyberneticsCore, Pylon] (1) {5378} -> 1
[Pylon, Gateway, Gateway, Pylon, Pylon, Pylon] (1) {4135} -> 0
[Pylon, Gateway, Assimilator, CyberneticsCore, Pylon, Stargate] (1) {1767} -> 1
[Pylon, Gateway, Assimilator, CyberneticsCore, Pylon, SingularityCharge] (1) {6758} -> 0
[Pylon, Gateway, Assimilator, Forge] (1) {1590} -> 1
[Pylon, Assimilator] (1) {3199} -> 1
