[Pylon, Gateway, Gateway] (1) {2280} -> 0
[Pylon, Gateway, Assimilator, CyberneticsCore, Pylon, SingularityCharge] (1) {6758} -> 0
[Pylon, Gateway, Assimilator, CyberneticsCore, Pylon, CitadelofAdun] (1) {9024} -> 1
[Pylon, Gateway, Assimilator, Pylon] (1) {2707} -> 1
