[Pylon, Gateway, Gateway, Pylon, CyberneticsCore] (1) {2403} -> 0
[Pylon, Gateway, Gateway, Pylon, Pylon, Assimilator] (1) {5378} -> 1
[Pylon, Gateway, Gateway, Pylon, Pylon, Pylon] (1) {4135} -> 0
[Pylon, Gateway, Assimilator] (2) {1678.5} -> 1
