[SpawningPool] (2) {1108} -> 0
[Hatchery, SpawningPool, Extractor] (1) {4594} -> 1
[Hatchery, SpawningPool, Hatchery, Extractor, CreepColony, CreepColony, Extractor] (1) {6164} -> 1
[Hatchery, SpawningPool, Hatchery, Extractor, CreepColony, CreepColony, MetabolicBoost] (1) {3921} -> 0
