[Pylon, Nexus] (141) {3233.348} -> 0.504
[Pylon, Gateway, Gateway, Pylon, Assimilator] (248) {3010.404} -> 0.488
[Pylon, Gateway, Gateway, Pylon, Pylon, Assimilator] (231) {2930.266} -> 0.472
[Pylon, Gateway, Gateway, Pylon, Pylon, Pylon] (221) {2658.101} -> 0.655
[Pylon, Gateway, Assimilator, CyberneticsCore, Pylon, RoboticsFacility, Pylon] (194) {3464.596} -> 0.485
[Pylon, Gateway, Assimilator, CyberneticsCore, Pylon, SingularityCharge, Pylon, RoboticsFacility] (225) {3590.882} -> 0.504
[Pylon, Gateway, Assimilator, CyberneticsCore, Pylon, Pylon] (164) {3102.581} -> 0.473
[Pylon, Gateway, Assimilator, Pylon, CyberneticsCore, Gateway] (127) {2670.534} -> 0.504
[Pylon, Gateway, Assimilator, Pylon, CyberneticsCore, Pylon, Stargate, CitadelofAdun] (128) {3362.553} -> 0.621
[Pylon, Gateway, Pylon, Assimilator] (123) {2946.056} -> 0.5
[Pylon, Forge, PhotonCannon] (124) {2828.656} -> 0.416
