[Pylon, Gateway, Gateway, Pylon, Assimilator, Pylon] (45) {2709.222} -> 0.489
[Pylon, Gateway, Gateway, Pylon, Pylon, Assimilator] (58) {2665.121} -> 0.414
[Pylon, Gateway, Assimilator, CyberneticsCore, Pylon, SingularityCharge, Pylon] (61) {3018.812} -> 0.375
[Pylon, Gateway, Assimilator, CyberneticsCore, Pylon, Gateway] (58) {3104.574} -> 0.443
[Pylon, Gateway, Assimilator, Pylon, Gateway] (53) {2743.618} -> 0.673
[Pylon, Gateway, Assimilator, Pylon, CyberneticsCore, Gateway, Pylon, SingularityCharge] (61) {2655.785} -> 0.462
[Pylon, Gateway, Assimilator, Pylon, CyberneticsCore, Pylon, RoboticsFacility, Pylon] (56) {2811.776} -> 0.534
[Pylon, Gateway, Assimilator, Pylon, CyberneticsCore, Pylon, SingularityCharge, RoboticsFacility, Pylon] (68) {3462.757} -> 0.657
[Pylon, Gateway, Assimilator, Pylon, CyberneticsCore, Pylon, Gateway, SingularityCharge, Pylon] (43) {3126.174} -> 0.565
[Pylon, Gateway, Assimilator, Pylon, Pylon] (51) {2780.434} -> 0.66
[Pylon, Gateway, Pylon, Assimilator, CyberneticsCore, Pylon] (57) {3002.431} -> 0.534
