[Pylon, Nexus, Gateway] (42) {3089.476} -> 0.452
[Pylon, Gateway, Assimilator, CyberneticsCore, Pylon, RoboticsFacility, Pylon, SingularityCharge] (60) {3313.435} -> 0.468
[Pylon, Gateway, Assimilator, CyberneticsCore, Pylon, RoboticsFacility, Pylon, RoboticsSupportBay] (47) {3376.367} -> 0.51
[Pylon, Gateway, Assimilator, CyberneticsCore, Pylon, SingularityCharge, Gateway, Pylon] (75) {3192.645} -> 0.421
[Pylon, Gateway, Assimilator, CyberneticsCore, Pylon, SingularityCharge, Pylon, RoboticsFacility, Gateway, Pylon, Observatory, Pylon] (59) {3482.9} -> 0.567
[Pylon, Gateway, Assimilator, CyberneticsCore, Pylon, SingularityCharge, Pylon, RoboticsFacility, Pylon] (99) {3765.68} -> 0.47
[Pylon, Gateway, Assimilator, CyberneticsCore, Pylon, SingularityCharge, Pylon, Nexus] (57) {3594.224} -> 0.569
[Pylon, Gateway, Assimilator, CyberneticsCore, Pylon, SingularityCharge, Pylon, Gateway, Pylon] (60) {3431.836} -> 0.508
[Pylon, Gateway, Assimilator, CyberneticsCore, Pylon, SingularityCharge, Pylon, Pylon] (50) {3662.608} -> 0.471
[Pylon, Gateway, Assimilator, CyberneticsCore, Pylon, Gateway] (75) {3267.118} -> 0.421
[Pylon, Gateway, Assimilator, CyberneticsCore, Pylon, CitadelofAdun] (64) {2969.262} -> 0.4
[Pylon, Gateway, Assimilator, CyberneticsCore, Pylon, Pylon, RoboticsFacility] (51) {3186.83} -> 0.491
[Pylon, Gateway, Assimilator, Assimilator] (67) {3119.868} -> 0.588
[Pylon, Gateway, Assimilator, Pylon, CyberneticsCore] (82) {3081.771} -> 0.578
