[Pylon, Nexus, Forge] (63) {3165.032} -> 0.54
[Pylon, Gateway, Gateway, Pylon, Assimilator, CyberneticsCore, Pylon] (86) {3214.023} -> 0.466
[Pylon, Gateway, Gateway, Pylon, Assimilator, Pylon, CyberneticsCore] (67) {2786.087} -> 0.449
[Pylon, Gateway, Gateway, Pylon, Pylon, Assimilator, CyberneticsCore, Pylon] (64) {2682.762} -> 0.512
[Pylon, Gateway, Gateway, Pylon, Pylon, Assimilator, Pylon, CyberneticsCore] (71) {2651.611} -> 0.567
[Pylon, Gateway, Gateway, Pylon, Pylon, Pylon, Assimilator] (100) {2466.4} -> 0.726
[Pylon, Gateway, Assimilator, CyberneticsCore, Pylon, Stargate, Pylon] (70) {2464.62} -> 0.465
[Pylon, Gateway, Assimilator, Pylon, CyberneticsCore, Stargate] (61) {2915.984} -> 0.397
[Pylon, Gateway, Assimilator, Pylon, CyberneticsCore, Pylon, Stargate, CitadelofAdun, Pylon] (75) {3383.987} -> 0.61
[Pylon, Gateway, Assimilator, Pylon, CyberneticsCore, Pylon, CitadelofAdun] (74) {3797.013} -> 0.592
[Pylon, Gateway, Pylon, Assimilator] (65) {2927.152} -> 0.47
[Pylon, Forge, Nexus] (109) {3304.409} -> 0.555
[Pylon, Forge, PhotonCannon] (123) {2841.581} -> 0.419
