[SupplyDepot, Barracks, Refinery, Factory, SupplyDepot, Factory, Armory] (25) {3082.333} -> 0.63
[SupplyDepot, Barracks, Refinery, Factory, SupplyDepot, Factory, MachineShop, SupplyDepot, SpiderMines] (21) {4139.174} -> 0.652
[SupplyDepot, Barracks, Refinery, Factory, SupplyDepot, Starport] (19) {4039.474} -> 0.368
[SupplyDepot, Barracks, Refinery, Factory, SupplyDepot, MachineShop] (16) {4111.938} -> 0.5
[SupplyDepot, Barracks, Refinery, SupplyDepot, Factory, Factory, Armory] (28) {3189.393} -> 0.464
[SupplyDepot, Barracks, Refinery, SupplyDepot, Factory, Factory, SupplyDepot, MachineShop] (25) {3549} -> 0.68
[SupplyDepot, Barracks, Refinery, SupplyDepot, Factory, Factory, MachineShop, SupplyDepot] (30) {3866.5} -> 0.7
[SupplyDepot, Barracks, Refinery, SupplyDepot, Factory, Starport] (16) {3922.562} -> 0.5
[SupplyDepot, Barracks, Refinery, SupplyDepot, Factory, SupplyDepot, Starport] (16) {3520.438} -> 0.438
[SupplyDepot, Barracks, Refinery, SupplyDepot, Factory, SupplyDepot, MachineShop] (17) {4075.235} -> 0.412
[SupplyDepot, Barracks, Refinery, SupplyDepot, Factory, MachineShop] (17) {3828} -> 0.235
[SupplyDepot, Refinery, Barracks, Factory, SupplyDepot] (17) {3886.471} -> 0.529
[SupplyDepot, Refinery, Barracks, SupplyDepot, Factory] (35) {3687.686} -> 0.514
