[Extractor, Hatchery, SpawningPool, Extractor] (100) {3110.79} -> 0.41
[SpawningPool, Extractor, MetabolicBoost, Hatchery] (88) {3070.72} -> 0.538
[SpawningPool, Extractor, Hatchery] (93) {2730.898} -> 0.408
[SpawningPool, Hatchery, Extractor] (106) {2681.284} -> 0.413
[SpawningPool, Hatchery, Hatchery, Extractor, CreepColony] (69) {3063.558} -> 0.519
[SpawningPool, Hatchery, Hatchery, CreepColony] (84) {3334.714} -> 0.451
[Hatchery, SpawningPool, Extractor, CreepColony] (87) {3226.258} -> 0.348
[Hatchery, SpawningPool, Extractor, MetabolicBoost] (93) {2751.137} -> 0.568
[Hatchery, SpawningPool, Extractor, Hatchery] (115) {3038.239} -> 0.581
[Hatchery, SpawningPool, CreepColony, CreepColony, CreepColony] (68) {3012.671} -> 0.397
[Hatchery, SpawningPool, Hatchery, Extractor, HydraliskDen] (96) {3246.384} -> 0.707
[Hatchery, SpawningPool, Hatchery, Extractor, CreepColony] (99) {3545.451} -> 0.578
[Hatchery, SpawningPool, Hatchery, CreepColony, Extractor] (66) {3041.657} -> 0.457
[Hatchery, SpawningPool, Hatchery, Hatchery] (66) {3871.145} -> 0.638
