[Extractor, Hatchery, SpawningPool, Extractor, CreepColony] (66) {2905.985} -> 0.343
[SpawningPool, Extractor, Hatchery] (73) {2818.526} -> 0.397
[SpawningPool, Hatchery, Extractor] (51) {2351.361} -> 0.393
[SpawningPool, Hatchery, Hatchery, Extractor] (62) {3080.2} -> 0.573
[Hatchery, SpawningPool, Extractor, Extractor] (86) {2823.07} -> 0.51
[Hatchery, SpawningPool, Extractor, CreepColony, Extractor] (55) {2811.042} -> 0.431
[Hatchery, SpawningPool, Extractor, CreepColony, HydraliskDen] (61) {3033.423} -> 0.436
[Hatchery, SpawningPool, Extractor, CreepColony, CreepColony] (119) {2712.051} -> 0.397
[Hatchery, SpawningPool, Extractor, Hatchery, CreepColony] (62) {2890.532} -> 0.468
[Hatchery, SpawningPool, CreepColony] (69) {2871.415} -> 0.427
[Hatchery, SpawningPool, Hatchery, Extractor, CreepColony, Extractor] (55) {3090.111} -> 0.528
[Hatchery, SpawningPool, Hatchery, Extractor, CreepColony, CreepColony] (76) {3219.462} -> 0.559
[Hatchery, SpawningPool, Hatchery, CreepColony, Extractor] (57) {3088.028} -> 0.444
