[Extractor, SpawningPool, Hatchery, Spire] (57) {2385.241} -> 0.362
[Extractor, SpawningPool, Hatchery, MetabolicBoost, Spire, Hatchery] (85) {2353.516} -> 0.667
[Extractor, Hatchery, SpawningPool] (80) {2072.775} -> 0.412
[SpawningPool, Extractor, MetabolicBoost, Spire] (75) {2312.341} -> 0.488
[SpawningPool, Extractor, MetabolicBoost, Hatchery] (65) {2018.167} -> 0.444
[SpawningPool, Extractor, Hatchery, Spire] (56) {2292.61} -> 0.458
[SpawningPool, Extractor, Hatchery, MetabolicBoost, Spire] (118) {2352.976} -> 0.537
[SpawningPool, Hatchery, Extractor] (82) {1857.325} -> 0.614
[Hatchery, Extractor, SpawningPool, MetabolicBoost] (98) {2245.152} -> 0.566
[Hatchery, SpawningPool, Extractor, CreepColony, MetabolicBoost] (53) {1937.887} -> 0.565
[Hatchery, SpawningPool, Extractor, MetabolicBoost, Spire] (104) {2143.5} -> 0.464
