[Pylon, Nexus, Gateway, Assimilator] (23) {4336.609} -> 0.478
[Pylon, Gateway, Gateway, Pylon, Pylon, Nexus, Assimilator] (24) {4447.5} -> 0.588
[Pylon, Gateway, Gateway, Pylon, Pylon, Assimilator] (34) {3000.159} -> 0.5
[Pylon, Gateway, Gateway, Pylon, Pylon, Pylon, Nexus] (25) {3096.233} -> 0.488
[Pylon, Gateway, Gateway, Pylon, Pylon, Pylon, Pylon] (23) {2341.146} -> 0.61
[Pylon, Gateway, Assimilator, CyberneticsCore, Pylon, SingularityCharge, Pylon, RoboticsFacility, Pylon] (34) {4053.486} -> 0.514
[Pylon, Gateway, Assimilator, CyberneticsCore, Pylon, SingularityCharge, Pylon, Pylon] (24) {4021.889} -> 0.593
[Pylon, Gateway, Assimilator, CyberneticsCore, Pylon, Pylon] (33) {3352.371} -> 0.429
[Pylon, Gateway, Assimilator, Pylon, CyberneticsCore, Pylon, SingularityCharge] (24) {3946.24} -> 0.68
[Pylon, Gateway, Pylon] (56) {3383.825} -> 0.333
[Pylon, Forge, PhotonCannon, Nexus] (29) {3814.069} -> 0.276
