[Pylon, Gateway, Gateway, Pylon, Pylon, Assimilator, CyberneticsCore, Pylon] (7) {3852.375} -> 0.375
[Pylon, Gateway, Gateway, Pylon, Pylon, Assimilator, Pylon] (6) {3078.857} -> 0.857
[Pylon, Gateway, Gateway, Pylon, Pylon, Pylon] (9) {2639.2} -> 0.7
[Pylon, Gateway, Assimilator, CyberneticsCore, Pylon, SingularityCharge, Pylon] (11) {3417.455} -> 0.727
[Pylon, Gateway, Assimilator, CyberneticsCore, Pylon, Pylon] (6) {2167.833} -> 0.5
[Pylon, Gateway, Assimilator, Pylon, Gateway] (6) {3640.667} -> 0.5
[Pylon, Gateway, Assimilator, Pylon, CyberneticsCore, Gateway, Pylon] (7) {2681.714} -> 0.571
[Pylon, Gateway, Assimilator, Pylon, CyberneticsCore, Pylon, SingularityCharge, RoboticsFacility, Gateway, Pylon] (6) {4404.333} -> 0.667
[Pylon, Gateway, Assimilator, Pylon, CyberneticsCore, Pylon, SingularityCharge, RoboticsFacility, Pylon] (6) {3590.167} -> 0.333
[Pylon, Gateway, Assimilator, Pylon, CyberneticsCore, Pylon, SingularityCharge, Pylon] (8) {4563.375} -> 0.625
[Pylon, Gateway, Assimilator, Pylon, CyberneticsCore, Pylon, Pylon] (9) {3622.778} -> 0.667
[Pylon, Gateway, Assimilator, Pylon, Pylon, CyberneticsCore, Pylon] (6) {2900.167} -> 0.5
[Pylon, Gateway, Pylon, Assimilator, CyberneticsCore, Pylon, SingularityCharge] (8) {3015.889} -> 0.556
[Pylon, Gateway, Pylon, Pylon] (6) {2536.857} -> 0.571
