[Pylon, Nexus, Gateway, Assimilator, CyberneticsCore, Gateway] (9) {5352.333} -> 0.556
[Pylon, Nexus, Gateway, Assimilator, Pylon, CyberneticsCore] (8) {4156.5} -> 0.375
[Pylon, Gateway, Assimilator, CyberneticsCore, Pylon, RoboticsFacility, Pylon] (10) {3962.917} -> 0.25
[Pylon, Gateway, Assimilator, CyberneticsCore, Pylon, SingularityCharge, Gateway, Pylon] (8) {2681.182} -> 0.636
[Pylon, Gateway, Assimilator, CyberneticsCore, Pylon, SingularityCharge, Pylon, RoboticsFacility, Gateway, Pylon] (8) {3333.091} -> 0.727
[Pylon, Gateway, Assimilator, CyberneticsCore, Pylon, SingularityCharge, Pylon, RoboticsFacility, Pylon, RoboticsSupportBay] (9) {3318.083} -> 0.75
[Pylon, Gateway, Assimilator, CyberneticsCore, Pylon, SingularityCharge, Pylon, Nexus, Pylon, RoboticsFacility] (9) {4803.667} -> 0.333
[Pylon, Gateway, Assimilator, CyberneticsCore, Pylon, SingularityCharge, Pylon, Pylon, RoboticsFacility] (10) {3073.692} -> 0.615
[Pylon, Gateway, Assimilator, CyberneticsCore, Pylon, Gateway, SingularityCharge] (8) {1979.9} -> 0.4
[Pylon, Gateway, Assimilator, CyberneticsCore, Pylon, Pylon, SingularityCharge, Pylon] (8) {4012.3} -> 0.6
[Pylon, Gateway, Assimilator, CyberneticsCore, Pylon, Pylon, Pylon] (9) {3170.636} -> 0.273
[Pylon, Gateway, Assimilator, Pylon, CyberneticsCore, Pylon] (16) {3912.706} -> 0.765
