[Pylon, Gateway, Gateway, Pylon, Nexus] (12) {3998.933} -> 0.4
[Pylon, Gateway, Gateway, Pylon, Assimilator] (18) {3164.095} -> 0.476
[Pylon, Gateway, Gateway, Pylon, Pylon, Nexus, Assimilator, Pylon] (15) {4541.348} -> 0.609
[Pylon, Gateway, Gateway, Pylon, Pylon, Assimilator, CyberneticsCore, Pylon] (13) {2631.227} -> 0.545
[Pylon, Gateway, Gateway, Pylon, Pylon, Pylon, Nexus, Assimilator] (17) {3094.429} -> 0.514
[Pylon, Gateway, Gateway, Pylon, Pylon, Pylon, Assimilator] (14) {2382.467} -> 0.533
[Pylon, Gateway, Gateway, Pylon, Pylon, Pylon, Pylon] (22) {2402.158} -> 0.605
[Pylon, Gateway, Assimilator, CyberneticsCore, Pylon] (14) {2582.143} -> 0.286
[Pylon, Gateway, Assimilator, Pylon, CyberneticsCore, Pylon, Stargate] (13) {3691.308} -> 0.615
[Pylon, Gateway, Pylon, Nexus] (13) {3420} -> 0.214
[Pylon, Forge, Nexus] (18) {3385.611} -> 0.333
[Pylon, Forge, PhotonCannon, Nexus, Gateway] (16) {3826.529} -> 0.235
[Pylon, Forge, PhotonCannon, PhotonCannon] (19) {3967.632} -> 0.316
[Pylon, Forge, Pylon] (15) {3844.733} -> 0.533
