[Extractor, Hatchery] (12) {3336.5} -> 0.583
[SpawningPool, Extractor, MetabolicBoost, Hatchery, Hatchery] (24) {3534.786} -> 0.429
[SpawningPool, Extractor, Hatchery, Hatchery] (17) {3376.059} -> 0.529
[SpawningPool, Hatchery, Extractor, Hatchery] (23) {4089.519} -> 0.704
[SpawningPool, Hatchery, CreepColony] (13) {4172.357} -> 0.643
[SpawningPool, Hatchery, Hatchery, Extractor, HydraliskDen] (12) {3249.722} -> 0.944
[SpawningPool, Hatchery, Hatchery, Extractor, CreepColony] (21) {4129.407} -> 0.704
[SpawningPool, Hatchery, Hatchery, Extractor, MetabolicBoost] (14) {2780.9} -> 0.75
[SpawningPool, Hatchery, Hatchery, CreepColony, Extractor] (23) {4813.483} -> 0.655
[Hatchery, SpawningPool, Extractor, Hatchery] (15) {3059.933} -> 0.467
[Hatchery, SpawningPool, CreepColony, CreepColony, CreepColony] (17) {2996.111} -> 0.389
[Hatchery, SpawningPool, Hatchery, Extractor, CreepColony] (13) {4182.154} -> 0.615
