[Pylon, Nexus] (842) {3807.383} -> 0.533
[Pylon, Gateway, Gateway, Pylon, Assimilator] (543) {2588.241} -> 0.493
[Pylon, Gateway, Gateway, Pylon, Pylon, Assimilator] (615) {2442.793} -> 0.552
[Pylon, Gateway, Gateway, Pylon, Pylon, Pylon] (652) {2513.535} -> 0.548
[Pylon, Gateway, Assimilator, CyberneticsCore, Pylon, Gateway] (624) {2908.728} -> 0.438
[Pylon, Gateway, Assimilator, CyberneticsCore, Pylon, Pylon] (550) {3242.407} -> 0.466
[Pylon, Gateway, Assimilator, CyberneticsCore, Pylon, SingularityCharge, Gateway, Pylon] (704) {3564.83} -> 0.497
[Pylon, Gateway, Assimilator, CyberneticsCore, Pylon, SingularityCharge, Pylon, RoboticsFacility] (954) {4186.428} -> 0.503
[Pylon, Gateway, Assimilator, CyberneticsCore, Pylon, SingularityCharge, Pylon, Nexus] (567) {3918.149} -> 0.509
[Pylon, Gateway, Assimilator, Pylon, CyberneticsCore, Pylon] (1263) {3355.356} -> 0.505
[Pylon, Gateway, Pylon, Assimilator, CyberneticsCore] (575) {3613.308} -> 0.486
[Pylon, Forge, Nexus] (837) {3932.543} -> 0.469
[Pylon, Forge, PhotonCannon, Nexus] (596) {3503.244} -> 0.445
[Pylon, Forge, PhotonCannon, PhotonCannon] (629) {3408.963} -> 0.436
