[Pylon, Gateway, Gateway, Pylon, Assimilator, Pylon, CyberneticsCore] (219) {2642.775} -> 0.571
[Pylon, Gateway, Gateway, Pylon, Pylon, Assimilator, CyberneticsCore, Pylon] (191) {2427.745} -> 0.55
[Pylon, Gateway, Gateway, Pylon, Pylon, Pylon] (350) {2693.913} -> 0.551
[Pylon, Gateway, Assimilator, CyberneticsCore, Pylon, SingularityCharge] (310) {2696.693} -> 0.477
[Pylon, Gateway, Assimilator, CyberneticsCore, Pylon, Gateway] (201) {2281.612} -> 0.364
[Pylon, Gateway, Assimilator, Pylon, Gateway] (182) {2699.057} -> 0.521
[Pylon, Gateway, Assimilator, Pylon, CyberneticsCore, Gateway, Pylon] (231) {2655.182} -> 0.458
[Pylon, Gateway, Assimilator, Pylon, CyberneticsCore, Pylon, SingularityCharge] (430) {3071.602} -> 0.496
[Pylon, Gateway, Assimilator, Pylon, Pylon] (189) {2678.806} -> 0.562
[Pylon, Gateway, Pylon, Assimilator, CyberneticsCore, Pylon] (302) {3177.813} -> 0.552
