[Pylon, Nexus, Gateway, Assimilator] (315) {3675.691} -> 0.498
[Pylon, Gateway, Gateway, Pylon] (264) {2459.423} -> 0.513
[Pylon, Gateway, Assimilator, CyberneticsCore, Gateway] (349) {3449.709} -> 0.429
[Pylon, Gateway, Assimilator, CyberneticsCore, Pylon, RoboticsFacility, Pylon] (390) {3696.307} -> 0.488
[Pylon, Gateway, Assimilator, CyberneticsCore, Pylon, SingularityCharge, Gateway, Pylon, Pylon] (321) {3544.973} -> 0.503
[Pylon, Gateway, Assimilator, CyberneticsCore, Pylon, SingularityCharge, Pylon, RoboticsFacility, Gateway, Pylon] (315) {4128.008} -> 0.487
[Pylon, Gateway, Assimilator, CyberneticsCore, Pylon, SingularityCharge, Pylon, RoboticsFacility, Pylon] (480) {4112.508} -> 0.529
[Pylon, Gateway, Assimilator, CyberneticsCore, Pylon, SingularityCharge, Pylon, Nexus, Pylon] (309) {3860.317} -> 0.51
[Pylon, Gateway, Assimilator, CyberneticsCore, Pylon, SingularityCharge, Pylon, Gateway] (439) {3707.311} -> 0.482
[Pylon, Gateway, Assimilator, CyberneticsCore, Pylon, SingularityCharge, Pylon, Pylon] (257) {3776.91} -> 0.532
[Pylon, Gateway, Assimilator, CyberneticsCore, Pylon, Gateway, SingularityCharge] (291) {2994.617} -> 0.458
[Pylon, Gateway, Assimilator, CyberneticsCore, Pylon, CitadelofAdun] (262) {2954.642} -> 0.526
[Pylon, Gateway, Assimilator, CyberneticsCore, Pylon, Pylon] (458) {3490.404} -> 0.474
[Pylon, Gateway, Assimilator, Pylon, CyberneticsCore, Pylon] (409) {3668.945} -> 0.457
[Pylon, Gateway, Pylon] (384) {3426.711} -> 0.488
