[Pylon, Nexus, Forge] (290) {4093.283} -> 0.601
[Pylon, Gateway, Gateway, Pylon, Assimilator] (222) {2558.895} -> 0.484
[Pylon, Gateway, Gateway, Pylon, Pylon, Assimilator] (339) {2361.225} -> 0.539
[Pylon, Gateway, Gateway, Pylon, Pylon, Pylon] (456) {2446.478} -> 0.565
[Pylon, Gateway, Assimilator, CyberneticsCore, Pylon] (218) {2754.6} -> 0.476
[Pylon, Gateway, Assimilator, Pylon, CyberneticsCore, Pylon, Stargate] (241) {3504.9} -> 0.586
[Pylon, Gateway, Pylon, Assimilator] (264) {3402.287} -> 0.467
[Pylon, Forge, Nexus, Gateway] (225) {3986.603} -> 0.506
[Pylon, Forge, Nexus, PhotonCannon] (406) {3774.239} -> 0.45
[Pylon, Forge, PhotonCannon, Nexus, Gateway] (298) {3482.431} -> 0.437
[Pylon, Forge, PhotonCannon, PhotonCannon, Nexus, Gateway] (207) {3093.662} -> 0.443
[Pylon, Forge, PhotonCannon, Pylon] (207) {3310.076} -> 0.415
[Pylon, Forge, Pylon, PhotonCannon] (278) {3124.197} -> 0.428
