[Pylon, Gateway, Gateway, Pylon, Assimilator, Pylon, CyberneticsCore] (1434) {2890.771} -> 0.411
[Pylon, Gateway, Gateway, Pylon, Pylon, Assimilator, CyberneticsCore] (1639) {2667.941} -> 0.476
[Pylon, Gateway, Gateway, Pylon, Pylon, Assimilator, Pylon, CyberneticsCore] (1432) {2679.69} -> 0.517
[Pylon, Gateway, Gateway, Pylon, Pylon, Pylon, Assimilator] (1740) {2504.192} -> 0.59
[Pylon, Gateway, Assimilator, CyberneticsCore, Pylon, Pylon] (2752) {3356.675} -> 0.492
[Pylon, Gateway, Assimilator, CyberneticsCore, Pylon, RoboticsFacility, Pylon, SingularityCharge] (1634) {3794.938} -> 0.504
[Pylon, Gateway, Assimilator, CyberneticsCore, Pylon, SingularityCharge, Pylon, RoboticsFacility] (2085) {3612.059} -> 0.507
[Pylon, Gateway, Assimilator, Pylon, CyberneticsCore, Pylon] (2707) {2918.882} -> 0.494
[Pylon, Gateway, Pylon, Assimilator] (1259) {2913.399} -> 0.518
