[Pylon, Gateway, Assimilator, Pylon, Pylon] (340) {2525.821} -> 0.546
[Pylon, Gateway, Assimilator, Pylon, Gateway, Pylon] (327) {2471.365} -> 0.635
[Pylon, Gateway, Assimilator, Pylon, CyberneticsCore, Pylon, RoboticsFacility] (535) {2562.377} -> 0.553
[Pylon, Gateway, Assimilator, Pylon, CyberneticsCore, Pylon, Gateway] (428) {2643.348} -> 0.49
[Pylon, Gateway, Assimilator, Pylon, CyberneticsCore, Gateway, Pylon] (469) {2539.99} -> 0.53
[Pylon, Gateway, Assimilator, CyberneticsCore, Pylon, Gateway] (428) {2268.365} -> 0.376
[Pylon, Gateway, Pylon, Assimilator, CyberneticsCore] (377) {2593.626} -> 0.586
[Pylon, Gateway, Gateway, Pylon, Assimilator, Pylon, CyberneticsCore, Pylon] (439) {2492.002} -> 0.498
[Pylon, Gateway, Gateway, Pylon, Assimilator, CyberneticsCore, Pylon] (321) {2318.619} -> 0.42
[Pylon, Gateway, Gateway, Pylon, Pylon, Assimilator, Pylon, CyberneticsCore] (413) {2303.989} -> 0.539
[Pylon, Gateway, Gateway, Pylon, Pylon, Assimilator, CyberneticsCore, Pylon] (429) {2367.054} -> 0.489
[Pylon, Gateway, Gateway, Pylon, Pylon, Pylon, Assimilator] (308) {2132.497} -> 0.486
