[Pylon, Gateway, Assimilator, Assimilator] (718) {3272.582} -> 0.484
[Pylon, Gateway, Assimilator, Pylon, CyberneticsCore] (808) {3185.557} -> 0.485
[Pylon, Gateway, Assimilator, CyberneticsCore, Pylon, Pylon, RoboticsFacility] (984) {3483.926} -> 0.493
[Pylon, Gateway, Assimilator, CyberneticsCore, Pylon, RoboticsFacility, Pylon, SingularityCharge, Observatory, Gateway] (604) {3917.774} -> 0.509
[Pylon, Gateway, Assimilator, CyberneticsCore, Pylon, RoboticsFacility, Pylon, RoboticsSupportBay, Pylon] (714) {3026.119} -> 0.494
[Pylon, Gateway, Assimilator, CyberneticsCore, Pylon, RoboticsFacility, SingularityCharge] (594) {3762.984} -> 0.471
[Pylon, Gateway, Assimilator, CyberneticsCore, Pylon, CitadelofAdun] (724) {2828.504} -> 0.547
[Pylon, Gateway, Assimilator, CyberneticsCore, Pylon, Gateway] (859) {2855.796} -> 0.431
[Pylon, Gateway, Assimilator, CyberneticsCore, Pylon, SingularityCharge, Pylon, RoboticsFacility, Pylon] (1111) {3530.065} -> 0.528
[Pylon, Gateway, Assimilator, CyberneticsCore, Pylon, SingularityCharge, Pylon, RoboticsFacility, Gateway, Pylon] (619) {3581.84} -> 0.497
[Pylon, Gateway, Assimilator, CyberneticsCore, Pylon, SingularityCharge, Pylon, Gateway] (699) {3258.126} -> 0.513
[Pylon, Gateway, Assimilator, CyberneticsCore, Pylon, SingularityCharge, Gateway, Pylon] (571) {3244.748} -> 0.453
[Pylon, Gateway, Assimilator, CyberneticsCore, Gateway, Pylon] (623) {2584.912} -> 0.636
