[Pylon, Gateway, Assimilator, Pylon, CyberneticsCore, Pylon, Stargate] (877) {3048.562} -> 0.517
[Pylon, Gateway, Assimilator, CyberneticsCore, Pylon, Stargate] (539) {3344.048} -> 0.476
[Pylon, Gateway, Pylon, Assimilator] (786) {3039.278} -> 0.496
[Pylon, Gateway, Gateway, Pylon, Assimilator, Pylon, CyberneticsCore, Pylon] (660) {2980.317} -> 0.398
[Pylon, Gateway, Gateway, Pylon, Assimilator, CyberneticsCore, Pylon] (775) {3033.868} -> 0.436
[Pylon, Gateway, Gateway, Pylon, Pylon, Assimilator, Pylon, CyberneticsCore, Pylon] (555) {2432.915} -> 0.582
[Pylon, Gateway, Gateway, Pylon, Pylon, Assimilator, CyberneticsCore, Pylon] (978) {2680.476} -> 0.5
[Pylon, Gateway, Gateway, Pylon, Pylon, Pylon, Assimilator, CyberneticsCore] (652) {2156.551} -> 0.643
[Pylon, Forge] (583) {3087.878} -> 0.504
[Pylon, Nexus, Forge] (599) {3312.798} -> 0.466
