[SupplyDepot, Barracks, Refinery, Factory, SupplyDepot, Starport, SupplyDepot, MachineShop] (364) {4165.512} -> 0.609
[SupplyDepot, Barracks, Refinery, Factory, SupplyDepot, Factory, Armory, SupplyDepot] (359) {4473.265} -> 0.519
[SupplyDepot, Barracks, Refinery, Factory, SupplyDepot, Factory, MachineShop, SupplyDepot] (291) {3858.593} -> 0.482
[SupplyDepot, Barracks, Refinery, Factory, SupplyDepot, Factory, SupplyDepot] (400) {3841.373} -> 0.516
[SupplyDepot, Barracks, Refinery, SupplyDepot, Factory, Starport, SupplyDepot] (357) {3906.366} -> 0.578
[SupplyDepot, Barracks, Refinery, SupplyDepot, Factory, Factory, Armory, SupplyDepot] (392) {4136.973} -> 0.468
[SupplyDepot, Barracks, Refinery, SupplyDepot, Factory, Factory, MachineShop] (385) {3682.025} -> 0.375
[SupplyDepot, Barracks, Refinery, SupplyDepot, Factory, Factory, SupplyDepot, Armory] (338) {3916.19} -> 0.52
[SupplyDepot, Barracks, Refinery, SupplyDepot, Factory, Factory, SupplyDepot, MachineShop] (379) {3896.727} -> 0.466
[SupplyDepot, Barracks, Refinery, SupplyDepot, Factory, Barracks] (327) {3662.719} -> 0.512
[SupplyDepot, Barracks, Refinery, SupplyDepot, Factory, SupplyDepot] (541) {3723.971} -> 0.484
[SupplyDepot, Refinery, Barracks] (300) {3455.322} -> 0.409
