[Barracks, SupplyDepot, Barracks, SupplyDepot] (874) {2691.155} -> 0.562
[Barracks, SupplyDepot, SupplyDepot] (909) {2704.345} -> 0.589
[SupplyDepot, Barracks, Barracks, Refinery, SupplyDepot] (975) {3258.327} -> 0.483
[SupplyDepot, Barracks, Barracks, SupplyDepot, Bunker, Refinery] (641) {2932.242} -> 0.492
[SupplyDepot, Barracks, Barracks, SupplyDepot, CommandCenter] (751) {4201.817} -> 0.508
[SupplyDepot, Barracks, Barracks, SupplyDepot, Refinery, Academy, SupplyDepot, StimPack, ComSat] (864) {3628.712} -> 0.535
[SupplyDepot, Barracks, Barracks, SupplyDepot, Refinery, SupplyDepot, Factory, Academy] (756) {3116} -> 0.528
[SupplyDepot, Barracks, Barracks, SupplyDepot, Refinery, SupplyDepot, Academy, SupplyDepot, StimPack] (691) {3930.174} -> 0.459
[SupplyDepot, Barracks, Barracks, SupplyDepot, SupplyDepot, Refinery, Academy] (716) {3208.874} -> 0.53
[SupplyDepot, Barracks, Refinery, SupplyDepot, Factory] (1210) {3186.68} -> 0.553
