[Extractor, SpawningPool, Hatchery] (638) {2551.763} -> 0.453
[Extractor, Hatchery, SpawningPool, Extractor, CreepColony] (624) {3308.043} -> 0.506
[Extractor, Hatchery, SpawningPool, CreepColony] (590) {2940.795} -> 0.46
[Extractor, Hatchery, SpawningPool, Hatchery] (526) {3089.539} -> 0.555
[SpawningPool, Extractor, MetabolicBoost, Hatchery] (709) {2769.772} -> 0.573
[SpawningPool, Extractor, Hatchery] (879) {3031.071} -> 0.544
[SpawningPool, Hatchery, Extractor] (1145) {2610.997} -> 0.53
[SpawningPool, Hatchery, Hatchery, Extractor] (780) {2869.663} -> 0.56
[SpawningPool, Hatchery, Hatchery, CreepColony] (637) {2784.977} -> 0.521
[Hatchery, SpawningPool, Extractor, CreepColony, CreepColony] (621) {3069.542} -> 0.462
[Hatchery, SpawningPool, Extractor, MetabolicBoost, Hatchery] (847) {3157.228} -> 0.571
[Hatchery, SpawningPool, Extractor, Hatchery] (909) {3398.869} -> 0.563
[Hatchery, SpawningPool, CreepColony, CreepColony] (707) {2783.274} -> 0.435
[Hatchery, SpawningPool, Hatchery, Extractor] (1461) {3337.654} -> 0.62
