[Pylon, Gateway, Gateway, Pylon, Assimilator, CyberneticsCore, Pylon] (4) {1798.5} -> 0.5
[Pylon, Gateway, Gateway, Pylon, Assimilator, Pylon, CyberneticsCore, Pylon] (4) {1789.333} -> 0.333
[Pylon, Gateway, Gateway, Pylon, Pylon, Assimilator, CyberneticsCore] (4) {1411.5} -> 0.5
[Pylon, Gateway, Gateway, Pylon, Pylon, Assimilator, Pylon, CyberneticsCore] (4) {1679.667} -> 0.333
[Pylon, Gateway, Gateway, Pylon, Pylon, Pylon] (6) {2531.75} -> 0.375
[Pylon, Gateway, Assimilator, Gateway] (6) {2487.333} -> 1
[Pylon, Gateway, Assimilator, CyberneticsCore, Pylon, RoboticsFacility, Pylon] (6) {3251.833} -> 0.5
[Pylon, Gateway, Assimilator, CyberneticsCore, Pylon, SingularityCharge, Pylon, Gateway] (5) {2483.8} -> 0.4
[Pylon, Gateway, Assimilator, CyberneticsCore, Pylon, SingularityCharge, Pylon, Pylon] (5) {2744.2} -> 0.6
[Pylon, Gateway, Assimilator, CyberneticsCore, Pylon, CitadelofAdun] (5) {1638.4} -> 0.2
[Pylon, Gateway, Assimilator, CyberneticsCore, Pylon, Pylon, RoboticsFacility] (5) {3324.8} -> 0.6
[Pylon, Gateway, Assimilator, Assimilator, CyberneticsCore, Pylon] (4) {3101.25} -> 0.25
[Pylon, Gateway, Assimilator, Pylon, CyberneticsCore, Pylon] (8) {2592} -> 0.375
