[Pylon, Gateway, Gateway, Pylon, Assimilator, Pylon, CyberneticsCore, Pylon, RoboticsFacility, Pylon] (3) {2978.333} -> 0.333
[Pylon, Gateway, Gateway, Pylon, Pylon, Assimilator, CyberneticsCore] (2) {3380.5} -> 0
[Pylon, Gateway, Gateway, Pylon, Pylon, Assimilator, Pylon, CyberneticsCore] (2) {2083.5} -> 0.5
[Pylon, Gateway, Assimilator, Gateway, Pylon, Assimilator, CyberneticsCore, Pylon, Pylon] (2) {1613.5} -> 0.5
[Pylon, Gateway, Assimilator, Gateway, Pylon, Assimilator, Pylon, CyberneticsCore] (2) {2614} -> 1
[Pylon, Gateway, Assimilator, CyberneticsCore, Pylon] (3) {2600.667} -> 0.333
[Pylon, Gateway, Assimilator, Assimilator, Pylon] (2) {2455.5} -> 0.5
[Pylon, Gateway, Assimilator, Pylon, ShieldBattery] (3) {1669.333} -> 1
[Pylon, Gateway, Assimilator, Pylon, CyberneticsCore, Pylon, Gateway, SingularityCharge, Pylon, RoboticsFacility] (2) {1616.5} -> 0.5
[Pylon, Gateway, Pylon, Assimilator] (2) {2919.5} -> 1
