[Pylon, Gateway, Assimilator, CyberneticsCore, Gateway, Pylon] (2) {2179.5} -> 0.5
[Pylon, Gateway, Assimilator, CyberneticsCore, Pylon, RoboticsFacility, SingularityCharge] (2) {3761.5} -> 1
[Pylon, Gateway, Assimilator, CyberneticsCore, Pylon, RoboticsFacility, Pylon, SingularityCharge] (2) {2864} -> 0.5
[Pylon, Gateway, Assimilator, CyberneticsCore, Pylon, RoboticsFacility, Pylon, Observatory] (2) {3997.5} -> 0.5
[Pylon, Gateway, Assimilator, CyberneticsCore, Pylon, SingularityCharge, Pylon, Gateway, RoboticsFacility, Pylon] (2) {2719.5} -> 0.5
[Pylon, Gateway, Assimilator, CyberneticsCore, Pylon, SingularityCharge, Pylon, Gateway, Pylon] (2) {2447.5} -> 0
[Pylon, Gateway, Assimilator, CyberneticsCore, Pylon, SingularityCharge, Pylon, Pylon, RoboticsFacility, Gateway, Pylon] (2) {1836.5} -> 0.5
[Pylon, Gateway, Assimilator, CyberneticsCore, Pylon, SingularityCharge, Pylon, Pylon, Pylon, RoboticsFacility, Gateway] (2) {3415} -> 0.5
[Pylon, Gateway, Assimilator, CyberneticsCore, Pylon, CitadelofAdun] (3) {1970} -> 0
[Pylon, Gateway, Assimilator, CyberneticsCore, Pylon, Pylon, RoboticsFacility, Pylon] (2) {3185.5} -> 1
[Pylon, Gateway, Assimilator, Assimilator, CyberneticsCore, Pylon, RoboticsFacility] (2) {1985.5} -> 0
[Pylon, Gateway, Assimilator, Assimilator, Assimilator] (2) {3638.5} -> 0.5
[Pylon, Gateway, Assimilator, Pylon, CyberneticsCore, Pylon] (2) {2867.5} -> 0.5
