[Pylon, Gateway, Gateway, Pylon] (24) {2252.333} -> 0.333
[Pylon, Gateway, Gateway, Pylon, Assimilator, CyberneticsCore, Pylon, CitadelofAdun] (2) {1463.5} -> 0.5
[Pylon, Gateway, Gateway, Pylon, Assimilator, Pylon, CyberneticsCore] (2) {949.75} -> 0.25
[Pylon, Gateway, Gateway, Pylon, Pylon, Assimilator, CyberneticsCore, Pylon, CitadelofAdun, Pylon] (2) {1009.25} -> 0.5
[Pylon, Gateway, Gateway, Pylon, Pylon, Assimilator, Pylon, CyberneticsCore] (3) {1600} -> 0.2
[Pylon, Gateway, Gateway, Pylon, Pylon, Pylon, Assimilator] (3) {2130.4} -> 0.4
[Pylon, Gateway, Gateway, Pylon, Pylon, Pylon, Pylon] (2) {2394.25} -> 0.25
[Pylon, Gateway, Assimilator, Gateway] (2) {3099} -> 1
[Pylon, Gateway, Assimilator, CyberneticsCore] (3) {4680.333} -> 1
[Pylon, Gateway, Assimilator, Pylon, CyberneticsCore, Pylon, Stargate] (3) {2377.333} -> 0
[Pylon, Gateway, Assimilator, Pylon, CyberneticsCore, Pylon, CitadelofAdun] (2) {3313} -> 1
[Pylon, Gateway, Forge] (2) {1234.5} -> 0
[Pylon, Gateway, Pylon, Assimilator, CyberneticsCore, Pylon, Stargate, RoboticsFacility, Pylon, Pylon, RoboticsSupportBay] (2) {2406.5} -> 0.5
