[Pylon, Gateway, Gateway, Pylon, Assimilator, CyberneticsCore, Pylon] (17) {2855.478} -> 0.565
[Pylon, Gateway, Gateway, Pylon, Assimilator, Pylon, CyberneticsCore, Pylon] (21) {2689.536} -> 0.393
[Pylon, Gateway, Gateway, Pylon, Pylon, Assimilator, CyberneticsCore, Pylon] (18) {1884.679} -> 0.5
[Pylon, Gateway, Gateway, Pylon, Pylon, Assimilator, Pylon, CyberneticsCore] (26) {2500.405} -> 0.486
[Pylon, Gateway, Gateway, Pylon, Pylon, Pylon, Assimilator, CyberneticsCore] (19) {1900.312} -> 0.594
[Pylon, Gateway, Gateway, Pylon, Pylon, Pylon, Pylon] (21) {2395.697} -> 0.606
[Pylon, Gateway, Assimilator, CyberneticsCore, Pylon, SingularityCharge, Pylon] (26) {3684.269} -> 0.538
[Pylon, Gateway, Assimilator, Assimilator] (22) {3775.182} -> 0.455
[Pylon, Gateway, Assimilator, Pylon, CyberneticsCore, Pylon] (40) {3421.122} -> 0.537
[Pylon, Gateway, Pylon, Assimilator, CyberneticsCore, Pylon] (17) {2429.889} -> 0.556
