[Pylon, Gateway, Gateway, Pylon, Assimilator, CyberneticsCore, Pylon] (6) {2462.889} -> 0.333
[Pylon, Gateway, Gateway, Pylon, Assimilator, Pylon, CyberneticsCore, Pylon] (8) {3010.455} -> 0.273
[Pylon, Gateway, Gateway, Pylon, Pylon, Assimilator, CyberneticsCore, Pylon] (9) {1976.615} -> 0.538
[Pylon, Gateway, Gateway, Pylon, Pylon, Assimilator, Pylon, CyberneticsCore, Pylon] (7) {2417.455} -> 0.364
[Pylon, Gateway, Gateway, Pylon, Pylon, Pylon, Assimilator] (8) {1925.583} -> 0.667
[Pylon, Gateway, Gateway, Pylon, Pylon, Pylon, Pylon, Assimilator] (6) {1909.4} -> 0.4
[Pylon, Gateway, Assimilator, Gateway] (6) {1716.833} -> 0.333
[Pylon, Gateway, Assimilator, Pylon, CyberneticsCore, Pylon, SingularityCharge] (6) {3010.143} -> 0.571
[Pylon, Gateway, Assimilator, Pylon, Pylon, CyberneticsCore] (6) {2379.333} -> 0.667
[Pylon, Gateway, Pylon, Gateway, Pylon] (6) {2661.833} -> 0.5
[Pylon, Gateway, Pylon, Assimilator, CyberneticsCore, Pylon, SingularityCharge] (7) {3463} -> 0.857
[Pylon, Gateway, Pylon, Assimilator, Pylon, CyberneticsCore, Gateway, Pylon] (6) {3324.333} -> 0.167
[Pylon, Gateway, Pylon, Pylon] (12) {2457.25} -> 0.667
