[Pylon, Gateway, Gateway, Pylon, Pylon] (7) {2193.857} -> 0.714
[Pylon, Gateway, Assimilator, CyberneticsCore, Pylon, RoboticsFacility, Pylon, RoboticsSupportBay, Pylon] (5) {2760.8} -> 0.6
[Pylon, Gateway, Assimilator, CyberneticsCore, Pylon, SingularityCharge, Pylon, RoboticsFacility, Pylon] (5) {4149.8} -> 0.4
[Pylon, Gateway, Assimilator, CyberneticsCore, Pylon, SingularityCharge, Pylon, Gateway, RoboticsFacility, Pylon] (5) {2058.6} -> 0.2
[Pylon, Gateway, Assimilator, CyberneticsCore, Pylon, SingularityCharge, Pylon, Gateway, Pylon] (5) {3522.8} -> 0.8
[Pylon, Gateway, Assimilator, CyberneticsCore, Pylon, SingularityCharge, Pylon, Pylon] (5) {4806.6} -> 0.8
[Pylon, Gateway, Assimilator, CyberneticsCore, Pylon, Pylon, SingularityCharge] (6) {3580.167} -> 0.667
[Pylon, Gateway, Assimilator, Assimilator, CyberneticsCore, Pylon] (10) {3839.7} -> 0.5
[Pylon, Gateway, Assimilator, Assimilator, Pylon, CyberneticsCore] (6) {4274.667} -> 0.5
[Pylon, Gateway, Assimilator, Pylon, CyberneticsCore, Gateway, Pylon, SingularityCharge] (5) {2756.6} -> 0.8
[Pylon, Gateway, Assimilator, Pylon, CyberneticsCore, Pylon, SingularityCharge] (5) {3795.4} -> 0.4
[Pylon, Gateway, Assimilator, Pylon, CyberneticsCore, Pylon, Pylon] (5) {3515.4} -> 0.4
[Pylon, Gateway, Assimilator, Pylon, Pylon] (6) {4169} -> 0.833
[Pylon, Gateway, Pylon] (5) {2142} -> 0.6
[Pylon, Assimilator, Gateway, Assimilator] (7) {2926.857} -> 0.143
