[Pylon, Gateway, Gateway, Pylon, Assimilator, CyberneticsCore, Pylon] (14) {2708.278} -> 0.5
[Pylon, Gateway, Gateway, Pylon, Assimilator, Pylon, CyberneticsCore, Pylon, CitadelofAdun] (9) {2272.538} -> 0.385
[Pylon, Gateway, Gateway, Pylon, Pylon, Assimilator, CyberneticsCore, Pylon] (11) {1933.333} -> 0.444
[Pylon, Gateway, Gateway, Pylon, Pylon, Assimilator, Pylon, CyberneticsCore, Pylon] (9) {2092} -> 0.647
[Pylon, Gateway, Gateway, Pylon, Pylon, Pylon, Assimilator, CyberneticsCore, Pylon] (8) {1764.263} -> 0.684
[Pylon, Gateway, Gateway, Pylon, Pylon, Pylon, Pylon, Assimilator] (8) {2410.765} -> 0.706
[Pylon, Gateway, Assimilator, Pylon, CyberneticsCore, Pylon, Stargate, RoboticsFacility] (8) {4283.625} -> 0.625
[Pylon, Gateway, Pylon, Assimilator, CyberneticsCore, Pylon, Stargate] (9) {2892.9} -> 0.4
[Pylon, Forge] (13) {2767} -> 0.385
