[Extractor, SpawningPool, Extractor] (20) {2386.85} -> 0.45
[Extractor, SpawningPool, Hatchery, MetabolicBoost, Spire] (27) {2149.667} -> 0.519
[Extractor, Hatchery, SpawningPool, Extractor, CreepColony] (23) {2446.435} -> 0.565
[SpawningPool, Extractor, MetabolicBoost, Hatchery] (17) {2424.739} -> 0.609
[SpawningPool, Extractor, Hatchery, MetabolicBoost] (18) {1836.308} -> 0.615
[SpawningPool, Hatchery, Extractor] (39) {2914.955} -> 0.432
[SpawningPool, Hatchery, Hatchery, Extractor] (33) {3129.632} -> 0.632
[SpawningPool, Hatchery, Hatchery, CreepColony] (22) {3142.889} -> 0.481
[Hatchery, Extractor, SpawningPool] (17) {2419.588} -> 0.647
[Hatchery, SpawningPool, Extractor, CreepColony, CreepColony] (26) {2889.423} -> 0.615
[Hatchery, SpawningPool, Extractor, MetabolicBoost] (24) {2504.5} -> 0.792
[Hatchery, SpawningPool, CreepColony] (30) {2969.4} -> 0.6
[Hatchery, SpawningPool, Hatchery, Extractor, CreepColony] (18) {2930.1} -> 0.55
