[Extractor, SpawningPool, Extractor, Hatchery] (9) {2521.111} -> 0.444
[Extractor, Hatchery, SpawningPool, Extractor, CreepColony, CreepColony] (9) {2580.444} -> 0.667
[SpawningPool, Extractor, MetabolicBoost, Hatchery, Hatchery] (8) {1968.154} -> 0.538
[SpawningPool, Extractor, Hatchery, Hatchery] (10) {2122.933} -> 0.6
[SpawningPool, Hatchery, Extractor] (18) {2830.5} -> 0.364
[SpawningPool, Hatchery, CreepColony] (10) {2735.214} -> 0.143
[SpawningPool, Hatchery, Hatchery, Extractor, HydraliskDen] (8) {2346.667} -> 0.5
[SpawningPool, Hatchery, Hatchery, CreepColony, Extractor] (8) {2587.077} -> 0.308
[SpawningPool, Hatchery, Hatchery, Hatchery, Extractor] (9) {2586.077} -> 0.462
[Hatchery, SpawningPool, Extractor, CreepColony, CreepColony] (10) {2569.6} -> 0.8
[Hatchery, SpawningPool, Extractor, MetabolicBoost] (9) {2782} -> 0.889
[Hatchery, SpawningPool, CreepColony, Hatchery] (8) {2360.125} -> 0.625
[Hatchery, SpawningPool, Hatchery, Extractor] (15) {2797.375} -> 0.688
