[Extractor, SpawningPool, Hatchery, Hatchery, Extractor, CreepColony] (6) {2734} -> 0.333
[Extractor, Hatchery, SpawningPool, Extractor, CreepColony] (7) {2071} -> 0.429
[SpawningPool, Extractor, Hatchery, Extractor] (8) {2789.636} -> 0.727
[SpawningPool, Hatchery, Extractor, CreepColony] (7) {3667.25} -> 0.625
[SpawningPool, Hatchery, Extractor, Hatchery] (6) {2740} -> 0.571
[SpawningPool, Hatchery, Hatchery, Extractor, CreepColony, CreepColony] (6) {3373.429} -> 0.857
[SpawningPool, Hatchery, Hatchery, CreepColony] (6) {3883} -> 0.714
[Hatchery, SpawningPool, Extractor, CreepColony, CreepColony, CreepColony] (6) {3699.333} -> 0.5
[Hatchery, SpawningPool, CreepColony] (13) {3832.846} -> 0.692
[Hatchery, SpawningPool, Hatchery, Extractor, CreepColony, CreepColony, CreepColony] (6) {2632.714} -> 0.429
[Hatchery, SpawningPool, Hatchery, CreepColony] (7) {2730.25} -> 0.375
