[Pylon, Gateway, Gateway, Pylon, Pylon] (26) {2726.5} -> 0.462
[Pylon, Gateway, Assimilator, CyberneticsCore, Pylon, RoboticsFacility] (18) {3603.316} -> 0.421
[Pylon, Gateway, Assimilator, CyberneticsCore, Pylon, SingularityCharge, Gateway, Pylon] (19) {3464.25} -> 0.35
[Pylon, Gateway, Assimilator, CyberneticsCore, Pylon, SingularityCharge, Pylon, RoboticsFacility, Pylon] (40) {4074.024} -> 0.548
[Pylon, Gateway, Assimilator, CyberneticsCore, Pylon, SingularityCharge, Pylon, Nexus] (26) {4035.929} -> 0.5
[Pylon, Gateway, Assimilator, CyberneticsCore, Pylon, Pylon] (27) {3658.321} -> 0.536
[Pylon, Gateway, Assimilator, Pylon, CyberneticsCore, Pylon, Stargate] (17) {3697.111} -> 0.389
[Pylon, Gateway, Assimilator, Pylon, CyberneticsCore, Pylon, SingularityCharge] (26) {3530.741} -> 0.481
[Pylon, Gateway, Assimilator, Pylon, CyberneticsCore, Pylon, CitadelofAdun] (17) {3428.389} -> 0.5
[Pylon, Gateway, Pylon] (18) {3118.222} -> 0.556
[Pylon, Forge, Nexus, PhotonCannon] (24) {3331.56} -> 0.36
[Pylon, Forge, PhotonCannon, Nexus, Gateway] (25) {3792.16} -> 0.32
