[Pylon, Gateway, Gateway, Pylon, Pylon] (12) {2687.667} -> 0.417
[Pylon, Gateway, Assimilator, CyberneticsCore, Pylon, SingularityCharge, Pylon] (7) {3081.857} -> 0.286
[Pylon, Gateway, Assimilator, CyberneticsCore, Pylon, Pylon] (10) {2658.2} -> 0.6
[Pylon, Gateway, Assimilator, Pylon, CyberneticsCore, Gateway] (9) {2713.444} -> 0.222
[Pylon, Gateway, Assimilator, Pylon, CyberneticsCore, Pylon, RoboticsFacility, SingularityCharge, Pylon] (9) {2878.333} -> 0.444
[Pylon, Gateway, Assimilator, Pylon, CyberneticsCore, Pylon, SingularityCharge, RoboticsFacility, Gateway, Pylon, Pylon] (7) {3556.429} -> 0.857
[Pylon, Gateway, Assimilator, Pylon, CyberneticsCore, Pylon, SingularityCharge, RoboticsFacility, Pylon] (14) {3466.357} -> 0.429
[Pylon, Gateway, Assimilator, Pylon, CyberneticsCore, Pylon, SingularityCharge, Pylon] (11) {3444} -> 0.545
[Pylon, Gateway, Assimilator, Pylon, CyberneticsCore, Pylon, Pylon, SingularityCharge] (9) {3152.444} -> 0.444
[Pylon, Gateway, Assimilator, Pylon, Pylon, CyberneticsCore, Pylon, SingularityCharge] (9) {4050.889} -> 0.667
[Pylon, Gateway, Pylon, Assimilator, CyberneticsCore] (7) {2658.286} -> 0.429
[Pylon, Gateway, Pylon, Assimilator, Pylon] (7) {2743.286} -> 0.571
