[Pylon, Gateway, Assimilator, CyberneticsCore, Pylon, RoboticsFacility, Pylon, SingularityCharge, Pylon, Observatory] (8) {3106.667} -> 0.556
[Pylon, Gateway, Assimilator, CyberneticsCore, Pylon, SingularityCharge, Gateway, Pylon, Pylon] (11) {2785.25} -> 0.333
[Pylon, Gateway, Assimilator, CyberneticsCore, Pylon, SingularityCharge, Pylon, RoboticsFacility, Gateway, Pylon, Observatory] (11) {4912.692} -> 0.462
[Pylon, Gateway, Assimilator, CyberneticsCore, Pylon, SingularityCharge, Pylon, RoboticsFacility, Pylon, Gateway] (8) {3962.5} -> 0.6
[Pylon, Gateway, Assimilator, CyberneticsCore, Pylon, SingularityCharge, Pylon, RoboticsFacility, Pylon, Observatory, Nexus] (11) {3696.154} -> 0.692
[Pylon, Gateway, Assimilator, CyberneticsCore, Pylon, SingularityCharge, Pylon, Nexus, Gateway, Pylon] (8) {3331.5} -> 0.7
[Pylon, Gateway, Assimilator, CyberneticsCore, Pylon, SingularityCharge, Pylon, Nexus, Pylon] (11) {4034.154} -> 0.308
[Pylon, Gateway, Assimilator, CyberneticsCore, Pylon, SingularityCharge, Pylon, Gateway] (10) {2383.083} -> 0.583
[Pylon, Gateway, Assimilator, CyberneticsCore, Pylon, SingularityCharge, Pylon, Pylon] (11) {4119.923} -> 0.385
[Pylon, Gateway, Assimilator, CyberneticsCore, Pylon, CitadelofAdun] (10) {4245.545} -> 0.545
[Pylon, Gateway, Assimilator, CyberneticsCore, Pylon, Pylon, SingularityCharge] (14) {4451.333} -> 0.4
[Pylon, Gateway, Assimilator, Assimilator] (10) {2254.455} -> 0.636
[Pylon, Gateway, Assimilator, Pylon, CyberneticsCore] (13) {3056.357} -> 0.5
[Pylon, Assimilator, Gateway] (10) {3127.8} -> 0.4
