[Pylon, Nexus] (6) {3719.667} -> 0.667
[Pylon, Gateway, Gateway, Pylon, Pylon, Pylon] (9) {2366.444} -> 0.667
[Pylon, Gateway, Assimilator, CyberneticsCore, Pylon, Stargate] (6) {4593.833} -> 0.5
[Pylon, Gateway, Assimilator, Pylon, CyberneticsCore, Pylon, Stargate, CitadelofAdun, Pylon, TemplarArchives] (6) {4410.333} -> 0.667
[Pylon, Gateway, Assimilator, Pylon, CyberneticsCore, Pylon, CitadelofAdun, Gateway, Pylon, TemplarArchives, LegEnhancement, Pylon] (8) {4013.625} -> 0.75
[Pylon, Forge, Nexus, Gateway] (8) {4532.556} -> 0.444
[Pylon, Forge, Nexus, PhotonCannon, Gateway, Assimilator] (8) {2986.444} -> 0.444
[Pylon, Forge, Nexus, PhotonCannon, PhotonCannon, Gateway, Assimilator, CyberneticsCore, Pylon] (7) {3401.625} -> 0.375
[Pylon, Forge, PhotonCannon, Nexus, Gateway, Assimilator, Pylon] (8) {3881.625} -> 0.5
[Pylon, Forge, PhotonCannon, Nexus, Gateway, Pylon, Assimilator, CyberneticsCore] (6) {5037.667} -> 0.167
[Pylon, Forge, PhotonCannon, PhotonCannon, Nexus, Gateway] (8) {2808.5} -> 0.5
[Pylon, Forge, Pylon, PhotonCannon] (11) {2938.636} -> 0.364
