[Extractor, SpawningPool, Hatchery] (22) {2667.227} -> 0.682
[SpawningPool, Extractor, MetabolicBoost, Spire] (26) {2106.833} -> 0.5
[SpawningPool, Extractor, MetabolicBoost, Hatchery, Hatchery] (15) {2668.852} -> 0.593
[SpawningPool, Extractor, Hatchery, Extractor] (15) {3320.85} -> 0.7
[SpawningPool, Extractor, Hatchery, MetabolicBoost, Spire] (18) {2044.792} -> 0.542
[SpawningPool, Extractor, Hatchery, Hatchery] (15) {3031} -> 0.65
[SpawningPool, Hatchery, Extractor, Hatchery, MetabolicBoost] (19) {3498.81} -> 0.476
[SpawningPool, Hatchery, Hatchery, Extractor, HydraliskDen] (15) {3260.882} -> 0.647
[Hatchery, SpawningPool, Extractor, CreepColony] (16) {2768.438} -> 0.562
[Hatchery, SpawningPool, Extractor, MetabolicBoost, Spire, Extractor, Hatchery] (18) {4074} -> 0.6
[Hatchery, SpawningPool, Extractor, Hatchery] (16) {3703.5} -> 0.438
[Hatchery, SpawningPool, Hatchery, Extractor, Extractor] (26) {5147.731} -> 0.615
[Hatchery, SpawningPool, Hatchery, Extractor, CreepColony] (16) {3860.438} -> 0.438
[Hatchery, SpawningPool, Hatchery, Extractor, MetabolicBoost] (20) {4683.6} -> 0.55
