[SpawningPool, Extractor, MetabolicBoost, Hatchery, Hatchery] (15) {3208.45} -> 0.55
[SpawningPool, Extractor, Hatchery, Extractor] (6) {3452.714} -> 0.571
[SpawningPool, Extractor, Hatchery, Hatchery] (9) {3598.3} -> 0.6
[SpawningPool, Hatchery, Extractor, Hatchery, MetabolicBoost, Spire, Hatchery] (7) {3514.7} -> 0.3
[SpawningPool, Hatchery, Hatchery, Extractor, HydraliskDen, CreepColony] (7) {3367.556} -> 0.556
[SpawningPool, Hatchery, Hatchery, Extractor, CreepColony] (6) {3414.5} -> 0.5
[SpawningPool, Hatchery, Hatchery, Extractor, MetabolicBoost, Spire, Hatchery] (6) {2722} -> 0.727
[SpawningPool, Hatchery, Hatchery, Hatchery, Extractor] (6) {3622.875} -> 0.625
[Hatchery, SpawningPool, Extractor, Hatchery] (7) {3670.286} -> 0.286
[Hatchery, SpawningPool, CreepColony, CreepColony] (7) {3862.571} -> 0.429
[Hatchery, SpawningPool, Hatchery, Extractor, MetabolicBoost] (6) {4785.333} -> 0.5
