[Pylon, Nexus, Forge] (249) -> 0.507
[Pylon, Gateway, Assimilator, Pylon, CyberneticsCore, Pylon] (290) -> 0.456
[Pylon, Gateway, Gateway, Pylon, Pylon, Pylon] (254) -> 0.305
[Pylon, Gateway, Pylon] (324) -> 0.524
[Pylon, Pylon] (395) -> 0.460
[Pylon, Forge, PhotonCannon, PhotonCannon, Nexus, Gateway, Pylon] (198) -> 0.449
[Pylon, Forge, PhotonCannon, Nexus, Gateway] (311) -> 0.437
[Pylon, Forge, Nexus, PhotonCannon, PhotonCannon] (221) -> 0.439
[Pylon, Forge, Nexus, PhotonCannon, Gateway] (219) -> 0.455
[Pylon, Forge, Nexus, Gateway] (407) -> 0.451
[Pylon, Forge, Pylon] (378) -> 0.498
[Pylon, Forge, Forge] (451) -> 0.422
