[Pylon, Gateway, Gateway, Pylon, Assimilator] (1) {2792} -> 0
[Pylon, Gateway, Gateway, Pylon, Pylon] (3) {3172.667} -> 1
[Pylon, Gateway, Assimilator, CyberneticsCore, Pylon, SingularityCharge] (2) {3995.5} -> 1
[Pylon, Gateway, Assimilator, CyberneticsCore, Pylon, CitadelofAdun] (1) {3476} -> 0
[Pylon, Gateway, Assimilator, Pylon, Gateway] (2) {1414} -> 0
[Pylon, Gateway, Assimilator, Pylon, CyberneticsCore, Gateway, SingularityCharge] (1) {2961} -> 1
[Pylon, Gateway, Assimilator, Pylon, CyberneticsCore, Gateway, Pylon] (2) {3373} -> 0
[Pylon, Gateway, Assimilator, Pylon, CyberneticsCore, Pylon, RoboticsFacility] (1) {6803} -> 0
[Pylon, Gateway, Assimilator, Pylon, CyberneticsCore, Pylon, CitadelofAdun] (2) {3237.5} -> 1
[Pylon, Gateway, Assimilator, Pylon, CyberneticsCore, Pylon, Pylon] (1) {5164} -> 1
[Pylon, Gateway, Assimilator, Pylon, Pylon] (3) {2484} -> 0
[Pylon, Gateway, Pylon, Gateway] (1) {4820} -> 1
[Pylon, Gateway, Pylon, Assimilator, CyberneticsCore] (1) {6091} -> 1
[Pylon, Gateway, Pylon, Assimilator, Pylon] (1) {3628} -> 0
