[Pylon, Nexus, Gateway, Forge, Pylon, PhotonCannon, Assimilator, Pylon] (2) {2530.5} -> 0.5
[Pylon, Nexus, Forge] (2) {3487} -> 1
[Pylon, Gateway, Assimilator, Pylon, CyberneticsCore, Pylon] (3) {2831.667} -> 0
[Pylon, Gateway, Pylon, Assimilator, CyberneticsCore, Pylon] (2) {1726.5} -> 0.5
[Pylon, Forge, Nexus, Gateway, PhotonCannon] (2) {5411} -> 1
[Pylon, Forge, Nexus, Gateway, Pylon] (2) {4795} -> 0
[Pylon, Forge, Nexus, PhotonCannon, Gateway, PhotonCannon] (2) {4652.5} -> 0.5
[Pylon, Forge, Nexus, PhotonCannon, PhotonCannon, Gateway, Assimilator] (2) {2911.5} -> 0.5
[Pylon, Forge, PhotonCannon, Nexus, Gateway, Pylon, Assimilator, CyberneticsCore, Stargate] (2) {3900.5} -> 1
[Pylon, Forge, PhotonCannon, Nexus, Gateway, Pylon, Assimilator, CyberneticsCore, PhotonCannon] (2) {3043.5} -> 0
[Pylon, Forge, PhotonCannon, Nexus, Pylon, Gateway, Assimilator] (2) {4728} -> 0.5
[Pylon, Forge, PhotonCannon, PhotonCannon, Nexus] (5) {3952.2} -> 0
[Pylon, Forge, PhotonCannon, PhotonCannon, Pylon] (3) {1332.333} -> 0.667
[Pylon, Forge, PhotonCannon, Pylon] (2) {1749.5} -> 0
[Pylon, Forge, Pylon] (3) {3393.667} -> 0
[Pylon, Pylon] (2) {4165.5} -> 0
