[Extractor] (2) {3784.5} -> 0
[SpawningPool] (14) {2339.571} -> 0.5
[SpawningPool, Extractor, MetabolicBoost] (1) {1255} -> 0.667
[SpawningPool, Extractor, Hatchery, Spire] (1) {788.333} -> 1
[SpawningPool, Extractor, Hatchery, MetabolicBoost] (1) {1284} -> 0.667
[SpawningPool, Extractor, Hatchery, Hatchery] (3) {2612.2} -> 0.4
[SpawningPool, Hatchery, Extractor] (1) {1337} -> 1
[SpawningPool, Hatchery, CreepColony] (1) {558} -> 1
[SpawningPool, Hatchery, Hatchery] (4) {1473} -> 0.667
[SpawningPool, Hatchery, Hatchery, Extractor, CreepColony] (2) {1475.4} -> 0.8
[SpawningPool, Hatchery, Hatchery, Extractor, CreepColony, Extractor] (1) {1475.4} -> 0.8
[SpawningPool, Hatchery, Hatchery, Extractor, Hatchery] (1) {839.75} -> 0.75
[Hatchery, SpawningPool, Extractor, Extractor] (1) {2306} -> 0
[Hatchery, SpawningPool, Extractor, MetabolicBoost, HydraliskDen] (1) {7040} -> 1
[Hatchery, SpawningPool, Extractor, MetabolicBoost, Spire] (1) {3305} -> 0
[Hatchery, SpawningPool, Extractor, Hatchery, MetabolicBoost, CreepColony, Spire] (1) {2312} -> 1
[Hatchery, SpawningPool, Extractor, Hatchery, MetabolicBoost, CreepColony, CreepColony] (1) {1480} -> 0
[Hatchery, SpawningPool, Hatchery, Extractor, Extractor, CreepColony, CreepColony] (1) {2339} -> 0
[Hatchery, SpawningPool, Hatchery, Extractor, Extractor, CreepColony, MetabolicBoost] (1) {3292} -> 1
[Hatchery, SpawningPool, Hatchery, Extractor, Extractor, MetabolicBoost, HydraliskDen] (1) {1820} -> 0
[Hatchery, SpawningPool, Hatchery, Extractor, Extractor, MetabolicBoost, Spire] (3) {5121.333} -> 1
[Hatchery, SpawningPool, Hatchery, Extractor, CreepColony] (3) {3245} -> 1
[Hatchery, SpawningPool, Hatchery, Extractor, MetabolicBoost] (1) {1382} -> 1
[Hatchery, Hatchery] (1) {2628} -> 1
