[Pylon, Nexus, Gateway] (38) {3757.342} -> 0.684
[Pylon, Gateway, Gateway, Pylon, Pylon] (40) {2136.186} -> 0.395
[Pylon, Gateway, Assimilator, CyberneticsCore, Gateway] (26) {2384.448} -> 0.448
[Pylon, Gateway, Assimilator, CyberneticsCore, Pylon, SingularityCharge, Pylon, RoboticsFacility] (26) {3847.267} -> 0.433
[Pylon, Gateway, Assimilator, Pylon, CyberneticsCore, Pylon] (37) {3216.128} -> 0.333
[Pylon, Gateway, Pylon] (38) {2850.395} -> 0.447
[Pylon, Forge, Nexus, PhotonCannon, PhotonCannon, Gateway] (22) {4260.783} -> 0.652
[Pylon, Forge, PhotonCannon, Nexus, Gateway] (31) {3263.242} -> 0.424
[Pylon, Forge, PhotonCannon, PhotonCannon] (25) {2930.185} -> 0.37
[Pylon, Forge, Pylon, PhotonCannon] (32) {3651.121} -> 0.485
