[Pylon, Gateway, Gateway, Gateway] (9) {2128} -> 0.545
[Pylon, Gateway, Gateway, Pylon, Assimilator, Pylon] (9) {1794.455} -> 0.545
[Pylon, Gateway, Gateway, Pylon, Pylon, Pylon] (16) {2648.895} -> 0.421
[Pylon, Gateway, Assimilator, CyberneticsCore, Pylon, SingularityCharge, Pylon, Gateway] (10) {2359.818} -> 0.455
[Pylon, Gateway, Assimilator, Pylon, Gateway] (11) {2596.083} -> 0.333
[Pylon, Gateway, Assimilator, Pylon, CyberneticsCore, Gateway, Pylon] (10) {2892} -> 0.545
[Pylon, Gateway, Assimilator, Pylon, CyberneticsCore, Pylon, SingularityCharge, Gateway] (10) {3126.545} -> 0.636
[Pylon, Gateway, Assimilator, Pylon, CyberneticsCore, Pylon, SingularityCharge, Pylon] (9) {2814.1} -> 0.2
[Pylon, Gateway, Assimilator, Pylon, Pylon, CyberneticsCore, Pylon, SingularityCharge] (9) {2715.2} -> 0.5
[Pylon, Gateway, Pylon, Gateway] (9) {2418} -> 0.455
[Pylon, Gateway, Pylon, Assimilator] (12) {2581.786} -> 0.643
[Pylon, Gateway, Pylon, Pylon] (15) {2487.882} -> 0.412
