[Pylon, Nexus, Gateway, Assimilator, Pylon, CyberneticsCore] (8) {4060.875} -> 0.875
[Pylon, Gateway, Gateway, Pylon, Pylon] (8) {1146.556} -> 0.778
[Pylon, Gateway, Assimilator, CyberneticsCore, Gateway, SingularityCharge, Pylon, Pylon] (9) {2062.583} -> 0.417
[Pylon, Gateway, Assimilator, CyberneticsCore, Gateway, Pylon] (9) {2514.667} -> 0.417
[Pylon, Gateway, Assimilator, CyberneticsCore, Pylon, SingularityCharge, Gateway, Pylon] (9) {2009.333} -> 0.333
[Pylon, Gateway, Assimilator, CyberneticsCore, Pylon, SingularityCharge, Pylon, RoboticsFacility, Pylon] (16) {3275.632} -> 0.421
[Pylon, Gateway, Assimilator, CyberneticsCore, Pylon, SingularityCharge, Pylon, Nexus, Pylon] (9) {2776.214} -> 0.643
[Pylon, Gateway, Assimilator, CyberneticsCore, Pylon, SingularityCharge, Pylon, Gateway] (12) {3002.867} -> 0.467
[Pylon, Gateway, Assimilator, CyberneticsCore, Pylon, Pylon] (14) {3454.882} -> 0.412
[Pylon, Gateway, Assimilator, Assimilator] (11) {3376} -> 0.583
[Pylon, Gateway, Assimilator, Pylon, CyberneticsCore, Pylon] (9) {2950} -> 0.4
[Pylon, Gateway, Pylon, Assimilator] (8) {3446.5} -> 0.625
[Pylon, Assimilator, Gateway] (11) {3801} -> 0.545
