[Pylon, Nexus, Forge] (12) {3172.333} -> 0.667
[Pylon, Gateway, Gateway, Pylon, Pylon] (13) {1995.786} -> 0.286
[Pylon, Gateway, Forge] (10) {4772.4} -> 0.5
[Pylon, Forge, Nexus, PhotonCannon, Gateway, Assimilator] (14) {3723.133} -> 0.533
[Pylon, Forge, Nexus, PhotonCannon, PhotonCannon, Gateway, Assimilator, CyberneticsCore] (10) {3780} -> 0.636
[Pylon, Forge, Gateway] (12) {1987.077} -> 0.615
[Pylon, Forge, PhotonCannon, Nexus, Gateway, Pylon, Assimilator, CyberneticsCore] (12) {3296.6} -> 0.533
[Pylon, Forge, PhotonCannon, PhotonCannon, Nexus] (10) {3071.083} -> 0.5
[Pylon, Forge, PhotonCannon, Pylon, Nexus, Gateway] (10) {2366} -> 0.417
[Pylon, Forge, Pylon, PhotonCannon, PhotonCannon] (13) {2639.714} -> 0.429
