[Extractor, Hatchery] (11) {2898.727} -> 0.182
[SpawningPool, Extractor, MetabolicBoost, Hatchery, Hatchery, Hatchery] (12) {1712.913} -> 0.783
[SpawningPool, Extractor, Hatchery, Extractor, Hatchery, MetabolicBoost, Spire, Hatchery] (12) {3994.588} -> 0.647
[SpawningPool, Extractor, Hatchery, Hatchery] (16) {2984.05} -> 0.55
[SpawningPool, Hatchery, Extractor, Hatchery, MetabolicBoost, Spire, Hatchery] (14) {4209.526} -> 0.474
[SpawningPool, Hatchery, Hatchery, Extractor, MetabolicBoost, Spire, Hatchery, Hatchery] (12) {3166.85} -> 0.35
[SpawningPool, Hatchery, Hatchery, Extractor, Hatchery] (17) {3295.12} -> 0.36
[SpawningPool, Hatchery, Hatchery, Hatchery] (13) {3590.579} -> 0.474
[Hatchery, SpawningPool, Extractor, Hatchery, MetabolicBoost] (10) {3542.1} -> 0.7
[Hatchery, SpawningPool, Hatchery, Extractor] (22) {3687.318} -> 0.364
