[Extractor, SpawningPool] (8) {1927.5} -> 0.625
[Extractor, Hatchery] (7) {3686.286} -> 0.571
[SpawningPool, Extractor, MetabolicBoost, Hatchery] (10) {1324.133} -> 0.733
[SpawningPool, Extractor, Hatchery, MetabolicBoost] (7) {2015.545} -> 0.455
[SpawningPool, Hatchery, Extractor, Hatchery] (7) {2558.182} -> 0.455
[SpawningPool, Hatchery, Hatchery, Extractor] (9) {2912.923} -> 0.538
[Hatchery, Extractor, SpawningPool, MetabolicBoost, Spire, Extractor] (9) {4857.778} -> 0.778
[Hatchery, SpawningPool, Extractor, CreepColony] (8) {5163.75} -> 0.25
[Hatchery, SpawningPool, Extractor, MetabolicBoost, Spire, Extractor] (7) {4225.375} -> 0.25
[Hatchery, SpawningPool, Extractor, Hatchery] (11) {3278.273} -> 0.545
[Hatchery, SpawningPool, Hatchery, Extractor, Extractor, MetabolicBoost] (9) {4720.556} -> 0.444
[Hatchery, SpawningPool, Hatchery, Extractor, CreepColony, HydraliskDen] (9) {3707.9} -> 0.5
[Hatchery, SpawningPool, Hatchery, Extractor, MetabolicBoost] (14) {4541.357} -> 0.429
[Hatchery, Hatchery, SpawningPool] (7) {6787.571} -> 0.429
