[Pylon, Nexus, Gateway, Assimilator] (70) {4185.264} -> 0.417
[Pylon, Gateway, Gateway, Pylon, Pylon] (74) {2294.519} -> 0.354
[Pylon, Gateway, Assimilator, CyberneticsCore, Gateway, SingularityCharge, Pylon, Pylon] (68) {3071.347} -> 0.611
[Pylon, Gateway, Assimilator, CyberneticsCore, Gateway, Pylon, SingularityCharge, Pylon, Pylon] (54) {2610.741} -> 0.534
[Pylon, Gateway, Assimilator, CyberneticsCore, Pylon, SingularityCharge, Gateway, Pylon] (55) {3398.15} -> 0.533
[Pylon, Gateway, Assimilator, CyberneticsCore, Pylon, SingularityCharge, Pylon, RoboticsFacility] (64) {4344.609} -> 0.493
[Pylon, Gateway, Assimilator, CyberneticsCore, Pylon, Gateway] (64) {3106.529} -> 0.441
[Pylon, Gateway, Assimilator, Pylon, CyberneticsCore, Pylon] (76) {3521.089} -> 0.582
[Pylon, Gateway, Pylon] (72) {2666.347} -> 0.56
[Pylon, Forge, Nexus, PhotonCannon] (69) {3536.292} -> 0.347
[Pylon, Forge, PhotonCannon, Nexus, Gateway] (78) {3666.309} -> 0.568
[Pylon, Forge, PhotonCannon, PhotonCannon, Nexus] (55) {3650.051} -> 0.559
[Pylon, Forge, Pylon] (68) {3439.423} -> 0.535
