[Pylon, Gateway, Gateway, Pylon, Assimilator, Pylon] (19) {2672.952} -> 0.524
[Pylon, Gateway, Gateway, Pylon, Pylon, Assimilator] (27) {2415.643} -> 0.321
[Pylon, Gateway, Gateway, Pylon, Pylon, Pylon, Pylon] (21) {3069.13} -> 0.609
[Pylon, Gateway, Assimilator, CyberneticsCore, Pylon, SingularityCharge, Pylon, Gateway] (28) {3454.286} -> 0.464
[Pylon, Gateway, Assimilator, CyberneticsCore, Pylon, Gateway, Pylon] (20) {2149.857} -> 0.429
[Pylon, Gateway, Assimilator, Pylon, Gateway, Pylon] (21) {2712.333} -> 0.619
[Pylon, Gateway, Assimilator, Pylon, CyberneticsCore, Gateway, SingularityCharge] (19) {3020.5} -> 0.45
[Pylon, Gateway, Assimilator, Pylon, CyberneticsCore, Gateway, Pylon, SingularityCharge] (23) {3444.042} -> 0.5
[Pylon, Gateway, Assimilator, Pylon, CyberneticsCore, Pylon, SingularityCharge, RoboticsFacility] (19) {4103.474} -> 0.474
[Pylon, Gateway, Assimilator, Pylon, CyberneticsCore, Pylon, SingularityCharge, Gateway] (22) {2960.182} -> 0.545
[Pylon, Gateway, Assimilator, Pylon, Pylon, CyberneticsCore] (23) {2855.435} -> 0.435
[Pylon, Gateway, Pylon, Assimilator, CyberneticsCore, Pylon] (30) {3180.258} -> 0.516
