[Pylon, Nexus, Gateway, Assimilator, CyberneticsCore, Gateway] (27) {4771.259} -> 0.407
[Pylon, Nexus, Gateway, Assimilator, Pylon, CyberneticsCore] (31) {4074.29} -> 0.452
[Pylon, Gateway, Assimilator, CyberneticsCore, Gateway, SingularityCharge, Pylon, Pylon, Pylon] (48) {2902.16} -> 0.72
[Pylon, Gateway, Assimilator, CyberneticsCore, Gateway, Pylon, SingularityCharge, Pylon, Pylon] (53) {2719.055} -> 0.545
[Pylon, Gateway, Assimilator, CyberneticsCore, Pylon, SingularityCharge, Gateway, Pylon, Pylon] (33) {3733.917} -> 0.528
[Pylon, Gateway, Assimilator, CyberneticsCore, Pylon, SingularityCharge, Pylon, RoboticsFacility, Pylon] (38) {4304.878} -> 0.512
[Pylon, Gateway, Assimilator, CyberneticsCore, Pylon, SingularityCharge, Pylon, Nexus] (39) {3707.381} -> 0.381
[Pylon, Gateway, Assimilator, CyberneticsCore, Pylon, SingularityCharge, Pylon, Gateway] (32) {3070.486} -> 0.314
[Pylon, Gateway, Assimilator, CyberneticsCore, Pylon, SingularityCharge, Pylon, Pylon] (43) {3791.304} -> 0.652
[Pylon, Gateway, Assimilator, CyberneticsCore, Pylon, Gateway, SingularityCharge, Pylon] (34) {3760.889} -> 0.472
[Pylon, Gateway, Assimilator, CyberneticsCore, Pylon, Pylon] (28) {3646.433} -> 0.433
[Pylon, Gateway, Assimilator, Pylon, CyberneticsCore] (39) {3537.1} -> 0.425
