[Pylon, Nexus, Forge] (24) {3985.308} -> 0.423
[Pylon, Gateway, Gateway, Pylon, Pylon, Pylon] (19) {2091.957} -> 0.217
[Pylon, Forge, Nexus, Gateway] (39) {3716.524} -> 0.381
[Pylon, Forge, Nexus, PhotonCannon, PhotonCannon, Gateway, Assimilator] (28) {3392.484} -> 0.323
[Pylon, Forge, PhotonCannon, Nexus, Gateway, Assimilator, Pylon] (23) {3516.808} -> 0.538
[Pylon, Forge, PhotonCannon, Nexus, Gateway, Pylon, Assimilator, CyberneticsCore] (22) {3445.88} -> 0.6
[Pylon, Forge, PhotonCannon, Nexus, Pylon, Gateway] (20) {3496.826} -> 0.348
[Pylon, Forge, PhotonCannon, PhotonCannon, Nexus, Gateway, Pylon, Assimilator] (19) {3976.174} -> 0.565
[Pylon, Forge, PhotonCannon, PhotonCannon, Pylon, Nexus, Gateway] (19) {2897.522} -> 0.391
[Pylon, Forge, PhotonCannon, Pylon, Nexus, Gateway] (19) {3547.565} -> 0.565
[Pylon, Forge, Pylon, PhotonCannon] (44) {3631.979} -> 0.489
