[SupplyDepot, Barracks, Refinery, Barracks, Factory, SupplyDepot, MachineShop] (22) {4415.292} -> 0.5
[SupplyDepot, Barracks, Refinery, Factory, SupplyDepot, Factory, MachineShop] (29) {4335.484} -> 0.516
[SupplyDepot, Barracks, Refinery, Factory, SupplyDepot, SupplyDepot, MachineShop, SpiderMines] (25) {4069.519} -> 0.444
[SupplyDepot, Barracks, Refinery, Factory, SupplyDepot, MachineShop, CommandCenter] (23) {4559.92} -> 0.52
[SupplyDepot, Barracks, Refinery, Factory, SupplyDepot, MachineShop, SupplyDepot] (40) {4015.571} -> 0.5
[SupplyDepot, Barracks, Refinery, SupplyDepot, Barracks, Factory] (44) {4275.5} -> 0.696
[SupplyDepot, Barracks, Refinery, SupplyDepot, Factory, Barracks] (44) {4118.383} -> 0.511
[SupplyDepot, Barracks, Refinery, SupplyDepot, Factory, Factory, MachineShop] (23) {2980.769} -> 0.577
[SupplyDepot, Barracks, Refinery, SupplyDepot, Factory, SupplyDepot, MachineShop, SpiderMines, SupplyDepot] (22) {4068.519} -> 0.63
[SupplyDepot, Barracks, Refinery, SupplyDepot, Factory, SupplyDepot, MachineShop, SupplyDepot, SpiderMines] (22) {3225.231} -> 0.654
[SupplyDepot, Barracks, Refinery, SupplyDepot, Factory, MachineShop, CommandCenter] (27) {4142.133} -> 0.3
[SupplyDepot, Refinery, Barracks] (22) {3531.261} -> 0.391
