[Barracks, SupplyDepot, Refinery] (17) {3805.706} -> 0.824
[SupplyDepot, Barracks, Barracks, SupplyDepot, Refinery] (21) {2878.217} -> 0.435
[SupplyDepot, Barracks, CommandCenter, SupplyDepot, Barracks] (17) {3995.824} -> 0.529
[SupplyDepot, Barracks, CommandCenter, SupplyDepot, Refinery] (28) {4762.75} -> 0.536
[SupplyDepot, Barracks, SupplyDepot, Barracks] (22) {3698.696} -> 0.696
[SupplyDepot, Barracks, SupplyDepot, CommandCenter, Barracks, Refinery] (15) {3455.812} -> 0.5
[SupplyDepot, Barracks, SupplyDepot, CommandCenter, SupplyDepot, Refinery] (15) {4117.294} -> 0.647
[SupplyDepot, Barracks, SupplyDepot, CommandCenter, Refinery] (39) {3693.55} -> 0.575
[SupplyDepot, Barracks, SupplyDepot, Bunker] (15) {2841.375} -> 0.375
[SupplyDepot, Barracks, Refinery, Factory, SupplyDepot] (26) {3500.444} -> 0.481
[SupplyDepot, Barracks, Refinery, SupplyDepot, Barracks, Factory] (15) {4098.867} -> 0.6
[SupplyDepot, Barracks, Refinery, SupplyDepot, Factory, Barracks] (21) {3348.174} -> 0.565
