[Extractor] (75) {2634.413} -> 0.44
[SpawningPool, Extractor, MetabolicBoost, Spire] (47) {1721.118} -> 0.618
[SpawningPool, Extractor, MetabolicBoost, Hatchery, Hatchery] (79) {3100.167} -> 0.579
[SpawningPool, Extractor, Hatchery, MetabolicBoost] (78) {2207.515} -> 0.583
[SpawningPool, Extractor, Hatchery, Hatchery] (51) {3182.289} -> 0.5
[SpawningPool, Hatchery, Extractor, Hatchery] (64) {2910.333} -> 0.44
[SpawningPool, Hatchery, Hatchery, Extractor] (112) {3186.91} -> 0.549
[Hatchery, SpawningPool, Extractor, CreepColony] (50) {2981.962} -> 0.462
[Hatchery, SpawningPool, Extractor, MetabolicBoost] (49) {3292.843} -> 0.314
[Hatchery, SpawningPool, Extractor, Hatchery] (79) {3891.519} -> 0.494
[Hatchery, SpawningPool, Hatchery, Extractor, Extractor] (43) {3991.864} -> 0.5
[Hatchery, SpawningPool, Hatchery, Extractor, CreepColony] (69) {3483.4} -> 0.5
