[Extractor] (24) {2910} -> 0.458
[SpawningPool, Extractor, MetabolicBoost, Hatchery, HydraliskDen] (27) {1669.156} -> 0.556
[SpawningPool, Extractor, MetabolicBoost, Hatchery, Hatchery, Spire] (24) {2960.814} -> 0.581
[SpawningPool, Extractor, Hatchery, MetabolicBoost] (19) {2105.065} -> 0.645
[SpawningPool, Extractor, Hatchery, Hatchery, Extractor] (32) {3436.773} -> 0.455
[SpawningPool, Hatchery, Extractor, Hatchery, MetabolicBoost] (26) {3201.583} -> 0.444
[SpawningPool, Hatchery, Hatchery, Extractor, CreepColony] (19) {2429.067} -> 0.367
[SpawningPool, Hatchery, Hatchery, Extractor, MetabolicBoost] (37) {3364.083} -> 0.583
[SpawningPool, Hatchery, Hatchery, Hatchery] (22) {2376.242} -> 0.606
[Hatchery, SpawningPool, Extractor, Hatchery] (31) {4838.742} -> 0.548
[Hatchery, SpawningPool, Hatchery, Extractor, MetabolicBoost] (23) {4568.304} -> 0.435
