[Pylon, Nexus, Gateway] (155) {3154.372} -> 0.596
[Pylon, Gateway, Gateway, Pylon, Pylon, Assimilator] (137) {2489.729} -> 0.497
[Pylon, Gateway, Gateway, Pylon, Pylon, Pylon] (256) {2704.339} -> 0.551
[Pylon, Gateway, Assimilator, CyberneticsCore, Gateway, Pylon, SingularityCharge, Pylon, Pylon] (149) {2805.36} -> 0.615
[Pylon, Gateway, Assimilator, CyberneticsCore, Pylon, SingularityCharge, Gateway, Pylon, Pylon] (139) {3332.223} -> 0.514
[Pylon, Gateway, Assimilator, CyberneticsCore, Pylon, SingularityCharge, Pylon] (277) {3715.588} -> 0.496
[Pylon, Gateway, Assimilator, CyberneticsCore, Pylon, Gateway] (156) {3260.865} -> 0.491
[Pylon, Gateway, Assimilator, Pylon, CyberneticsCore] (207) {2839.364} -> 0.514
[Pylon, Gateway, Pylon] (226) {2700.626} -> 0.491
[Pylon, Forge, Nexus, PhotonCannon] (119) {3062.675} -> 0.592
[Pylon, Forge, PhotonCannon, Nexus, Gateway] (167) {3574.731} -> 0.602
[Pylon, Forge, PhotonCannon, PhotonCannon] (174) {3183.382} -> 0.562
[Pylon, Forge, Pylon] (140) {3340.73} -> 0.532
