[Pylon, Gateway, Gateway, Pylon, Assimilator, CyberneticsCore] (54) {3036.214} -> 0.554
[Pylon, Gateway, Gateway, Pylon, Assimilator, Pylon, CyberneticsCore, Pylon] (61) {2917.234} -> 0.469
[Pylon, Gateway, Gateway, Pylon, Pylon, Nexus] (76) {3244.646} -> 0.532
[Pylon, Gateway, Gateway, Pylon, Pylon, Assimilator, CyberneticsCore, Pylon] (87) {2746.13} -> 0.489
[Pylon, Gateway, Gateway, Pylon, Pylon, Assimilator, Pylon, CyberneticsCore] (78) {2772.841} -> 0.524
[Pylon, Gateway, Gateway, Pylon, Pylon, Pylon, Nexus, Pylon] (51) {3301.582} -> 0.618
[Pylon, Gateway, Gateway, Pylon, Pylon, Pylon, Assimilator, CyberneticsCore] (51) {2584.764} -> 0.6
[Pylon, Gateway, Gateway, Pylon, Pylon, Pylon, Pylon] (90) {2868.904} -> 0.479
[Pylon, Gateway, Assimilator, CyberneticsCore, Gateway, Pylon] (67) {2550.735} -> 0.471
[Pylon, Gateway, Assimilator, CyberneticsCore, Pylon, Gateway] (94) {2604.568} -> 0.474
[Pylon, Gateway, Assimilator, Pylon, Gateway, Pylon] (61) {2459.683} -> 0.524
[Pylon, Gateway, Assimilator, Pylon, CyberneticsCore, Gateway, Pylon, SingularityCharge] (58) {2567.082} -> 0.557
[Pylon, Gateway, Assimilator, Pylon, CyberneticsCore, Pylon] (89) {2886.703} -> 0.56
[Pylon, Gateway, Pylon, Assimilator, CyberneticsCore] (79) {2706.775} -> 0.488
