[Pylon, Nexus, Gateway, Assimilator, Pylon, CyberneticsCore, Gateway] (51) {3362.056} -> 0.63
[Pylon, Gateway, Gateway, Pylon] (62) {1703.206} -> 0.429
[Pylon, Gateway, Assimilator, CyberneticsCore, Gateway, SingularityCharge, Pylon, Pylon, Pylon] (60) {3367.422} -> 0.594
[Pylon, Gateway, Assimilator, CyberneticsCore, Gateway, Pylon, SingularityCharge, Pylon, Pylon, Nexus] (47) {2662.194} -> 0.625
[Pylon, Gateway, Assimilator, CyberneticsCore, Pylon, SingularityCharge, Gateway, Pylon, Pylon, Nexus] (62) {3269.104} -> 0.537
[Pylon, Gateway, Assimilator, CyberneticsCore, Pylon, SingularityCharge, Pylon, RoboticsFacility] (59) {3562.206} -> 0.571
[Pylon, Gateway, Assimilator, CyberneticsCore, Pylon, SingularityCharge, Pylon, Nexus] (100) {3678.26} -> 0.538
[Pylon, Gateway, Assimilator, CyberneticsCore, Pylon, SingularityCharge, Pylon, Gateway] (80) {3632.619} -> 0.476
[Pylon, Gateway, Assimilator, CyberneticsCore, Pylon, Gateway, SingularityCharge, Pylon, Pylon] (54) {3349.759} -> 0.569
[Pylon, Gateway, Assimilator, CyberneticsCore, Pylon, Pylon] (59) {3040.063} -> 0.381
[Pylon, Gateway, Assimilator, Assimilator] (54) {2771.931} -> 0.655
[Pylon, Gateway, Assimilator, Pylon, CyberneticsCore] (102) {3156.708} -> 0.585
[Pylon, Gateway, Pylon] (62) {3131.778} -> 0.54
