[Barracks, SupplyDepot] (123) {3156.61} -> 0.496
[SupplyDepot, Barracks, Barracks, SupplyDepot] (198) {3392.126} -> 0.425
[SupplyDepot, Barracks, CommandCenter, SupplyDepot] (89) {3817.232} -> 0.505
[SupplyDepot, Barracks, SupplyDepot, CommandCenter, Refinery] (117) {3798.731} -> 0.631
[SupplyDepot, Barracks, Refinery, Factory, SupplyDepot, SupplyDepot, MachineShop] (85) {3721.219} -> 0.49
[SupplyDepot, Barracks, Refinery, Factory, SupplyDepot, MachineShop] (99) {3787.136} -> 0.418
[SupplyDepot, Barracks, Refinery, SupplyDepot, Factory, Barracks] (177) {3658.01} -> 0.449
[SupplyDepot, Barracks, Refinery, SupplyDepot, Factory, Factory, MachineShop, SupplyDepot] (81) {3151.554} -> 0.446
[SupplyDepot, Barracks, Refinery, SupplyDepot, Factory, SupplyDepot, MachineShop, SpiderMines] (87) {3440.514} -> 0.477
[SupplyDepot, Barracks, Refinery, SupplyDepot, Factory, MachineShop] (138) {3949.414} -> 0.478
[SupplyDepot, Refinery, Barracks] (113) {3729.113} -> 0.487
