[SupplyDepot, Barracks, Refinery, Factory, SupplyDepot, Factory] (58) {2910.388} -> 0.463
[SupplyDepot, Barracks, Refinery, Factory, SupplyDepot, SupplyDepot, MachineShop, SpiderMines] (50) {3407.373} -> 0.458
[SupplyDepot, Barracks, Refinery, Factory, SupplyDepot, MachineShop, SupplyDepot] (50) {3462.525} -> 0.441
[SupplyDepot, Barracks, Refinery, SupplyDepot, Barracks, Factory] (53) {3293.29} -> 0.468
[SupplyDepot, Barracks, Refinery, SupplyDepot, Factory, Barracks, MachineShop] (63) {3664.208} -> 0.416
[SupplyDepot, Barracks, Refinery, SupplyDepot, Factory, Factory, MachineShop, SupplyDepot] (71) {2996.129} -> 0.459
[SupplyDepot, Barracks, Refinery, SupplyDepot, Factory, SupplyDepot, MachineShop, SpiderMines, SupplyDepot, CommandCenter] (52) {3454.239} -> 0.507
[SupplyDepot, Barracks, Refinery, SupplyDepot, Factory, SupplyDepot, MachineShop, SiegeTankMode] (61) {3595.533} -> 0.493
[SupplyDepot, Barracks, Refinery, SupplyDepot, Factory, MachineShop, CommandCenter] (61) {3818.747} -> 0.48
[SupplyDepot, Refinery, Barracks, SupplyDepot, Factory] (51) {3916.269} -> 0.596
