[Extractor, Hatchery, SpawningPool] (125) {3222.216} -> 0.472
[SpawningPool, Extractor, MetabolicBoost, Hatchery, Hatchery] (169) {2438.704} -> 0.585
[SpawningPool, Extractor, Hatchery, MetabolicBoost] (125) {2106.859} -> 0.5
[SpawningPool, Extractor, Hatchery, Hatchery] (125) {2814.153} -> 0.506
[SpawningPool, Hatchery, Extractor, Hatchery] (95) {2894.188} -> 0.436
[SpawningPool, Hatchery, Hatchery, Extractor] (248) {3522.421} -> 0.44
[Hatchery, SpawningPool, Extractor, MetabolicBoost] (91) {2514.535} -> 0.436
[Hatchery, SpawningPool, Extractor, Hatchery] (151) {3426.826} -> 0.447
[Hatchery, SpawningPool, CreepColony] (90) {2856.99} -> 0.34
[Hatchery, SpawningPool, Hatchery, Extractor, Extractor] (135) {3889.093} -> 0.493
[Hatchery, SpawningPool, Hatchery, Extractor, CreepColony] (204) {3502.192} -> 0.461
