[Extractor, Hatchery, SpawningPool] (68) {3080.691} -> 0.426
[SpawningPool, Extractor, MetabolicBoost, Hatchery, Hatchery] (145) {2924.816} -> 0.546
[SpawningPool, Extractor, Hatchery, MetabolicBoost] (60) {2635.43} -> 0.494
[SpawningPool, Extractor, Hatchery, Hatchery, Extractor] (58) {2929.688} -> 0.506
[SpawningPool, Hatchery, Extractor, Hatchery] (77) {3000.022} -> 0.44
[SpawningPool, Hatchery, Hatchery, Extractor, MetabolicBoost] (57) {3302.566} -> 0.539
[SpawningPool, Hatchery, Hatchery, Extractor, Hatchery] (50) {2998.464} -> 0.493
[SpawningPool, Hatchery, Hatchery, Hatchery, Extractor] (66) {3582.373} -> 0.446
[Hatchery, SpawningPool, Extractor, Hatchery] (83) {3644.407} -> 0.442
[Hatchery, SpawningPool, CreepColony] (69) {3018.239} -> 0.352
[Hatchery, SpawningPool, Hatchery, Extractor, CreepColony] (53) {3053.119} -> 0.441
[Hatchery, SpawningPool, Hatchery, Extractor, Hatchery] (57) {3370.635} -> 0.317
[Hatchery, SpawningPool, Hatchery, Hatchery, Extractor] (64) {3986.778} -> 0.389
