[Extractor, SpawningPool, Hatchery] (20) {1840.55} -> 0.45
[SpawningPool, Extractor, CreepColony] (36) {1750.293} -> 0.537
[SpawningPool, Extractor, MetabolicBoost] (186) {1826.298} -> 0.56
[SpawningPool, Extractor, MetabolicBoost, Spire] (94) {1775.992} -> 0.563
[SpawningPool, Extractor, MetabolicBoost, Spire, CreepColony, CreepColony] (27) {1584.088} -> 0.56
[SpawningPool, Extractor, MetabolicBoost, Spire, Hatchery] (21) {1539.973} -> 0.6
[SpawningPool, Extractor, MetabolicBoost, CreepColony, Spire] (30) {1590.652} -> 0.638
[SpawningPool, Extractor, MetabolicBoost, Hatchery] (19) {1192.412} -> 0.51
[SpawningPool, Extractor, Hatchery, MetabolicBoost, Spire] (43) {1687.414} -> 0.431
[SpawningPool, Extractor, Hatchery, MetabolicBoost, CreepColony] (20) {1553.686} -> 0.371
[SpawningPool, Hatchery, Extractor] (19) {2595.333} -> 0.381
[Hatchery, SpawningPool, Extractor, CreepColony] (38) {2469.171} -> 0.415
[Hatchery, SpawningPool, Extractor, MetabolicBoost, Spire] (26) {2100.757} -> 0.541
