[Pylon, Nexus] (2) {5862.5} -> 0
[Pylon, Gateway, Gateway, Pylon, Assimilator, Pylon, CyberneticsCore, Gateway, Pylon, SingularityCharge, Pylon, Stargate, Nexus, Pylon, Nexus, Assimilator, Pylon, Pylon, Pylon, Gateway, Pylon] (2) {465} -> 0.5
[Pylon, Gateway, Gateway, Pylon, Pylon] (3) {1205.667} -> 0.667
[Pylon, Gateway, Assimilator, CyberneticsCore, Gateway, Pylon, SingularityCharge] (2) {2618.5} -> 0.5
[Pylon, Gateway, Assimilator, CyberneticsCore, Pylon, SingularityCharge, Pylon, RoboticsFacility] (2) {2861.5} -> 0
[Pylon, Gateway, Assimilator, Pylon, CyberneticsCore, Gateway, SingularityCharge, Pylon, Pylon] (2) {1147} -> 0
[Pylon, Gateway, Assimilator, Pylon, CyberneticsCore, Gateway, Pylon] (3) {4296.667} -> 0.667
[Pylon, Gateway, Pylon] (2) {1658.5} -> 0
[Pylon, Forge, Nexus] (2) {3795} -> 0
[Pylon, Forge, PhotonCannon, Nexus, Pylon] (3) {2767} -> 0
[Pylon, Forge, PhotonCannon, PhotonCannon] (2) {4051.5} -> 1
[Pylon, Forge, Pylon] (2) {1426.5} -> 0
