[Pylon, Nexus] (2) {5862.5} -> 0
[Pylon, Gateway, Nexus] (1) {2128} -> 0
[Pylon, Gateway, Gateway, Pylon, Assimilator, Pylon, Gateway] (1) {7080} -> 0
[Pylon, Gateway, Gateway, Pylon, Assimilator, Pylon, CyberneticsCore, Gateway, Pylon, SingularityCharge, Pylon, Stargate, Nexus, Pylon, Nexus, Assimilator, Pylon, Pylon, Pylon, Gateway, Pylon] (2) {465} -> 0.5
[Pylon, Gateway, Assimilator, CyberneticsCore, Gateway, Pylon, SingularityCharge, RoboticsFacility] (1) {1040} -> 0
[Pylon, Gateway, Assimilator, CyberneticsCore, Gateway, Pylon, SingularityCharge, Pylon] (1) {4197} -> 1
[Pylon, Gateway, Assimilator, CyberneticsCore, Pylon, RoboticsFacility] (1) {6888} -> 1
[Pylon, Gateway, Assimilator, CyberneticsCore, Pylon, SingularityCharge] (2) {2861.5} -> 0
[Pylon, Gateway, Assimilator, Pylon] (2) {5479} -> 1
[Pylon, Gateway, Pylon] (1) {1792} -> 0
