[SupplyDepot, Barracks, Refinery, SupplyDepot, Factory, Barracks] (1) {5024} -> 1
[SupplyDepot, Barracks, Refinery, SupplyDepot, Factory, Factory] (2) {3955} -> 0
[SupplyDepot, Barracks, Refinery, SupplyDepot, Factory, MachineShop] (1) {4328} -> 1
