[Pylon, Gateway, Gateway, Pylon, Assimilator, CyberneticsCore] (79) {2500.169} -> 0.506
[Pylon, Gateway, Gateway, Pylon, Assimilator, Pylon, CyberneticsCore] (100) {2564.279} -> 0.365
[Pylon, Gateway, Gateway, Pylon, Pylon, Assimilator, CyberneticsCore, Pylon] (73) {2114.734} -> 0.606
[Pylon, Gateway, Gateway, Pylon, Pylon, Assimilator, Pylon, CyberneticsCore] (78) {2089.483} -> 0.686
[Pylon, Gateway, Gateway, Pylon, Pylon, Pylon, Assimilator] (121) {1864.157} -> 0.749
[Pylon, Gateway, Assimilator, CyberneticsCore, Pylon, RoboticsFacility, Pylon] (89) {3126.944} -> 0.629
[Pylon, Gateway, Assimilator, CyberneticsCore, Pylon, SingularityCharge, Pylon, RoboticsFacility] (99) {3201.081} -> 0.657
[Pylon, Gateway, Assimilator, CyberneticsCore, Pylon, Pylon] (89) {2969.056} -> 0.607
[Pylon, Gateway, Assimilator, Pylon, CyberneticsCore, Pylon] (201) {2896.348} -> 0.547
[Pylon, Gateway, Pylon] (117) {2575.863} -> 0.496
[Pylon, Forge] (74) {2247.595} -> 0.405
