[Pylon, Nexus, Gateway, Gateway, Pylon] (26) {2697.269} -> 0.731
[Pylon, Gateway, Gateway, Pylon, Assimilator, CyberneticsCore] (26) {2534.577} -> 0.5
[Pylon, Gateway, Gateway, Pylon, Assimilator, Pylon, CyberneticsCore, Pylon] (52) {2707.481} -> 0.462
[Pylon, Gateway, Gateway, Pylon, Pylon, Assimilator, CyberneticsCore, Pylon] (39) {2583.4} -> 0.375
[Pylon, Gateway, Gateway, Pylon, Pylon, Assimilator, Pylon, CyberneticsCore] (34) {2358.529} -> 0.5
[Pylon, Gateway, Gateway, Pylon, Pylon, Pylon] (48) {2640.896} -> 0.562
[Pylon, Gateway, Assimilator, CyberneticsCore, Pylon] (61) {2407.934} -> 0.41
[Pylon, Gateway, Assimilator, Pylon, Gateway, Pylon, CyberneticsCore, Pylon] (33) {2593.861} -> 0.556
[Pylon, Gateway, Assimilator, Pylon, CyberneticsCore, Gateway, Pylon] (28) {2577.036} -> 0.393
[Pylon, Gateway, Assimilator, Pylon, CyberneticsCore, Pylon, RoboticsFacility] (28) {3081.857} -> 0.464
[Pylon, Gateway, Assimilator, Pylon, CyberneticsCore, Pylon, SingularityCharge] (27) {2929.778} -> 0.444
[Pylon, Gateway, Assimilator, Pylon, CyberneticsCore, Pylon, Gateway] (45) {2627.2} -> 0.667
[Pylon, Gateway, Pylon, Assimilator] (44) {2962.591} -> 0.477
