[Pylon, Gateway, Gateway] (27) {2231.185} -> 0.556
[Pylon, Gateway, Assimilator, CyberneticsCore, Gateway, Pylon] (25) {2531.44} -> 0.8
[Pylon, Gateway, Assimilator, CyberneticsCore, Pylon, RoboticsFacility, Pylon, SingularityCharge] (35) {3209.229} -> 0.514
[Pylon, Gateway, Assimilator, CyberneticsCore, Pylon, SingularityCharge, Gateway, Pylon, Pylon] (24) {3256.667} -> 0.5
[Pylon, Gateway, Assimilator, CyberneticsCore, Pylon, SingularityCharge, Pylon, RoboticsFacility, Gateway, Pylon, Observatory, Pylon] (28) {3359.107} -> 0.75
[Pylon, Gateway, Assimilator, CyberneticsCore, Pylon, SingularityCharge, Pylon, RoboticsFacility, Pylon] (39) {3387.641} -> 0.692
[Pylon, Gateway, Assimilator, CyberneticsCore, Pylon, SingularityCharge, Pylon, Nexus, Pylon] (25) {3083.76} -> 0.72
[Pylon, Gateway, Assimilator, CyberneticsCore, Pylon, SingularityCharge, Pylon, Gateway, Pylon] (33) {2644.212} -> 0.606
[Pylon, Gateway, Assimilator, CyberneticsCore, Pylon, SingularityCharge, Pylon, Pylon] (34) {2908.471} -> 0.529
[Pylon, Gateway, Assimilator, CyberneticsCore, Pylon, Gateway, Pylon] (24) {2694.208} -> 0.5
[Pylon, Gateway, Assimilator, CyberneticsCore, Pylon, Pylon, SingularityCharge] (26) {2907.538} -> 0.692
[Pylon, Gateway, Assimilator, Assimilator, CyberneticsCore, Pylon] (24) {2675.042} -> 0.583
[Pylon, Gateway, Assimilator, Pylon, CyberneticsCore] (46) {2519.435} -> 0.717
