[Pylon, Gateway, Gateway, Pylon, Assimilator, CyberneticsCore, Pylon] (56) {2510.729} -> 0.458
[Pylon, Gateway, Gateway, Pylon, Assimilator, Pylon, CyberneticsCore] (64) {2622.134} -> 0.358
[Pylon, Gateway, Gateway, Pylon, Pylon, Assimilator, CyberneticsCore, Pylon] (53) {1998.534} -> 0.659
[Pylon, Gateway, Gateway, Pylon, Pylon, Assimilator, Pylon, CyberneticsCore] (63) {2109.618} -> 0.686
[Pylon, Gateway, Gateway, Pylon, Pylon, Pylon, Assimilator, CyberneticsCore] (41) {1622.21} -> 0.84
[Pylon, Gateway, Gateway, Pylon, Pylon, Pylon, Assimilator, Pylon] (38) {1390.698} -> 0.845
[Pylon, Gateway, Gateway, Pylon, Pylon, Pylon, Pylon] (44) {1369.58} -> 0.812
[Pylon, Gateway, Assimilator, Pylon, CyberneticsCore, Pylon, Stargate] (66) {2908.773} -> 0.53
[Pylon, Gateway, Pylon, Assimilator] (37) {2443.649} -> 0.514
[Pylon, Forge] (73) {2266.411} -> 0.411
