[Extractor, SpawningPool, Hatchery, MetabolicBoost] (76) {1807.608} -> 0.532
[Extractor, Hatchery, SpawningPool, Extractor, CreepColony] (91) {2920.742} -> 0.387
[SpawningPool, Extractor, MetabolicBoost, Hatchery] (86) {1898.265} -> 0.51
[SpawningPool, Extractor, Hatchery] (183) {2265.758} -> 0.453
[SpawningPool, Hatchery, Extractor] (159) {2210.459} -> 0.453
[SpawningPool, Hatchery, Hatchery, Extractor] (112) {2711.583} -> 0.606
[Hatchery, SpawningPool, Extractor, Extractor] (84) {2592.011} -> 0.415
[Hatchery, SpawningPool, Extractor, CreepColony, CreepColony] (141) {2383.465} -> 0.331
[Hatchery, SpawningPool, Extractor, MetabolicBoost] (136) {2275.034} -> 0.473
[Hatchery, SpawningPool, Extractor, Hatchery] (99) {2800.202} -> 0.422
[Hatchery, SpawningPool, CreepColony, CreepColony, CreepColony] (81) {1987.874} -> 0.211
[Hatchery, SpawningPool, Hatchery, Extractor] (139) {2840.443} -> 0.483
