[Extractor, SpawningPool, Hatchery] (38) {2339.263} -> 0.342
[Extractor, Hatchery, SpawningPool, Extractor, CreepColony] (50) {2985.42} -> 0.44
[Extractor, Hatchery, SpawningPool, CreepColony, CreepColony] (37) {2313.75} -> 0.425
[SpawningPool, Extractor, MetabolicBoost] (53) {2148.909} -> 0.455
[SpawningPool, Extractor, Hatchery] (50) {2464.538} -> 0.462
[SpawningPool, Hatchery, Extractor] (63) {2307.703} -> 0.484
[SpawningPool, Hatchery, Hatchery, Extractor, CreepColony] (41) {2871.045} -> 0.659
[SpawningPool, Hatchery, Hatchery, CreepColony] (56) {2721.746} -> 0.475
[Hatchery, SpawningPool, Extractor, CreepColony] (75) {2750.051} -> 0.359
[Hatchery, SpawningPool, Extractor, MetabolicBoost, Hatchery] (42) {2575.544} -> 0.386
[Hatchery, SpawningPool, Extractor, Hatchery] (63) {2919.515} -> 0.515
[Hatchery, SpawningPool, CreepColony, CreepColony, CreepColony, CreepColony] (39) {1723.208} -> 0.167
[Hatchery, SpawningPool, Hatchery, Extractor] (89) {2879.066} -> 0.527
[Hatchery, SpawningPool, Hatchery, CreepColony] (43) {2355.533} -> 0.511
