[Extractor, Hatchery, SpawningPool, Extractor, CreepColony] (36) {3121.757} -> 0.324
[SpawningPool, Extractor, MetabolicBoost] (35) {1946.842} -> 0.395
[SpawningPool, Extractor, Hatchery, Extractor] (40) {2244.311} -> 0.356
[SpawningPool, Hatchery, Extractor, CreepColony] (29) {2173.895} -> 0.421
[SpawningPool, Hatchery, Hatchery, Extractor] (28) {1982.714} -> 0.514
[Hatchery, SpawningPool, Extractor, Extractor, CreepColony, CreepColony] (27) {2456.333} -> 0.455
[Hatchery, SpawningPool, Extractor, CreepColony, Extractor] (32) {2667.341} -> 0.39
[Hatchery, SpawningPool, Extractor, CreepColony, HydraliskDen] (27) {2886.278} -> 0.472
[Hatchery, SpawningPool, Extractor, CreepColony, CreepColony, CreepColony] (44) {2201.526} -> 0.228
[Hatchery, SpawningPool, Extractor, Hatchery] (35) {2765.8} -> 0.3
[Hatchery, SpawningPool, CreepColony, Extractor] (32) {2208.59} -> 0.359
[Hatchery, SpawningPool, CreepColony, CreepColony] (31) {2143.474} -> 0.211
[Hatchery, SpawningPool, Hatchery, Extractor, CreepColony] (35) {2934.068} -> 0.409
