[Pylon, Nexus] (200) {3542.605} -> 0.5
[Pylon, Gateway, Gateway, Pylon, Assimilator, Pylon, CyberneticsCore] (195) {2870.966} -> 0.451
[Pylon, Gateway, Gateway, Pylon, Pylon, Assimilator, CyberneticsCore] (184) {2717.886} -> 0.457
[Pylon, Gateway, Gateway, Pylon, Pylon, Pylon] (374) {2625.985} -> 0.553
[Pylon, Gateway, Assimilator, CyberneticsCore, Pylon, Gateway] (226) {3562.738} -> 0.489
[Pylon, Gateway, Assimilator, CyberneticsCore, Pylon, Pylon] (200) {3570.616} -> 0.478
[Pylon, Gateway, Assimilator, CyberneticsCore, Pylon, SingularityCharge, Gateway, Pylon, Pylon] (198) {4207.931} -> 0.495
[Pylon, Gateway, Assimilator, CyberneticsCore, Pylon, SingularityCharge, Pylon, RoboticsFacility] (201) {4214.507} -> 0.551
[Pylon, Gateway, Assimilator, CyberneticsCore, Pylon, SingularityCharge, Pylon, Gateway] (252) {4165.953} -> 0.43
[Pylon, Gateway, Assimilator, Pylon, CyberneticsCore, Pylon] (524) {3487.612} -> 0.495
[Pylon, Gateway, Pylon, Assimilator, CyberneticsCore] (234) {3360.751} -> 0.523
[Pylon, Forge, PhotonCannon] (368) {3825.601} -> 0.503
