[Pylon, Gateway, Gateway, Pylon, Assimilator, Pylon, CyberneticsCore, Pylon] (73) {2737.095} -> 0.419
[Pylon, Gateway, Gateway, Pylon, Pylon, Assimilator, CyberneticsCore, Pylon] (63) {2673.864} -> 0.561
[Pylon, Gateway, Gateway, Pylon, Pylon, Assimilator, Pylon, CyberneticsCore] (67) {2586.31} -> 0.507
[Pylon, Gateway, Gateway, Pylon, Pylon, Pylon, Assimilator] (57) {2512.4} -> 0.5
[Pylon, Gateway, Assimilator, CyberneticsCore, Pylon, Gateway] (72) {2618.521} -> 0.425
[Pylon, Gateway, Assimilator, Pylon, Gateway, Pylon] (51) {2798.353} -> 0.627
[Pylon, Gateway, Assimilator, Pylon, CyberneticsCore, Gateway, Pylon] (80) {3208.988} -> 0.438
[Pylon, Gateway, Assimilator, Pylon, CyberneticsCore, Pylon, SingularityCharge] (83) {3283.566} -> 0.482
[Pylon, Gateway, Assimilator, Pylon, CyberneticsCore, Pylon, Gateway, SingularityCharge] (53) {3106.889} -> 0.463
[Pylon, Gateway, Assimilator, Pylon, Pylon] (84) {3118.345} -> 0.488
[Pylon, Gateway, Pylon, Assimilator, CyberneticsCore, Pylon] (106) {3207.383} -> 0.495
