[Pylon, Gateway, Gateway, Pylon, Assimilator] (119) {3328.331} -> 0.537
[Pylon, Gateway, Gateway, Pylon, Pylon] (83) {2785.212} -> 0.565
[Pylon, Gateway, Assimilator, CyberneticsCore, Gateway, Pylon] (81) {3810.807} -> 0.458
[Pylon, Gateway, Assimilator, CyberneticsCore, Pylon, RoboticsFacility, Pylon] (113) {3552.565} -> 0.417
[Pylon, Gateway, Assimilator, CyberneticsCore, Pylon, SingularityCharge, Gateway, Pylon, Pylon, Nexus] (90) {4285.298} -> 0.532
[Pylon, Gateway, Assimilator, CyberneticsCore, Pylon, SingularityCharge, Pylon, RoboticsFacility, Gateway, Pylon] (95) {4232.49} -> 0.551
[Pylon, Gateway, Assimilator, CyberneticsCore, Pylon, SingularityCharge, Pylon, Gateway, Pylon] (155) {4059.646} -> 0.456
[Pylon, Gateway, Assimilator, CyberneticsCore, Pylon, Gateway, SingularityCharge, Pylon] (110) {3990.554} -> 0.536
[Pylon, Gateway, Assimilator, CyberneticsCore, Pylon, Pylon] (178) {3633.633} -> 0.467
[Pylon, Gateway, Assimilator, Pylon, CyberneticsCore, Gateway] (85) {3222.345} -> 0.391
[Pylon, Gateway, Assimilator, Pylon, CyberneticsCore, Pylon] (142) {3835.75} -> 0.507
[Pylon, Gateway, Pylon, Assimilator, CyberneticsCore] (85) {3516.837} -> 0.616
