[Pylon, Nexus, Forge] (114) {3705.614} -> 0.491
[Pylon, Gateway, Gateway, Pylon, Assimilator, Pylon, CyberneticsCore] (106) {2995.398} -> 0.451
[Pylon, Gateway, Gateway, Pylon, Pylon, Assimilator, CyberneticsCore] (101) {2634.273} -> 0.417
[Pylon, Gateway, Gateway, Pylon, Pylon, Assimilator, Pylon, CyberneticsCore] (85) {2455.118} -> 0.496
[Pylon, Gateway, Gateway, Pylon, Pylon, Pylon, Assimilator] (144) {2447.548} -> 0.563
[Pylon, Gateway, Assimilator, Pylon, CyberneticsCore, Pylon, Stargate] (136) {3545.906} -> 0.496
[Pylon, Gateway, Pylon, Assimilator] (104) {3441.971} -> 0.467
[Pylon, Forge, Nexus, PhotonCannon] (95) {4184.295} -> 0.516
[Pylon, Forge, PhotonCannon, Nexus] (131) {4052.977} -> 0.508
[Pylon, Forge, PhotonCannon, PhotonCannon] (133) {3661.328} -> 0.448
[Pylon, Forge, PhotonCannon, Pylon] (85) {3821.674} -> 0.558
[Pylon, Forge, Pylon, PhotonCannon] (115) {3595.217} -> 0.574
