[SupplyDepot, Barracks, Refinery, Factory, SupplyDepot, Factory, MachineShop, SupplyDepot] (122) {4361.605} -> 0.488
[SupplyDepot, Barracks, Refinery, Factory, SupplyDepot, SupplyDepot, MachineShop, SpiderMines, SupplyDepot, CommandCenter] (84) {5269.756} -> 0.456
[SupplyDepot, Barracks, Refinery, Factory, SupplyDepot, MachineShop, SupplyDepot, SpiderMines, SupplyDepot] (85) {5157.433} -> 0.5
[SupplyDepot, Barracks, Refinery, SupplyDepot, Factory, Factory, SupplyDepot, MachineShop] (125) {3660.326} -> 0.452
[SupplyDepot, Barracks, Refinery, SupplyDepot, Factory, Factory, MachineShop, SupplyDepot] (182) {4033.22} -> 0.497
[SupplyDepot, Barracks, Refinery, SupplyDepot, Factory, SupplyDepot, MachineShop, SpiderMines, SupplyDepot, CommandCenter] (135) {4603.25} -> 0.527
[SupplyDepot, Barracks, Refinery, SupplyDepot, Factory, SupplyDepot, MachineShop, CommandCenter] (137) {4499.711} -> 0.57
[SupplyDepot, Barracks, Refinery, SupplyDepot, Factory, SupplyDepot, MachineShop, SupplyDepot] (110) {4564.959} -> 0.533
[SupplyDepot, Barracks, Refinery, SupplyDepot, Factory, MachineShop, SupplyDepot] (117) {4250.113} -> 0.468
[SupplyDepot, Refinery, Barracks, SupplyDepot] (87) {3867.011} -> 0.534
