[SupplyDepot, Barracks, Refinery, Factory, SupplyDepot, Factory, SupplyDepot] (24) {4476.292} -> 0.458
[SupplyDepot, Barracks, Refinery, Factory, SupplyDepot, Factory, MachineShop, SupplyDepot, SpiderMines, SupplyDepot] (29) {4665.931} -> 0.724
[SupplyDepot, Barracks, Refinery, Factory, SupplyDepot, Starport, SupplyDepot] (21) {4481.048} -> 0.571
[SupplyDepot, Barracks, Refinery, Factory, SupplyDepot, SupplyDepot] (27) {4852.704} -> 0.481
[SupplyDepot, Barracks, Refinery, Factory, SupplyDepot, MachineShop] (47) {5206} -> 0.468
[SupplyDepot, Barracks, Refinery, SupplyDepot, Factory, Factory, SupplyDepot, MachineShop] (57) {4326.017} -> 0.586
[SupplyDepot, Barracks, Refinery, SupplyDepot, Factory, Factory, MachineShop, SupplyDepot, IonThrusters] (21) {4073.5} -> 0.409
[SupplyDepot, Barracks, Refinery, SupplyDepot, Factory, SupplyDepot, MachineShop] (32) {4153.5} -> 0.324
[SupplyDepot, Refinery, Barracks, Factory, SupplyDepot] (21) {4063.524} -> 0.524
[SupplyDepot, Refinery, Barracks, SupplyDepot, Factory] (55) {5805.873} -> 0.527
