[Barracks, SupplyDepot, SupplyDepot, Bunker] (88) {3647.374} -> 0.582
[SupplyDepot, Barracks, Barracks, SupplyDepot, CommandCenter, SupplyDepot, Refinery, Academy] (115) {4719.232} -> 0.544
[SupplyDepot, Barracks, Barracks, SupplyDepot, CommandCenter, Refinery, Academy] (73) {5347.458} -> 0.554
[SupplyDepot, Barracks, Barracks, SupplyDepot, CommandCenter, Refinery, SupplyDepot, Academy] (127) {4702.504} -> 0.431
[SupplyDepot, Barracks, Barracks, SupplyDepot, SupplyDepot, CommandCenter, Refinery, Academy] (90) {4276.638} -> 0.571
[SupplyDepot, Barracks, Barracks, SupplyDepot, SupplyDepot, Refinery] (89) {3360.825} -> 0.476
[SupplyDepot, Barracks, Barracks, SupplyDepot, Refinery, Academy, SupplyDepot, StimPack, ComSat] (93) {4489.922} -> 0.524
[SupplyDepot, Barracks, Barracks, SupplyDepot, Refinery, SupplyDepot, Academy] (99) {3823.596} -> 0.541
[SupplyDepot, Barracks, Barracks, SupplyDepot, Bunker] (118) {3509.172} -> 0.469
[SupplyDepot, Barracks, Barracks, Refinery] (74) {3424.895} -> 0.487
[SupplyDepot, Barracks, SupplyDepot, Barracks] (107) {5341.907} -> 0.583
[SupplyDepot, Barracks, SupplyDepot, CommandCenter] (111) {4226.482} -> 0.518
[SupplyDepot, Barracks, Refinery, SupplyDepot, Factory] (97) {3850.5} -> 0.48
