[Extractor, Hatchery, SpawningPool, Extractor] (108) {3138.627} -> 0.427
[SpawningPool, Extractor, Hatchery] (111) {3007} -> 0.442
[SpawningPool, Hatchery, Extractor] (85) {2663.011} -> 0.522
[SpawningPool, Hatchery, Hatchery] (83) {3327.444} -> 0.433
[Hatchery, SpawningPool, Extractor, Extractor, CreepColony] (78) {3423.659} -> 0.537
[Hatchery, SpawningPool, Extractor, CreepColony, HydraliskDen] (92) {4020.673} -> 0.612
[Hatchery, SpawningPool, Extractor, CreepColony, CreepColony] (129) {3722.43} -> 0.348
[Hatchery, SpawningPool, Extractor, Hatchery, CreepColony] (85) {4114.854} -> 0.438
[Hatchery, SpawningPool, CreepColony] (112) {3385.759} -> 0.414
[Hatchery, SpawningPool, Hatchery, Extractor, CreepColony, Extractor, CreepColony] (100) {4172.826} -> 0.486
[Hatchery, SpawningPool, Hatchery, Extractor, CreepColony, CreepColony, Extractor] (72) {3910.123} -> 0.481
[Hatchery, SpawningPool, Hatchery, Extractor, CreepColony, CreepColony, CreepColony] (111) {4308.708} -> 0.45
[Hatchery, SpawningPool, Hatchery, CreepColony, Extractor, CreepColony] (89) {4375.629} -> 0.433
