[Extractor, Extractor, SpawningPool] (52) {2102.192} -> 0.346
[Extractor, SpawningPool, Hatchery, MetabolicBoost, Spire, Hatchery, Extractor] (48) {2077.052} -> 0.577
[Extractor, Hatchery, SpawningPool] (47) {1909.745} -> 0.447
[SpawningPool, Extractor, CreepColony] (58) {1983.583} -> 0.533
[SpawningPool, Extractor, MetabolicBoost, Spire] (46) {2048.211} -> 0.596
[SpawningPool, Extractor, MetabolicBoost, CreepColony] (47) {1620.379} -> 0.586
[SpawningPool, Extractor, MetabolicBoost, Hatchery, Spire] (58) {2175.506} -> 0.568
[SpawningPool, Extractor, Hatchery, Spire] (51) {2082.576} -> 0.593
[SpawningPool, Extractor, Hatchery, MetabolicBoost, Spire] (147) {2214.478} -> 0.584
[SpawningPool, Extractor, Hatchery, MetabolicBoost, Spire, Hatchery, Extractor] (47) {2141.079} -> 0.632
[SpawningPool, Hatchery, Extractor] (67) {2325.739} -> 0.449
[Hatchery, Extractor] (44) {2407.75} -> 0.455
[Hatchery, SpawningPool, Extractor, CreepColony] (70) {2145.162} -> 0.5
[Hatchery, SpawningPool, Extractor, MetabolicBoost, Spire] (72) {2263.405} -> 0.429
