[Pylon, Gateway, Gateway, Pylon, Assimilator, CyberneticsCore, Pylon, SingularityCharge] (18) {2929.381} -> 0.476
[Pylon, Gateway, Gateway, Pylon, Assimilator, Pylon, CyberneticsCore] (17) {2010.632} -> 0.316
[Pylon, Gateway, Gateway, Pylon, Pylon, Assimilator, CyberneticsCore, Pylon] (28) {3300.2} -> 0.4
[Pylon, Gateway, Gateway, Pylon, Pylon, Assimilator, Pylon, CyberneticsCore] (18) {3245.05} -> 0.4
[Pylon, Gateway, Gateway, Pylon, Pylon, Pylon, Assimilator] (20) {4238.957} -> 0.435
[Pylon, Gateway, Assimilator, CyberneticsCore, Pylon, SingularityCharge, Gateway, Pylon, Pylon] (15) {4844.25} -> 0.375
[Pylon, Gateway, Assimilator, CyberneticsCore, Pylon, SingularityCharge, Pylon, RoboticsFacility] (18) {4340.526} -> 0.526
[Pylon, Gateway, Assimilator, CyberneticsCore, Pylon, SingularityCharge, Pylon, Gateway] (18) {4098.789} -> 0.684
[Pylon, Gateway, Assimilator, CyberneticsCore, Pylon, Gateway] (18) {3466.389} -> 0.5
[Pylon, Gateway, Assimilator, Pylon, CyberneticsCore] (18) {2866.722} -> 0.5
[Pylon, Gateway, Forge] (15) {4109.867} -> 0.467
[Pylon, Gateway, Pylon, Assimilator, CyberneticsCore, Pylon] (20) {3247.7} -> 0.75
[Pylon, Forge] (25) {4213.4} -> 0.28
