[Pylon, Gateway, Gateway, Pylon, Assimilator, CyberneticsCore, Pylon, SingularityCharge, Pylon, Gateway] (8) {2118.778} -> 0.111
[Pylon, Gateway, Gateway, Pylon, Assimilator, CyberneticsCore, Pylon, SingularityCharge, Pylon, Pylon] (9) {2338.1} -> 0.9
[Pylon, Gateway, Gateway, Pylon, Assimilator, CyberneticsCore, Pylon, CitadelofAdun, TemplarArchives] (7) {2904} -> 0.714
[Pylon, Gateway, Gateway, Pylon, Assimilator, CyberneticsCore, Pylon, CitadelofAdun, Pylon, TemplarArchives, Pylon] (7) {2028} -> 1
[Pylon, Gateway, Gateway, Pylon, Assimilator, Pylon, CyberneticsCore, Pylon, SingularityCharge, Pylon] (7) {2570.429} -> 0.429
[Pylon, Gateway, Gateway, Pylon, Pylon, Assimilator, CyberneticsCore, Pylon, SingularityCharge, Pylon] (8) {3682.75} -> 0.625
[Pylon, Gateway, Gateway, Pylon, Pylon, Assimilator, Pylon, CyberneticsCore] (9) {3161.556} -> 0.444
[Pylon, Gateway, Gateway, Pylon, Pylon, Pylon, Assimilator] (11) {3217.727} -> 0.545
[Pylon, Gateway, Assimilator, Pylon, CyberneticsCore] (9) {1854.444} -> 0.556
[Pylon, Gateway, Pylon, Assimilator, CyberneticsCore] (9) {3433.333} -> 0.222
