[Pylon, Gateway, Gateway, Pylon, Pylon] (6) {2434} -> 0.833
[Pylon, Gateway, Assimilator, CyberneticsCore, Gateway, Pylon, SingularityCharge] (6) {1976.714} -> 0.714
[Pylon, Gateway, Assimilator, CyberneticsCore, Pylon, SingularityCharge, Gateway, Pylon, Pylon, RoboticsFacility, Pylon] (8) {4812.222} -> 0.222
[Pylon, Gateway, Assimilator, CyberneticsCore, Pylon, SingularityCharge, Pylon, RoboticsFacility, Pylon] (11) {4472} -> 0.583
[Pylon, Gateway, Assimilator, CyberneticsCore, Pylon, SingularityCharge, Pylon, Gateway, RoboticsFacility, Pylon] (6) {4397.857} -> 0.714
[Pylon, Gateway, Assimilator, CyberneticsCore, Pylon, SingularityCharge, Pylon, Gateway, Pylon] (8) {3784.444} -> 0.556
[Pylon, Gateway, Assimilator, CyberneticsCore, Pylon, Gateway, SingularityCharge, Pylon] (6) {2754.833} -> 0.667
[Pylon, Gateway, Assimilator, CyberneticsCore, Pylon, Pylon] (8) {4365.75} -> 1
[Pylon, Gateway, Assimilator, Assimilator, CyberneticsCore, Pylon] (7) {3343} -> 0.571
[Pylon, Gateway, Assimilator, Pylon, CyberneticsCore] (7) {2174.714} -> 0.857
[Pylon, Gateway, Forge, Pylon, PhotonCannon] (6) {2481.714} -> 0.429
