[Pylon, Gateway, Gateway, Pylon, Assimilator] (15) {4007.5} -> 0
[Pylon, Gateway, Gateway, Pylon, Pylon, Assimilator, CyberneticsCore, Pylon, CitadelofAdun] (6) {2760.125} -> 0.25
[Pylon, Gateway, Gateway, Pylon, Pylon, Assimilator, Pylon, CyberneticsCore] (10) {3366.167} -> 0.417
[Pylon, Gateway, Gateway, Pylon, Pylon, Forge, Pylon] (6) {3149.625} -> 0.625
[Pylon, Gateway, Gateway, Pylon, Pylon, Pylon, Assimilator, CyberneticsCore] (8) {2625.75} -> 0.667
[Pylon, Gateway, Gateway, Pylon, Pylon, Pylon, Forge] (8) {2772.545} -> 0.455
[Pylon, Gateway, Gateway, Pylon, Pylon, Pylon, Pylon] (8) {1582.273} -> 0.727
[Pylon, Gateway, Assimilator, Pylon, CyberneticsCore] (6) {4311.333} -> 0.167
[Pylon, Gateway, Forge] (6) {6218.5} -> 0.667
[Pylon, Gateway, Pylon, Assimilator, CyberneticsCore, Pylon, RoboticsFacility] (10) {3086.2} -> 0.8
[Pylon, Forge, PhotonCannon] (11) {3561.091} -> 0.455
