[Barracks, Barracks, SupplyDepot] (5) {2426.2} -> 0.2
[Barracks, SupplyDepot, Barracks, SupplyDepot, Refinery] (5) {4400.167} -> 0.333
[Barracks, SupplyDepot, SupplyDepot] (11) {4574.455} -> 0.455
[Barracks, SupplyDepot, Refinery, SupplyDepot] (5) {3379} -> 0.2
[Barracks, SupplyDepot, Bunker] (5) {3201.4} -> 0.4
[SupplyDepot, Barracks, Barracks, SupplyDepot, SupplyDepot, Refinery, Academy, SupplyDepot] (5) {3483} -> 0.375
[SupplyDepot, Barracks, Barracks, SupplyDepot, Refinery, Academy, SupplyDepot, Barracks] (5) {2454.889} -> 0.222
[SupplyDepot, Barracks, Barracks, SupplyDepot, Refinery, Academy, SupplyDepot, StimPack, ComSat, SupplyDepot] (5) {3042.889} -> 0.222
[SupplyDepot, Barracks, Barracks, SupplyDepot, Refinery, Academy, SupplyDepot, SupplyDepot] (6) {4102.3} -> 0.3
[SupplyDepot, Barracks, Barracks, SupplyDepot, Refinery, SupplyDepot, Academy, SupplyDepot] (6) {2941.7} -> 0.3
[SupplyDepot, Barracks, Barracks, SupplyDepot, Bunker, SupplyDepot, Refinery] (6) {3623.7} -> 0.5
[SupplyDepot, Barracks, Barracks, SupplyDepot, Bunker, Refinery] (7) {3057.9} -> 0.3
[SupplyDepot, Barracks, Barracks, Bunker, SupplyDepot] (5) {3184} -> 0.8
[SupplyDepot, Barracks, Refinery, SupplyDepot] (5) {3802.8} -> 0.4
