[Extractor, SpawningPool, Hatchery, MetabolicBoost, Spire] (2) {2070.5} -> 0.5
[SpawningPool, Extractor, Extractor] (2) {2593.5} -> 0.5
[SpawningPool, Extractor, CreepColony, Hatchery, Spire] (2) {1882.5} -> 0.25
[SpawningPool, Extractor, MetabolicBoost] (13) {2116.538} -> 0.462
[SpawningPool, Extractor, MetabolicBoost, Hatchery, Spire] (6) {1915.455} -> 0.455
[SpawningPool, Extractor, Hatchery, Extractor] (2) {1621.5} -> 0
[SpawningPool, Extractor, Hatchery, Spire] (2) {4590} -> 1
[SpawningPool, Extractor, Hatchery, MetabolicBoost, Spire] (7) {3192} -> 0.429
[SpawningPool, Extractor, Hatchery, MetabolicBoost, Spire, Hatchery, Hatchery] (2) {3352.4} -> 0.4
[SpawningPool, Extractor, Hatchery, MetabolicBoost, CreepColony] (2) {3969.5} -> 1
[SpawningPool, Hatchery, Extractor, MetabolicBoost, Spire] (3) {1727} -> 0.75
[Hatchery, SpawningPool, Extractor, MetabolicBoost] (3) {2146.333} -> 0.667
