[Pylon, Gateway, Gateway, Pylon, Assimilator, Pylon] (12) {1818.333} -> 0.333
[Pylon, Gateway, Gateway, Pylon, Pylon, Assimilator, CyberneticsCore, Pylon] (12) {3817.583} -> 0.417
[Pylon, Gateway, Gateway, Pylon, Pylon, Assimilator, Pylon, CyberneticsCore] (17) {2788.647} -> 0.294
[Pylon, Gateway, Gateway, Pylon, Pylon, Pylon, Assimilator, Pylon, CyberneticsCore] (11) {2354.067} -> 0.933
[Pylon, Gateway, Assimilator, CyberneticsCore, Pylon, SingularityCharge, Gateway, Pylon, Pylon] (12) {1991.167} -> 0.833
[Pylon, Gateway, Assimilator, CyberneticsCore, Pylon, SingularityCharge, Pylon, RoboticsFacility, Gateway, Pylon] (11) {3231.273} -> 0.909
[Pylon, Gateway, Assimilator, CyberneticsCore, Pylon, SingularityCharge, Pylon, RoboticsFacility, Pylon] (11) {4423.909} -> 0.727
[Pylon, Gateway, Assimilator, CyberneticsCore, Pylon, SingularityCharge, Pylon, Gateway] (15) {4328.733} -> 0.4
[Pylon, Gateway, Assimilator, CyberneticsCore, Pylon, Gateway] (16) {2769.312} -> 0.375
[Pylon, Gateway, Assimilator, CyberneticsCore, Pylon, Pylon] (17) {2565.353} -> 0.529
[Pylon, Gateway, Assimilator, Pylon] (22) {2320.955} -> 0.5
[Pylon, Gateway, Forge] (16) {2339.562} -> 0.562
[Pylon, Gateway, Pylon] (11) {2232.636} -> 0.364
[Pylon, Forge] (17) {1761.176} -> 0.588
