[Pylon, Gateway, Gateway, Pylon, Assimilator, Pylon, CyberneticsCore, Pylon, CitadelofAdun, Pylon, TemplarArchives] (4) {2004} -> 0.75
[Pylon, Gateway, Gateway, Pylon, Assimilator, Pylon, Pylon] (4) {1932} -> 0.75
[Pylon, Gateway, Gateway, Pylon, Pylon, Gateway] (5) {1331} -> 0.333
[Pylon, Gateway, Gateway, Pylon, Pylon, Assimilator, CyberneticsCore, Pylon] (6) {1703.429} -> 0.571
[Pylon, Gateway, Gateway, Pylon, Pylon, Assimilator, Pylon, CyberneticsCore, Pylon] (7) {1672} -> 0.25
[Pylon, Gateway, Gateway, Pylon, Pylon, Assimilator, Pylon, Pylon, CyberneticsCore] (5) {2561.833} -> 0.833
[Pylon, Gateway, Gateway, Pylon, Pylon, Pylon, Gateway, Pylon] (6) {1446.714} -> 0.857
[Pylon, Gateway, Gateway, Pylon, Pylon, Pylon, Assimilator, CyberneticsCore] (4) {1470.6} -> 0.4
[Pylon, Gateway, Gateway, Pylon, Pylon, Pylon, Assimilator, Pylon, CyberneticsCore, Pylon] (7) {2049.5} -> 0.75
[Pylon, Gateway, Gateway, Pylon, Pylon, Pylon, Pylon] (4) {1958.6} -> 0.8
[Pylon, Gateway, Assimilator, CyberneticsCore, Pylon, Gateway, Pylon, SingularityCharge] (4) {1483} -> 0.75
[Pylon, Gateway, Assimilator, Pylon, Gateway, Pylon, Pylon] (5) {1711.2} -> 0.6
[Pylon, Gateway, Assimilator, Pylon, CyberneticsCore] (5) {1692.2} -> 0.6
