[Pylon, Gateway, Gateway, Pylon] (5) {2804.2} -> 0.8
[Pylon, Gateway, Assimilator, CyberneticsCore, Gateway, Pylon, SingularityCharge, Pylon] (5) {2259.8} -> 0.4
[Pylon, Gateway, Assimilator, CyberneticsCore, Pylon, SingularityCharge, Gateway, Pylon, Pylon, RoboticsFacility] (6) {2235.667} -> 0.833
[Pylon, Gateway, Assimilator, CyberneticsCore, Pylon, SingularityCharge, Pylon, RoboticsFacility, Gateway, Pylon, Observatory, Pylon, Nexus, Pylon] (5) {2563.6} -> 1
[Pylon, Gateway, Assimilator, CyberneticsCore, Pylon, SingularityCharge, Pylon, RoboticsFacility, Pylon, Gateway] (5) {4196.6} -> 0.6
[Pylon, Gateway, Assimilator, CyberneticsCore, Pylon, SingularityCharge, Pylon, Gateway, RoboticsFacility, Pylon] (6) {4308.667} -> 0.333
[Pylon, Gateway, Assimilator, CyberneticsCore, Pylon, SingularityCharge, Pylon, Gateway, Pylon] (6) {4811.833} -> 0.333
[Pylon, Gateway, Assimilator, CyberneticsCore, Pylon, SingularityCharge, Pylon, Pylon] (7) {4197.286} -> 0.429
[Pylon, Gateway, Assimilator, CyberneticsCore, Pylon, Gateway, SingularityCharge, Pylon] (5) {2449.4} -> 0.6
[Pylon, Gateway, Assimilator, CyberneticsCore, Pylon, Pylon, RoboticsFacility] (6) {2513.167} -> 0.333
[Pylon, Gateway, Assimilator, CyberneticsCore, Pylon, Pylon, SingularityCharge] (6) {2417.333} -> 0.5
[Pylon, Gateway, Assimilator, Assimilator] (8) {2995.5} -> 0.375
[Pylon, Gateway, Assimilator, Pylon, CyberneticsCore] (6) {3911} -> 0.5
