[Pylon, Gateway, Gateway, Pylon, Assimilator, Pylon] (5) {2115.2} -> 0.4
[Pylon, Gateway, Gateway, Pylon, Pylon, Assimilator, CyberneticsCore, Pylon] (8) {4776.5} -> 0.375
[Pylon, Gateway, Gateway, Pylon, Pylon, Assimilator, Pylon, CyberneticsCore, Pylon] (6) {3271.167} -> 0.167
[Pylon, Gateway, Gateway, Pylon, Pylon, Assimilator, Pylon, Forge] (10) {2716.6} -> 0.8
[Pylon, Gateway, Gateway, Pylon, Pylon, Forge, Pylon] (5) {1705.6} -> 0.4
[Pylon, Gateway, Gateway, Pylon, Pylon, Pylon, Assimilator, Pylon] (11) {2250.5} -> 0.917
[Pylon, Gateway, Assimilator, Pylon] (7) {1454.143} -> 0.286
[Pylon, Gateway, Forge, Pylon] (8) {1917.25} -> 0.5
[Pylon, Gateway, Pylon] (7) {2621.571} -> 0.429
[Pylon, Forge, Pylon, PhotonCannon] (5) {2804.2} -> 0.6
