[Barracks, SupplyDepot] (9) {1554.222} -> 0.778
[SupplyDepot, Barracks, Barracks, SupplyDepot, SupplyDepot] (12) {2517.5} -> 0.5
[SupplyDepot, Barracks, Barracks, SupplyDepot, Refinery, Academy, SupplyDepot] (12) {2206.692} -> 0.692
[SupplyDepot, Barracks, Barracks, SupplyDepot, Refinery, SupplyDepot, Academy] (9) {2588.444} -> 0.778
[SupplyDepot, Barracks, Barracks, SupplyDepot, Bunker] (13) {2170.385} -> 0.692
[SupplyDepot, Barracks, Barracks, Refinery, SupplyDepot] (9) {1729.333} -> 0.444
[SupplyDepot, Barracks, Refinery, Barracks, Factory, SupplyDepot, Factory] (9) {3478.333} -> 0.222
[SupplyDepot, Barracks, Refinery, Factory, SupplyDepot, Barracks] (11) {4252.273} -> 0.727
[SupplyDepot, Barracks, Refinery, Factory, SupplyDepot, Factory, MachineShop] (9) {2639.9} -> 0.3
[SupplyDepot, Barracks, Refinery, Factory, SupplyDepot, MachineShop] (10) {2920.8} -> 0.1
[SupplyDepot, Barracks, Refinery, SupplyDepot, Barracks, Factory, Factory] (10) {4633.6} -> 0.6
[SupplyDepot, Barracks, Refinery, SupplyDepot, Factory, Barracks, Factory] (10) {2847.545} -> 0.455
[SupplyDepot, Barracks, Refinery, SupplyDepot, Factory, Factory, SupplyDepot, MachineShop] (11) {3383.583} -> 0.583
[SupplyDepot, Barracks, Refinery, SupplyDepot, Factory, Factory, MachineShop] (10) {2582.545} -> 0.364
[SupplyDepot, Barracks, Refinery, SupplyDepot, Factory, SupplyDepot] (9) {3887.5} -> 0.4
