[Barracks, SupplyDepot, Barracks, SupplyDepot, Refinery] (5) {1555} -> 0.6
[SupplyDepot, Barracks, Barracks, SupplyDepot, SupplyDepot, Refinery, Academy] (4) {1267.75} -> 0.25
[SupplyDepot, Barracks, Barracks, SupplyDepot, Refinery, Academy, SupplyDepot, Factory] (4) {1403} -> 0.8
[SupplyDepot, Barracks, Barracks, SupplyDepot, Refinery, Academy, SupplyDepot, StimPack, ComSat, SupplyDepot] (4) {2416.6} -> 0.6
[SupplyDepot, Barracks, Barracks, SupplyDepot, Refinery, SupplyDepot, Academy, SupplyDepot] (4) {2158.5} -> 0.75
[SupplyDepot, Barracks, Barracks, SupplyDepot, Refinery, SupplyDepot, Factory] (5) {2641.2} -> 0.4
[SupplyDepot, Barracks, Barracks, SupplyDepot, Bunker, Refinery] (5) {2634.167} -> 0.667
[SupplyDepot, Barracks, Barracks, Refinery, SupplyDepot] (9) {1729.333} -> 0.444
[SupplyDepot, Barracks, Barracks, Bunker, SupplyDepot] (6) {2607.667} -> 0.5
[SupplyDepot, Barracks, Refinery, Barracks, SupplyDepot] (5) {3237.8} -> 0.8
[SupplyDepot, Barracks, Refinery, Factory, SupplyDepot] (4) {2373.5} -> 0.25
[SupplyDepot, Barracks, Refinery, SupplyDepot, Factory] (4) {3965.75} -> 0.5
