[Pylon, Nexus, Gateway, Assimilator, Pylon, CyberneticsCore] (15) {3144.067} -> 0.8
[Pylon, Nexus, Forge] (15) {4052.8} -> 0.333
[Pylon, Gateway, Gateway, Pylon, Pylon, Nexus] (23) {3386.75} -> 0.417
[Pylon, Gateway, Gateway, Pylon, Pylon, Pylon] (30) {3242.194} -> 0.516
[Pylon, Gateway, Assimilator, CyberneticsCore, Gateway, Pylon] (13) {2287.214} -> 0.5
[Pylon, Gateway, Assimilator, CyberneticsCore, Pylon, SingularityCharge, Pylon] (28) {3582.414} -> 0.552
[Pylon, Gateway, Assimilator, Pylon] (14) {2313.929} -> 0.429
[Pylon, Gateway, Pylon, Nexus, Assimilator] (13) {4077.231} -> 0.538
[Pylon, Forge, Nexus, Pylon] (15) {3628.133} -> 0.6
[Pylon, Forge, PhotonCannon, Nexus] (15) {4049.333} -> 0.467
[Pylon, Forge, PhotonCannon, PhotonCannon] (20) {3895.85} -> 0.6
[Pylon, Forge, PhotonCannon, Pylon] (16) {4413.438} -> 0.562
