[Pylon, Gateway, Gateway, Pylon, Nexus, Pylon] (8) {3280.5} -> 0.375
[Pylon, Gateway, Gateway, Pylon, Assimilator, Pylon, CyberneticsCore, Pylon] (6) {1996.833} -> 0.5
[Pylon, Gateway, Gateway, Pylon, Pylon, Nexus, Assimilator, CyberneticsCore] (6) {4382.167} -> 0.5
[Pylon, Gateway, Gateway, Pylon, Pylon, Nexus, Assimilator, Pylon, CyberneticsCore, CitadelofAdun] (6) {3787.833} -> 0.333
[Pylon, Gateway, Gateway, Pylon, Pylon, Nexus, Pylon, Assimilator, CyberneticsCore] (9) {3316.889} -> 0.556
[Pylon, Gateway, Gateway, Pylon, Pylon, Nexus, Pylon, Pylon] (6) {3073} -> 0.333
[Pylon, Gateway, Gateway, Pylon, Pylon, Assimilator, CyberneticsCore, Pylon] (9) {3347.556} -> 0.444
[Pylon, Gateway, Gateway, Pylon, Pylon, Assimilator, Pylon, CyberneticsCore] (7) {2481} -> 0.429
[Pylon, Gateway, Gateway, Pylon, Pylon, Pylon, Nexus, Assimilator] (9) {4309} -> 0.444
[Pylon, Gateway, Gateway, Pylon, Pylon, Pylon, Assimilator] (12) {2363.583} -> 0.5
[Pylon, Gateway, Gateway, Pylon, Pylon, Pylon, Pylon, Pylon] (8) {2997.75} -> 0.5
[Pylon, Gateway, Assimilator, CyberneticsCore, Gateway, Pylon] (6) {2150.167} -> 0.5
[Pylon, Gateway, Assimilator, CyberneticsCore, Pylon] (10) {2803.5} -> 0.5
[Pylon, Gateway, Assimilator, Pylon, CyberneticsCore] (8) {2798.25} -> 0.375
[Pylon, Gateway, Pylon] (11) {2977.455} -> 0.273
