[Pylon, Nexus, Gateway, Assimilator, CyberneticsCore, Gateway, Pylon] (5) {2733.5} -> 0.5
[Pylon, Nexus, Gateway, Assimilator, Pylon, CyberneticsCore, Gateway, SingularityCharge, Pylon] (7) {2681.429} -> 0.714
[Pylon, Nexus, Gateway, Pylon] (5) {3435.8} -> 0.4
[Pylon, Gateway, Nexus, Pylon, Assimilator, CyberneticsCore, Gateway] (5) {2857} -> 0.4
[Pylon, Gateway, Gateway] (5) {2194.6} -> 0.6
[Pylon, Gateway, Assimilator, CyberneticsCore, Gateway, Pylon, SingularityCharge, Pylon, Pylon, Pylon] (7) {2114.625} -> 0.75
[Pylon, Gateway, Assimilator, CyberneticsCore, Pylon, Nexus] (5) {3597.833} -> 0.667
[Pylon, Gateway, Assimilator, CyberneticsCore, Pylon, SingularityCharge, Gateway, Pylon, Pylon] (8) {2981.778} -> 0.667
[Pylon, Gateway, Assimilator, CyberneticsCore, Pylon, SingularityCharge, Pylon, RoboticsFacility] (5) {3275.5} -> 0.833
[Pylon, Gateway, Assimilator, CyberneticsCore, Pylon, SingularityCharge, Pylon, Nexus, Pylon] (11) {3984.917} -> 0.5
[Pylon, Gateway, Assimilator, CyberneticsCore, Pylon, SingularityCharge, Pylon, Gateway, Pylon] (6) {2989.429} -> 0.571
[Pylon, Gateway, Assimilator, Pylon] (6) {2812.5} -> 0.5
[Pylon, Gateway, Pylon, Nexus, Assimilator, CyberneticsCore, Gateway] (5) {5107.4} -> 0.8
[Pylon, Gateway, Pylon, Nexus, Assimilator, CyberneticsCore, Pylon] (5) {4400} -> 0.4
[Pylon, Gateway, Pylon, Assimilator, CyberneticsCore, Pylon] (5) {3529.2} -> 1
