[Pylon, Nexus, Forge, Gateway] (7) {4682.571} -> 0.429
[Pylon, Nexus, Forge, PhotonCannon, Gateway] (6) {2956.5} -> 0.333
[Pylon, Gateway, Gateway, Pylon, Pylon] (9) {3502.667} -> 0.444
[Pylon, Gateway, Pylon, Nexus] (6) {2987.333} -> 0.667
[Pylon, Gateway, Pylon, Forge] (9) {4129.889} -> 0.333
[Pylon, Forge, Nexus, Gateway, Pylon] (6) {4761} -> 0.833
[Pylon, Forge, Nexus, PhotonCannon] (10) {3721.3} -> 0.1
[Pylon, Forge, Nexus, Pylon, Gateway, PhotonCannon] (6) {3453.667} -> 0.667
[Pylon, Forge, PhotonCannon, Nexus, Gateway, Pylon] (6) {4800.5} -> 0.667
[Pylon, Forge, PhotonCannon, Gateway] (9) {6233.111} -> 0.556
[Pylon, Forge, PhotonCannon, PhotonCannon, Nexus, Gateway] (6) {4234.167} -> 0.667
[Pylon, Forge, PhotonCannon, PhotonCannon, Pylon] (8) {4347.75} -> 0.75
[Pylon, Forge, PhotonCannon, Pylon, Nexus, Gateway, Assimilator] (7) {5676.5} -> 0.5
[Pylon, Forge, Pylon] (10) {3666.3} -> 1
