[Extractor] (4) {5240.25} -> 0.5
[SpawningPool, Extractor, MetabolicBoost] (12) {1530.538} -> 0.462
[SpawningPool, Extractor, MetabolicBoost, Hatchery] (5) {1676.727} -> 0.455
[SpawningPool, Extractor, Hatchery, Hatchery, Extractor] (4) {2090} -> 0.5
[SpawningPool, Hatchery, Hatchery, Extractor] (6) {4468.375} -> 0.625
[Hatchery, SpawningPool, Extractor, Hatchery] (4) {3765} -> 0.25
[Hatchery, SpawningPool, CreepColony, Hatchery] (4) {4412.25} -> 0
[Hatchery, SpawningPool, Hatchery, Extractor, Extractor, CreepColony] (8) {3355.75} -> 0.375
[Hatchery, SpawningPool, Hatchery, Extractor, CreepColony, Extractor, MetabolicBoost] (6) {3712.667} -> 0.667
[Hatchery, SpawningPool, Hatchery, Extractor, CreepColony, CreepColony] (4) {5721.5} -> 0.5
[Hatchery, SpawningPool, Hatchery, Extractor, MetabolicBoost] (4) {2629.5} -> 0.5
[Hatchery, SpawningPool, Hatchery, CreepColony] (5) {2720.6} -> 0.4
[Hatchery, Hatchery, SpawningPool, Extractor, Extractor] (5) {4592.5} -> 0.667
[Hatchery, Hatchery, SpawningPool, Extractor, CreepColony] (5) {3900.5} -> 0.667
