[Pylon, Gateway, Gateway, Forge, Pylon, PhotonCannon, PhotonCannon] (1) {3803} -> 0
[Pylon, Gateway, Gateway, Forge, Pylon, PhotonCannon, Pylon] (1) {3074} -> 1
[Pylon, Gateway, Gateway, Pylon] (2) {4342.5} -> 0
[Pylon, Gateway, Assimilator] (1) {926} -> 0
