[SupplyDepot, Barracks, Refinery, SupplyDepot, Factory, Factory, MachineShop, SupplyDepot, SpiderMines, Barracks] (1) {1441} -> 0
[SupplyDepot, Barracks, Refinery, SupplyDepot, Factory, Factory, MachineShop, SupplyDepot, SpiderMines, SiegeTankMode] (1) {1107} -> 0
[SupplyDepot, Barracks, Refinery, SupplyDepot, Factory, Factory, MachineShop, SupplyDepot, SpiderMines, SupplyDepot] (1) {3190} -> 1
