[Extractor] (1) {968} -> 1
[Hatchery, SpawningPool, Extractor, CreepColony] (2) {5571} -> 1
[Hatchery, SpawningPool, Extractor, MetabolicBoost] (1) {3106} -> 0
[Hatchery, SpawningPool, Hatchery] (1) {6125} -> 1
