[Pylon, Nexus] (9) {2691.333} -> 0.222
[Pylon, Gateway, Gateway, Pylon, Assimilator, Pylon] (11) {1731.667} -> 0.5
[Pylon, Gateway, Gateway, Pylon, Pylon, Assimilator] (15) {2526.75} -> 0.625
[Pylon, Gateway, Gateway, Pylon, Pylon, Pylon, Assimilator] (10) {1885} -> 0.385
[Pylon, Gateway, Assimilator, CyberneticsCore, Pylon, SingularityCharge] (17) {2203.944} -> 0.611
[Pylon, Gateway, Assimilator, Pylon, CyberneticsCore] (13) {2635.214} -> 0.429
[Pylon, Gateway, Pylon, Gateway, Pylon, Gateway] (8) {1383.25} -> 0.417
[Pylon, Forge, PhotonCannon, Nexus] (8) {2307.5} -> 0.5
