[Pylon, Nexus, Gateway, Gateway, Pylon] (3) {2749.667} -> 0.333
[Pylon, Gateway, Gateway, Gateway, Pylon, Pylon, Pylon, Pylon] (3) {2412.333} -> 0.667
[Pylon, Gateway, Gateway, Pylon, Gateway, Pylon, Pylon, Pylon] (3) {1563.333} -> 0.667
[Pylon, Gateway, Gateway, Pylon, Assimilator, CyberneticsCore, Pylon] (3) {2531} -> 0.667
[Pylon, Gateway, Gateway, Pylon, Pylon, Gateway, Pylon] (4) {2156.75} -> 0.5
[Pylon, Gateway, Gateway, Pylon, Pylon, Assimilator, CyberneticsCore, Pylon] (4) {1947.5} -> 0.5
[Pylon, Gateway, Gateway, Pylon, Pylon, Assimilator, Pylon, CyberneticsCore] (3) {2528.25} -> 0.75
[Pylon, Gateway, Gateway, Pylon, Pylon, Pylon, Assimilator] (4) {1228} -> 0.667
[Pylon, Gateway, Gateway, Pylon, Pylon, Pylon, Pylon] (7) {1685.222} -> 0.333
[Pylon, Gateway, Assimilator, CyberneticsCore, Pylon, SingularityCharge] (4) {2427} -> 0.5
[Pylon, Gateway, Assimilator, Pylon, CyberneticsCore] (3) {1590} -> 0.333
[Pylon, Gateway, Pylon, Gateway, Pylon] (3) {596.333} -> 0.667
[Pylon, Gateway, Pylon, Assimilator] (3) {1383.667} -> 0.667
[Pylon, Gateway, Pylon, Pylon, Pylon, Pylon] (3) {889.333} -> 0.667
[Pylon, Pylon] (3) {1411.667} -> 0.333
