[Pylon, Gateway, Gateway, Pylon, Assimilator, CyberneticsCore, Pylon] (3) {2420} -> 0.333
[Pylon, Gateway, Gateway, Pylon, Assimilator, Pylon] (3) {1449.667} -> 0.667
[Pylon, Gateway, Gateway, Pylon, Pylon] (6) {2015.833} -> 0.833
[Pylon, Gateway, Assimilator, CyberneticsCore, Gateway, SingularityCharge, Pylon, Pylon] (3) {2715} -> 0.333
[Pylon, Gateway, Assimilator, CyberneticsCore, Gateway, Pylon, SingularityCharge] (3) {4070.667} -> 1
[Pylon, Gateway, Assimilator, CyberneticsCore, Pylon, SingularityCharge, Gateway, Pylon] (4) {2477.25} -> 0.5
[Pylon, Gateway, Assimilator, CyberneticsCore, Pylon, SingularityCharge, Pylon, RoboticsFacility, Gateway, Pylon] (3) {2353} -> 0.667
[Pylon, Gateway, Assimilator, CyberneticsCore, Pylon, Gateway, SingularityCharge, Pylon] (4) {2790} -> 0.25
[Pylon, Gateway, Assimilator, CyberneticsCore, Pylon, Pylon] (5) {2171.2} -> 0.6
[Pylon, Gateway, Assimilator, Assimilator] (3) {3457.667} -> 0
[Pylon, Gateway, Assimilator, Pylon, CyberneticsCore, Gateway, SingularityCharge, Pylon] (3) {2059.667} -> 0.667
[Pylon, Gateway, Assimilator, Pylon, CyberneticsCore, Pylon, SingularityCharge] (3) {2068.333} -> 0.333
[Pylon, Gateway, Pylon, Pylon] (3) {1894.333} -> 0.667
[Pylon, Assimilator, Gateway] (3) {2161.667} -> 0.667
