[Pylon, Nexus] (5) {2577.4} -> 0.4
[Pylon, Gateway, Gateway, Pylon, Assimilator, Pylon] (6) {1725.571} -> 0.286
[Pylon, Gateway, Gateway, Pylon, Pylon, Gateway] (4) {1552.8} -> 0.4
[Pylon, Gateway, Gateway, Pylon, Pylon, Assimilator, Pylon] (4) {2122} -> 0.4
[Pylon, Gateway, Gateway, Pylon, Pylon, Pylon, Gateway] (4) {1291.667} -> 0.167
[Pylon, Gateway, Gateway, Pylon, Pylon, Pylon, Assimilator, CyberneticsCore] (5) {2117} -> 0.286
[Pylon, Gateway, Gateway, Pylon, Pylon, Pylon, Forge] (5) {1831.143} -> 0.714
[Pylon, Gateway, Assimilator] (4) {4341.2} -> 0
[Pylon, Gateway, Forge] (4) {1331} -> 0.2
[Pylon, Gateway, Pylon, Gateway, Pylon, Gateway] (6) {1359.5} -> 0.4
[Pylon, Forge, Nexus] (5) {2446.4} -> 0.2
[Pylon, Forge, PhotonCannon, Nexus, Gateway, Pylon] (5) {2299.8} -> 0.6
[Pylon, Forge, PhotonCannon, PhotonCannon] (6) {2971.5} -> 0.667
