[Pylon, Nexus] (1) {2031} -> 0
[Pylon, Gateway, Gateway, Pylon, Pylon, Assimilator, CyberneticsCore] (2) {1445.5} -> 0.5
[Pylon, Gateway, Gateway, Pylon, Pylon, Assimilator, CyberneticsCore, Pylon] (1) {1445.5} -> 0.5
[Pylon, Gateway, Assimilator, CyberneticsCore, Gateway] (1) {6377} -> 0
[Pylon, Gateway, Assimilator, CyberneticsCore, Pylon, SingularityCharge, Gateway, Pylon, CitadelofAdun] (1) {5015} -> 1
[Pylon, Gateway, Assimilator, CyberneticsCore, Pylon, SingularityCharge, Gateway, Pylon, Pylon] (2) {1999.5} -> 0
[Pylon, Gateway, Assimilator, CyberneticsCore, Pylon, SingularityCharge, Pylon, RoboticsFacility] (1) {6892} -> 0
[Pylon, Gateway, Assimilator, CyberneticsCore, Pylon, SingularityCharge, Pylon, Gateway] (1) {3849} -> 1
[Pylon, Gateway, Assimilator, CyberneticsCore, Pylon, SingularityCharge, Pylon, CitadelofAdun] (1) {2017} -> 0
[Pylon, Gateway, Assimilator, CyberneticsCore, Pylon, Gateway, SingularityCharge] (2) {1825} -> 1
[Pylon, Gateway, Assimilator, CyberneticsCore, Pylon, Gateway, Pylon, SingularityCharge, CitadelofAdun] (1) {2847} -> 1
[Pylon, Gateway, Assimilator, CyberneticsCore, Pylon, Gateway, Pylon, SingularityCharge, Pylon] (1) {5188} -> 0
[Pylon, Gateway, Assimilator, Pylon, CyberneticsCore, Gateway] (1) {989} -> 1
[Pylon, Gateway, Assimilator, Pylon, CyberneticsCore, CitadelofAdun] (1) {9155} -> 1
[Pylon, Gateway, Assimilator, Pylon, CyberneticsCore, Pylon, SingularityCharge] (1) {992} -> 0
[Pylon, Gateway, Assimilator, Pylon, CyberneticsCore, Pylon, Gateway] (1) {3194} -> 1
[Pylon, Gateway, Assimilator, Pylon, CyberneticsCore, Pylon, CitadelofAdun] (1) {5833} -> 1
[Pylon, Gateway, Assimilator, Pylon, Pylon] (1) {1995} -> 1
[Pylon, Gateway, Pylon] (2) {3426} -> 0
