[Extractor, SpawningPool, Extractor] (1) {1305} -> 0
[Extractor, SpawningPool, CreepColony] (1) {2645} -> 0
[Extractor, SpawningPool, Hatchery] (1) {4760} -> 1
[Extractor, Hatchery] (1) {3945} -> 0
[SpawningPool, Extractor, Extractor] (1) {1706} -> 1
[SpawningPool, Extractor, Spire] (1) {4168} -> 0
[SpawningPool, Extractor, CreepColony] (1) {2648} -> 1
[SpawningPool, Extractor, MetabolicBoost] (1) {847} -> 1
[SpawningPool, Extractor, Hatchery] (1) {514} -> 0
[Hatchery] (1) {2528} -> 1
