[Pylon, Gateway, Gateway, Pylon, Nexus] (2) {2280} -> 0
[Pylon, Gateway, Gateway, Pylon, Pylon, Nexus, Assimilator, Pylon, CyberneticsCore, Assimilator] (2) {3676.667} -> 0.333
[Pylon, Gateway, Gateway, Pylon, Pylon, Nexus, Pylon, Assimilator] (2) {2580} -> 0.333
[Pylon, Gateway, Gateway, Pylon, Pylon, Assimilator, CyberneticsCore, Pylon, SingularityCharge, Pylon] (2) {5233} -> 0.333
[Pylon, Gateway, Gateway, Pylon, Pylon, Pylon, Nexus, Pylon, Assimilator, CyberneticsCore] (2) {2452.333} -> 0.333
[Pylon, Gateway, Assimilator, CyberneticsCore, Pylon, Gateway, Pylon] (2) {3300} -> 0.5
[Pylon, Gateway, Pylon, Nexus] (3) {4194.667} -> 0.667
[Pylon, Gateway, Pylon, Gateway, Pylon] (2) {3481} -> 1
[Pylon, Gateway, Pylon, Assimilator, CyberneticsCore, Pylon] (3) {2057} -> 0.667
