[Pylon, Nexus, Forge, Gateway] (3) {4083.333} -> 0.667
[Pylon, Nexus, Forge, PhotonCannon, Pylon] (3) {3106.333} -> 1
[Pylon, Gateway, Gateway, Pylon] (5) {1682.4} -> 0.2
[Pylon, Forge, Nexus, PhotonCannon, PhotonCannon, Gateway, Assimilator] (3) {3926} -> 0
[Pylon, Forge, Nexus, PhotonCannon, PhotonCannon, Pylon, Gateway] (3) {3649} -> 0.333
[Pylon, Forge, PhotonCannon, Nexus, Gateway, Pylon, Assimilator] (3) {4088} -> 0.333
[Pylon, Forge, PhotonCannon, Nexus, PhotonCannon] (4) {3938.25} -> 0.25
[Pylon, Forge, PhotonCannon, Nexus, Pylon, Gateway] (3) {5946.667} -> 0.667
[Pylon, Forge, PhotonCannon, PhotonCannon, Nexus] (5) {3445.6} -> 0.4
[Pylon, Forge, PhotonCannon, PhotonCannon, Pylon, Nexus, Gateway, Assimilator, CyberneticsCore] (3) {3610} -> 0.333
[Pylon, Forge, Pylon] (4) {4713.25} -> 0.5
[Pylon, Pylon] (3) {3825} -> 0.667
