[SpawningPool, Extractor, MetabolicBoost, Hatchery, Hatchery, Hatchery] (3) {3725} -> 0.667
[SpawningPool, Extractor, Hatchery, MetabolicBoost, Hatchery] (3) {3402} -> 0.667
[SpawningPool, Extractor, Hatchery, Hatchery, Extractor, MetabolicBoost] (5) {4427.8} -> 1
[SpawningPool, Hatchery, Extractor] (3) {4308.333} -> 1
[SpawningPool, Hatchery, Hatchery, Extractor, CreepColony] (3) {2544.25} -> 0.5
[SpawningPool, Hatchery, Hatchery, Extractor, MetabolicBoost, Spire] (3) {4005.5} -> 0.75
[SpawningPool, Hatchery, Hatchery, Extractor, Hatchery] (4) {3570.4} -> 0.4
[SpawningPool, Hatchery, Hatchery, Hatchery, Extractor] (7) {4336.143} -> 0.429
[Hatchery, SpawningPool, Hatchery, Extractor] (6) {4315.667} -> 0.5
[Hatchery, SpawningPool, Hatchery, Hatchery] (3) {5152.333} -> 1
