[Pylon, Nexus, Forge] (8) {4533.75} -> 0.5
[Pylon, Gateway, Gateway, Pylon, Forge] (7) {1349.1} -> 0.3
[Pylon, Gateway, Gateway, Pylon, Pylon, Assimilator] (10) {2075.538} -> 0.308
[Pylon, Gateway, Assimilator, CyberneticsCore, Pylon, RoboticsFacility, Pylon] (10) {4486.091} -> 0.727
[Pylon, Gateway, Assimilator, CyberneticsCore, Pylon, SingularityCharge, Gateway, Pylon] (8) {2749.4} -> 0.4
[Pylon, Gateway, Assimilator, CyberneticsCore, Pylon, SingularityCharge, Pylon, RoboticsFacility, Gateway] (7) {3175.333} -> 0.333
[Pylon, Gateway, Assimilator, CyberneticsCore, Pylon, SingularityCharge, Pylon, RoboticsFacility, Pylon] (7) {3668.444} -> 0.444
[Pylon, Gateway, Assimilator, CyberneticsCore, Pylon, SingularityCharge, Pylon, Gateway] (8) {4082.3} -> 0.5
[Pylon, Gateway, Assimilator, CyberneticsCore, Pylon, Gateway] (9) {2950.2} -> 0.4
[Pylon, Gateway, Assimilator, CyberneticsCore, Pylon, Pylon] (14) {3142.267} -> 0.467
[Pylon, Gateway, Assimilator, Assimilator] (10) {3678.2} -> 0.4
[Pylon, Gateway, Assimilator, Pylon, CyberneticsCore] (13) {2753.077} -> 0.538
[Pylon, Gateway, Forge, Pylon] (8) {2351.75} -> 0.375
[Pylon, Gateway, Pylon] (8) {2611.125} -> 0.5
[Pylon, Assimilator] (8) {3443.625} -> 0.5
[Pylon, Forge] (13) {2860.462} -> 0.615
[Pylon, Pylon] (7) {2771.143} -> 0.429
