[Barracks, SupplyDepot] (5) {3379.4} -> 0.6
[SupplyDepot, Barracks, Barracks, SupplyDepot, Academy] (5) {3046.2} -> 0.8
[SupplyDepot, Barracks, Barracks, SupplyDepot, Barracks] (6) {1804} -> 0.667
[SupplyDepot, Barracks, Barracks, SupplyDepot, SupplyDepot, Refinery, Academy, SupplyDepot] (9) {2019.636} -> 0.818
[SupplyDepot, Barracks, Barracks, SupplyDepot, Refinery, Academy, SupplyDepot, StimPack, SupplyDepot, ComSat] (5) {3363.2} -> 0.8
[SupplyDepot, Barracks, Barracks, SupplyDepot, Refinery, Academy, SupplyDepot, StimPack, ComSat] (6) {4474} -> 0.667
[SupplyDepot, Barracks, Barracks, SupplyDepot, Refinery, SupplyDepot, Academy, SupplyDepot] (9) {3104.111} -> 0.778
[SupplyDepot, Barracks, Barracks, SupplyDepot, Bunker] (5) {1942.4} -> 0
[SupplyDepot, Barracks, Barracks, Refinery, SupplyDepot] (9) {3602.889} -> 0.556
[SupplyDepot, Barracks, SupplyDepot] (6) {2547.667} -> 0.167
[SupplyDepot, Barracks, Refinery, Barracks] (5) {3116.8} -> 0.8
[SupplyDepot, Barracks, Refinery, Factory] (7) {3942.571} -> 0.571
[SupplyDepot, Barracks, Refinery, SupplyDepot, Academy] (6) {2789} -> 0.5
[SupplyDepot, Barracks, Refinery, SupplyDepot, Factory] (5) {4065.2} -> 0.8
