[Pylon, Gateway, Gateway, Pylon, Gateway, Pylon, Pylon, Pylon] (11) {2254.545} -> 0.636
[Pylon, Gateway, Gateway, Pylon, Assimilator, Pylon] (12) {3224.333} -> 0.417
[Pylon, Gateway, Gateway, Pylon, Pylon, Gateway, Pylon, Assimilator] (9) {2533.111} -> 0.333
[Pylon, Gateway, Gateway, Pylon, Pylon, Gateway, Pylon, Pylon] (19) {3132.105} -> 0.526
[Pylon, Gateway, Gateway, Pylon, Pylon, Assimilator, CyberneticsCore] (9) {3309.556} -> 0.333
[Pylon, Gateway, Gateway, Pylon, Pylon, Pylon] (21) {4107.095} -> 0.571
[Pylon, Gateway, Assimilator, CyberneticsCore, Pylon, SingularityCharge, Gateway] (11) {4607.636} -> 0.545
[Pylon, Gateway, Assimilator, CyberneticsCore, Pylon, Gateway, SingularityCharge, Pylon] (11) {4014.273} -> 0.455
[Pylon, Gateway, Assimilator, Pylon, CyberneticsCore, Gateway] (10) {3669.1} -> 0.9
[Pylon, Gateway, Pylon, Gateway] (9) {7887} -> 0.222
[Pylon, Forge] (18) {4581.444} -> 0.556
