[Pylon, Gateway, Gateway, Pylon, Gateway, Pylon, Pylon, Pylon, Pylon] (8) {2012.769} -> 0.538
[Pylon, Gateway, Gateway, Pylon, Assimilator, Pylon] (6) {1645.167} -> 0
[Pylon, Gateway, Gateway, Pylon, Pylon, Gateway, Gateway, Pylon] (6) {1976} -> 0.143
[Pylon, Gateway, Gateway, Pylon, Pylon, Gateway, Pylon, Gateway, Pylon] (6) {2503.875} -> 0.25
[Pylon, Gateway, Gateway, Pylon, Pylon, Gateway, Pylon, Assimilator, Pylon, CyberneticsCore] (6) {2622.125} -> 0.25
[Pylon, Gateway, Gateway, Pylon, Pylon, Gateway, Pylon, Pylon, Gateway, Pylon, Pylon] (8) {2733} -> 0.4
[Pylon, Gateway, Gateway, Pylon, Pylon, Gateway, Pylon, Pylon, Assimilator, Pylon] (8) {2500.6} -> 0.7
[Pylon, Gateway, Gateway, Pylon, Pylon, Assimilator, CyberneticsCore, Pylon] (10) {2504.2} -> 0.4
[Pylon, Gateway, Gateway, Pylon, Pylon, Assimilator, Pylon, CyberneticsCore] (6) {5031.833} -> 0.667
[Pylon, Gateway, Gateway, Pylon, Pylon, Pylon, Gateway, Pylon] (8) {2011.875} -> 0.5
[Pylon, Gateway, Assimilator, CyberneticsCore] (6) {2075.333} -> 0.5
[Pylon, Gateway, Pylon, Gateway] (9) {9068.111} -> 0.333
[Pylon, Pylon] (6) {3568.667} -> 0.5
