[Pylon, Nexus, Gateway, Assimilator, Pylon] (4) {4918} -> 0.25
[Pylon, Gateway, Gateway, Pylon, Assimilator, CyberneticsCore] (4) {5073.5} -> 0
[Pylon, Gateway, Gateway, Pylon, Assimilator, Pylon, Pylon] (4) {4232.25} -> 0.25
[Pylon, Gateway, Gateway, Pylon, Forge, Pylon, PhotonCannon] (4) {2032} -> 0.75
[Pylon, Gateway, Gateway, Pylon, Pylon, Assimilator, CyberneticsCore] (4) {4402.5} -> 0.25
[Pylon, Gateway, Assimilator, CyberneticsCore, Pylon, SingularityCharge, Gateway, Pylon, Pylon] (4) {3596} -> 0.5
[Pylon, Gateway, Assimilator, CyberneticsCore, Pylon, SingularityCharge, Pylon, Gateway] (4) {2383.25} -> 0.5
[Pylon, Gateway, Assimilator, CyberneticsCore, Pylon, Gateway, SingularityCharge, Pylon, Pylon] (4) {3725.25} -> 0.5
[Pylon, Gateway, Assimilator, CyberneticsCore, Pylon, Gateway, Pylon, SingularityCharge] (4) {3438.5} -> 1
[Pylon, Gateway, Assimilator, CyberneticsCore, Pylon, CitadelofAdun] (4) {1672.75} -> 1
[Pylon, Gateway, Assimilator, Pylon, CyberneticsCore, Gateway, Pylon] (5) {3096.4} -> 1
[Pylon, Gateway, Pylon] (5) {3698.8} -> 0.2
