[Pylon, Gateway, Gateway, Pylon, Gateway, Pylon] (3) {3355.667} -> 0.667
[Pylon, Gateway, Gateway, Pylon, Assimilator, Pylon, CyberneticsCore] (3) {2682.333} -> 0.667
[Pylon, Gateway, Gateway, Pylon, Pylon, Gateway] (4) {3478} -> 0.5
[Pylon, Gateway, Gateway, Pylon, Pylon, Assimilator, Pylon] (3) {5513.667} -> 0.333
[Pylon, Gateway, Gateway, Pylon, Pylon, Forge] (3) {6555} -> 0.333
[Pylon, Gateway, Gateway, Pylon, Pylon, Pylon, Pylon] (5) {3111} -> 0.8
[Pylon, Gateway, Assimilator] (4) {3909.5} -> 0.25
[Pylon, Gateway, Forge, PhotonCannon] (3) {2911} -> 0.667
[Pylon, Gateway, Pylon, Gateway] (4) {2997.75} -> 0.25
[Pylon, Gateway, Pylon, Forge, Pylon] (3) {2541} -> 0.667
[Pylon, Forge, Gateway] (4) {7843.5} -> 1
[Pylon, Forge, PhotonCannon] (5) {2844.4} -> 0.6
[Pylon, Forge, Pylon, PhotonCannon, PhotonCannon] (3) {1958} -> 0.333
