[Pylon, Gateway, Assimilator, CyberneticsCore, Pylon, RoboticsFacility, SingularityCharge, Pylon] (3) {1312} -> 0.333
[Pylon, Gateway, Assimilator, CyberneticsCore, Pylon, RoboticsFacility, Pylon, SingularityCharge, Observatory, Pylon, Pylon] (3) {1894} -> 0.667
[Pylon, Gateway, Assimilator, CyberneticsCore, Pylon, RoboticsFacility, Pylon, Observatory, Pylon] (4) {3429.25} -> 1
[Pylon, Gateway, Assimilator, CyberneticsCore, Pylon, RoboticsFacility, Pylon, RoboticsSupportBay, Pylon] (3) {2057.667} -> 0.333
[Pylon, Gateway, Assimilator, CyberneticsCore, Pylon, RoboticsFacility, Pylon, Pylon, SingularityCharge] (3) {3250} -> 0.667
[Pylon, Gateway, Assimilator, CyberneticsCore, Pylon, Stargate, Pylon, RoboticsFacility, Pylon, Forge] (3) {3959.333} -> 0.667
[Pylon, Gateway, Assimilator, CyberneticsCore, Pylon, Stargate, Pylon, Pylon] (3) {2259.333} -> 0.333
[Pylon, Assimilator, Gateway, CyberneticsCore, Pylon, RoboticsFacility, Pylon, SingularityCharge, Observatory, Pylon] (3) {2550.667} -> 0.667
[Pylon, Assimilator, Gateway, CyberneticsCore, Pylon, RoboticsFacility, Pylon, Pylon, Observatory, SingularityCharge, Pylon, RoboticsSupportBay, Gateway, Gateway, Pylon] (4) {2892} -> 1
[Pylon, Assimilator, Gateway, CyberneticsCore, Pylon, Stargate, RoboticsFacility] (5) {2991} -> 1
[Pylon, Assimilator, Gateway, CyberneticsCore, Pylon, CitadelofAdun, RoboticsFacility] (4) {1438.75} -> 0.75
[Pylon, Assimilator, Gateway, Pylon, CyberneticsCore, RoboticsFacility] (4) {1732.25} -> 0
[Pylon, Assimilator, Gateway, Pylon, CyberneticsCore, Stargate, ProtossAirWeapons] (3) {3756.333} -> 0.667
