[Pylon, Gateway, Assimilator, CyberneticsCore, Pylon, RoboticsFacility, SingularityCharge, Pylon, Observatory, Pylon] (2) {1055.5} -> 0
[Pylon, Gateway, Assimilator, CyberneticsCore, Pylon, RoboticsFacility, Pylon, SingularityCharge, Observatory] (3) {2209.333} -> 1
[Pylon, Gateway, Assimilator, CyberneticsCore, Pylon, RoboticsFacility, Pylon, RoboticsSupportBay, Pylon, Pylon] (3) {1378.667} -> 0
[Pylon, Gateway, Assimilator, CyberneticsCore, Pylon, RoboticsFacility, Pylon, Pylon, Observatory] (3) {2364.333} -> 0.667
[Pylon, Gateway, Assimilator, CyberneticsCore, Pylon, RoboticsFacility, Pylon, Pylon, RoboticsSupportBay, Pylon] (2) {2002} -> 0.5
[Pylon, Gateway, Assimilator, CyberneticsCore, Pylon, SingularityCharge] (2) {2343} -> 0.5
[Pylon, Gateway, Assimilator, CyberneticsCore, Pylon, Pylon, RoboticsFacility] (2) {1790} -> 0.5
[Pylon, Assimilator, Gateway, CyberneticsCore, Pylon, RoboticsFacility, Pylon, SingularityCharge, Observatory, Pylon, Pylon] (2) {2278} -> 0
[Pylon, Assimilator, Gateway, CyberneticsCore, Pylon, RoboticsFacility, Pylon, RoboticsSupportBay] (2) {1726} -> 1
[Pylon, Assimilator, Gateway, CyberneticsCore, Pylon, RoboticsFacility, Pylon, Pylon, Observatory] (7) {2784.286} -> 1
[Pylon, Assimilator, Gateway, CyberneticsCore, Pylon, RoboticsFacility, Pylon, Pylon, RoboticsSupportBay] (2) {1648.5} -> 0.5
[Pylon, Assimilator, Gateway, CyberneticsCore, Pylon, CitadelofAdun] (2) {974} -> 1
[Pylon, Assimilator, Gateway, CyberneticsCore, Pylon, Pylon] (3) {1738.667} -> 0
[Pylon, Assimilator, Gateway, Pylon] (4) {1550.25} -> 0
