[Assimilator] (1) {5746} -> 0
[Pylon, Gateway, Assimilator, CyberneticsCore, Pylon, RoboticsFacility] (2) {2369} -> 0
[Pylon, Gateway, Assimilator, CyberneticsCore, Pylon, Stargate, Pylon, RoboticsFacility, Pylon, Forge, PhotonCannon, ProtossAirWeapons] (1) {2473} -> 1
[Pylon, Gateway, Assimilator, CyberneticsCore, Pylon, Stargate, Pylon, RoboticsFacility, Pylon, Forge, PhotonCannon, RoboticsSupportBay] (1) {6391} -> 0
[Pylon, Gateway, Assimilator, CyberneticsCore, Pylon, Stargate, Pylon, RoboticsFacility, Pylon, Forge, Pylon] (1) {3014} -> 1
[Pylon, Gateway, Assimilator, CyberneticsCore, Pylon, Stargate, Pylon, RoboticsFacility, Pylon, RoboticsSupportBay] (2) {2665} -> 1
[Pylon, Gateway, Assimilator, CyberneticsCore, Pylon, Stargate, Pylon, Pylon] (2) {2505} -> 0
[Pylon, Assimilator, Gateway, CyberneticsCore, Pylon, RoboticsFacility] (1) {2202} -> 0
[Pylon, Assimilator, Gateway, CyberneticsCore, Pylon, Stargate, ProtossAirWeapons] (1) {3778} -> 0
[Pylon, Assimilator, Gateway, CyberneticsCore, Pylon, Stargate, RoboticsFacility] (4) {2891.75} -> 1
[Pylon, Assimilator, Gateway, CyberneticsCore, Pylon, Stargate, Pylon] (2) {2252} -> 1
[Pylon, Assimilator, Gateway, Pylon, CyberneticsCore, Stargate, ProtossAirWeapons, RoboticsFacility] (1) {5141} -> 1
[Pylon, Assimilator, Gateway, Pylon, CyberneticsCore, Stargate, ProtossAirWeapons, Pylon, RoboticsFacility, Pylon, Forge, RoboticsSupportBay] (1) {2588} -> 0
[Pylon, Assimilator, Gateway, Pylon, CyberneticsCore, Stargate, ProtossAirWeapons, Pylon, RoboticsFacility, Pylon, Forge, Pylon] (1) {3540} -> 1
[Pylon, Assimilator, Gateway, Pylon, CyberneticsCore, Pylon] (1) {1198} -> 0
