[Extractor, SpawningPool, Hatchery, HydraliskDen, Spire] (1) {4531} -> 0
[Extractor, SpawningPool, Hatchery, HydraliskDen, VentralSacs] (1) {5882} -> 1
[Extractor, SpawningPool, Hatchery, Spire, VentralSacs, EvolutionChamber] (1) {2618} -> 0
[Extractor, SpawningPool, Hatchery, Spire, VentralSacs, MetabolicBoost] (1) {2737} -> 0
[Extractor, SpawningPool, Hatchery, Spire, VentralSacs, Hatchery] (1) {3991} -> 1
[SpawningPool] (2) {2641.5} -> 1
